Workbook

Sheet サマリ
A1: SWEBOK Guide v4.0a（固定参照版）・クラウドWell-Architected Framework参照・整合 開発レビューチェックリスト
A2: 更新: 2026-07-18 / SWEBOK参照版: v4.0a / .workspace/swebok-v4a.pdf (SHA-256: b3cb8028fecb9607f757504c861947fa3bf423087ea8bf08c58020f0ba3596dc)。全18KAとの関係と適用・除外理由は「KA対応表」を参照。WAFは規範的な一律要件ではなく、案件条件に基づき適用判定する。各レビューシートに適用／N/A、Pass／Fail、証跡、指摘、例外承認、再確認の実施記録列を追加。出典は「出典マスター」、運用は「利用ガイド」、追加承認65件は「追加項目管理」を参照。
A4: 領域 | B4: シート | C4: 対象ドキュメント | D4: 項目数（数式） | E4: Critical | F4: High | G4: Medium | H4: Low | I4: カバレッジ総評
A5: ソフトウェア要件定義 | B5: 01_要件定義 | C5: swebok-v4a.pdf ch01 Software Requirements | D5: =COUNTA('01_要件定義'!$A$2:$A$89) | E5: =COUNTIF('01_要件定義'!$D$2:$D$89,"Critical") | F5: =COUNTIF('01_要件定義'!$D$2:$D$89,"High") | G5: =COUNTIF('01_要件定義'!$D$2:$D$89,"Medium") | H5: =COUNTIF('01_要件定義'!$D$2:$D$89,"Low") | I5: チェックリストはSWEBOK v4 第1章の主要トピック(要求の分類、獲得、分析、仕様化、妥当性確認、管理、優先順位付け・トレーサビリティ・計測、ツール)をほぼ網羅しており、ISO 29148/25010による実務補完も適切。特に3.1の望ましい性質(曖昧性・テスト可能性・原子性等)と6章の管理活動(スクラビング・変更管理・スコープマッチング)のカバーが厚い。一方、3.4「要求間対立への対処」の解決プロセス記録、QoS制約間の相互関係・トレードオフ(1.5/3.2)、7.6「要求プロセスの品質と改善」が手薄であり、gap として補完を提案する。
A6: ソフトウェアアーキテクチャ設計 | B6: 02_アーキテクチャ | C6: swebok-v4a.pdf ch02 Software Architecture | D6: =COUNTA('02_アーキテクチャ'!$A$2:$A$83) | E6: =COUNTIF('02_アーキテクチャ'!$D$2:$D$83,"Critical") | F6: =COUNTIF('02_アーキテクチャ'!$D$2:$D$83,"High") | G6: =COUNTIF('02_アーキテクチャ'!$D$2:$D$83,"Medium") | H6: =COUNTIF('02_アーキテクチャ'!$D$2:$D$83,"Low") | I6: SWEBOK v4 第2章(Software Architecture)の4トピック(基礎/記述/プロセス/評価)を、10カテゴリ76項目でほぼ網羅的にカバーしている。特に2.4(重要決定・根拠・技術的負債)、2.1(ビュー/ビューポイント)、4章(評価・レビュー・メトリクス)への対応が厚く、実務補完(観測可能性、ライセンス、Docs as Code等)も適切に織り込まれている。一方、1.3の再利用・プロダクトライン、3.4のアーキテクチャ知識管理、3.1のライフサイクルコンテキスト(アジャイル等での創発的アーキテクチャのリスク)への対応がやや手薄である。
A7: ソフトウェア詳細設計 | B7: 03_詳細設計 | C7: swebok-v4a.pdf ch03 Software Design | D7: =COUNTA('03_詳細設計'!$A$2:$A$98) | E7: =COUNTIF('03_詳細設計'!$D$2:$D$98,"Critical") | F7: =COUNTIF('03_詳細設計'!$D$2:$D$98,"High") | G7: =COUNTIF('03_詳細設計'!$D$2:$D$98,"Medium") | H7: =COUNTIF('03_詳細設計'!$D$2:$D$98,"Low") | I7: SWEBOK v4 CHAPTER 03(Software Design)の主要トピックはおおむねカバーされている。特に設計原則(1.4)、詳細設計の対象(2.2)、設計品質特性(3.1〜3.8)、記録・根拠(4章)、レビューと評価(6章)に対応する項目が体系的に配置されている。一方、既製コンポーネント/フレームワーク再利用の検討(2.2/5.6)、セーフティ(3.7)、外部システムとの統合・相互運用性(3.6)、採用設計手法の明示(5章)がやや手薄である。API仕様・DB実務・Web UI 実務の項目は SWEBOK を実務標準で補完したものとして妥当である。
A8: ソフトウェア実装 | B8: 04_実装 | C8: swebok-v4a.pdf ch04 Software Construction | D8: =COUNTA('04_実装'!$A$2:$A$86) | E8: =COUNTIF('04_実装'!$D$2:$D$86,"Critical") | F8: =COUNTIF('04_実装'!$D$2:$D$86,"High") | G8: =COUNTIF('04_実装'!$D$2:$D$86,"Medium") | H8: =COUNTIF('04_実装'!$D$2:$D$86,"Low") | I8: SWEBOK v4 第4章の中核である構築の基礎(複雑性最小化・検証可能性・標準適用)、構築技術(エラー処理・防御的プログラミング・並行処理・API設計・性能)、管理(依存関係・統合・CI)、構築テストをコードレビュー実務の観点で幅広くカバーしており、実務補完(セキュアコーディング詳細、レビュー記録)も適切に組み込まれている。一方、2.3 構築の計測、3.5 再利用のための構築(可変性の実装・資産の文書化)、4.8 実行時コンフィギュレーションと国際化はチェック項目が手薄である。4.6〜4.7(実行可能モデル、状態ベース/テーブル駆動)や4.13(ヘテロジニアスシステム)は適用場面が限定的であり、汎用チェックリストからの除外は妥当と判断する。
A9: ソフトウェアテスト | B9: 05_テスト | C9: swebok-v4a.pdf ch05 Software Testing | D9: =COUNTA('05_テスト'!$A$2:$A$91) | E9: =COUNTIF('05_テスト'!$D$2:$D$91,"Critical") | F9: =COUNTIF('05_テスト'!$D$2:$D$91,"High") | G9: =COUNTIF('05_テスト'!$D$2:$D$91,"Medium") | H9: =COUNTIF('05_テスト'!$D$2:$D$91,"Low") | I9: チェックリストはSWEBOK v4 第5章の主要トピック(テストレベル、仕様/構造/経験ベース技法、テストプロセス、測定、完了判定)を計画〜報告のライフサイクル全体にわたり高い密度でカバーしており、フォールト/フェイラの区別やオラクル問題、テスト理論の限界といった基礎概念も項目に反映されている。一方、SWEBOKが独立トピックとして扱う利用ベース技法(運用プロファイルによる信頼性評価)、テスト容易性、適合・コンプライアンステスト、アルファ/ベータテスト、テストツール選定は既存項目で明示的にカバーされていない。自動テストコードのカテゴリはSWEBOK記述を超える実務補完だが、シフトレフト開発(6.1.2)の趣旨と整合している。
A10: ソフトウェア運用 | B10: 06_運用 | C10: swebok-v4a.pdf ch06 SE Operations | D10: =COUNTA('06_運用'!$A$2:$A$106) | E10: =COUNTIF('06_運用'!$D$2:$D$106,"Critical") | F10: =COUNTIF('06_運用'!$D$2:$D$106,"High") | G10: =COUNTIF('06_運用'!$D$2:$D$106,"Medium") | H10: =COUNTIF('06_運用'!$D$2:$D$106,"Low") | I10: SWEBOK v4 第6章(Software Engineering Operations)の3大プロセス(計画・デリバリー・統制)と実践的考慮事項・ツールをほぼ全域にわたりカバーしており、SLO/エラーバジェットや Runbook 具体性などSRE実務の補完も適切である。一方、運用計画の柱である財務管理・予算(2.1.1)、情報セキュリティリスクアセスメントとポリシー/教育(2.6)、承認外構成変更の検知(4.3)、継続的な運用リスク管理とリスク許容度の合意(5.2)が手薄であり、これらを補うことで章構成との対応が完全に近くなる。
A11: ソフトウェア保守 | B11: 07_保守 | C11: swebok-v4a.pdf ch07 Software Maintenance | D11: =COUNTA('07_保守'!$A$2:$A$87) | E11: =COUNTIF('07_保守'!$D$2:$D$87,"Critical") | F11: =COUNTIF('07_保守'!$D$2:$D$87,"High") | G11: =COUNTIF('07_保守'!$D$2:$D$87,"Medium") | H11: =COUNTIF('07_保守'!$D$2:$D$87,"Low") | I11: チェックリストは SWEBOK v4 第7章の主要トピック(保守区分、影響分析、保守性・技術的負債、リファクタリング/リエンジニアリング、テスト、SCM、供給者管理・SLA、測定、プロセス、プログラム理解)をほぼ網羅しており、EOL・移行・廃棄など ISO/IEC/IEEE 14764 の Disposal 側も実務的に補完している。一方、章が明示する「保守区分別のコスト/工数傾向分析」「リリース/バージョン計画の利用者合意・競合調整」「継続的デリバリー/デプロイの自動化」「稼働ソフトウェアのサーベイランス(容量・継続性・可用性)」はやや手薄である。全体として SWEBOK 準拠度は高く、追加提案は4件にとどまる。
A12: ソフトウェア構成管理 | B12: 08_構成管理 | C12: swebok-v4a.pdf ch08 Software Configuration Management | D12: =COUNTA('08_構成管理'!$A$2:$A$97) | E12: =COUNTIF('08_構成管理'!$D$2:$D$97,"Critical") | F12: =COUNTIF('08_構成管理'!$D$2:$D$97,"High") | G12: =COUNTIF('08_構成管理'!$D$2:$D$97,"Medium") | H12: =COUNTIF('08_構成管理'!$D$2:$D$97,"Low") | I12: SWEBOK v4 第8章の6大トピック(SCMプロセス管理、構成識別、変更管理、状況記録、構成監査、リリース管理・配布)とツール(7節)をすべてカバーし、ブランチ戦略・バージョニング・CI/CDといった実務領域も8-1.3/8-2.3/8-6.1由来として体系的に展開している。デビエーション/ウェーバー、FCA/PCA、SBOMなど形式的な要素も漏れなく項目化されており、章構成に対するカバレッジは高い。一方、ソフトウェアライブラリのバックアップ・復旧(2.6節)、リリース配布先の追跡(6.2節)、ツール移行性(1.3.3節)の3点が手薄であり、gapsとして補完を提案する。
A13: SEマネジメント | B13: 09_マネジメント | C13: swebok-v4a.pdf ch09 SE Management | D13: =COUNTA('09_マネジメント'!$A$2:$A$94) | E13: =COUNTIF('09_マネジメント'!$D$2:$D$94,"Critical") | F13: =COUNTIF('09_マネジメント'!$D$2:$D$94,"High") | G13: =COUNTIF('09_マネジメント'!$D$2:$D$94,"Medium") | H13: =COUNTIF('09_マネジメント'!$D$2:$D$94,"Low") | I13: SWEBOK v4 第9章(Software Engineering Management)の7トピック(開始と適用範囲の定義、計画、実行、レビューと評価、終結、測定、ツール)を、チェックリストの14カテゴリでほぼ網羅している。特に計画(SDLC選定・見積り・リスク・品質)と監視統制・測定(15939準拠)の対応が厚い。一方、1.1「要求の決定と交渉」の実施確認、リスクの機会(ポジティブリスク)側面、4.2の要員パフォーマンスレビュー、6.1の測定コミットメント(資源・責任)、3.2の契約形態・知財条項が手薄であり、gapsとして補完を提案する。
A14: SEプロセス | B14: 10_プロセス | C14: swebok-v4a.pdf ch10 SE Process | D14: =COUNTA('10_プロセス'!$A$2:$A$96) | E14: =COUNTIF('10_プロセス'!$D$2:$D$96,"Critical") | F14: =COUNTIF('10_プロセス'!$D$2:$D$96,"High") | G14: =COUNTIF('10_プロセス'!$D$2:$D$96,"Medium") | H14: =COUNTIF('10_プロセス'!$D$2:$D$96,"Low") | I14: チェックリストはSWEBOK v4 第10章の主要トピック(プロセス定義の3要素と統制・実現メカニズム、ライフサイクルモデルの類型と選定根拠、12207の4プロセスカテゴリ、テーラリング、GQMベースの計測、モニタリング、PDCA/フレームワークベースのアセスメントと改善、レトロスペクティブ、プロセスインフラ・ツール統合)をほぼ網羅している。特に2.4〜2.5のライフサイクルパラダイムとアジャイルの誤解、2.8のテーラリング、3章のアセスメント・改善は手厚い。一方、2.9が明言する「測定・見積もりの精度と不確実性レベルの定義」、2.5の大規模アジャイル適用の難しさ、2.6の段階間遷移の仕様化はやや手薄であり、gapとして補完を提案する。
A15: ソフトウェア品質保証 | B15: 12_品質保証 | C15: swebok-v4a.pdf ch12 Software Quality | D15: =COUNTA('12_品質保証'!$A$2:$A$92) | E15: =COUNTIF('12_品質保証'!$D$2:$D$92,"Critical") | F15: =COUNTIF('12_品質保証'!$D$2:$D$92,"High") | G15: =COUNTIF('12_品質保証'!$D$2:$D$92,"Medium") | H15: =COUNTIF('12_品質保証'!$D$2:$D$92,"Low") | I15: チェックリストはSWEBOK v4 第12章の主要構成(品質基礎、品質コスト、標準・インテグリティレベル、SQM計画/SQAP、品質測定、プロセス保証・プロダクト保証、V&V、レビュー/監査、欠陥分析・CAPA、ツール)をほぼ網羅しており、品質ゲート(第7カテゴリ)はSWEBOKのマイルストーン評価・技術レビュー群を実務向けに具体化した妥当な補完である。一方、SQAPが明示的に扱うべきとされる供給者/COTS調達ソフトへの品質保証、QMS運営の前提となる経営層のコミットメント、安全ハザード分析(FMEA/FTA)、V&Vを支える成果物間トレーサビリティの4点が手薄であり、gapとして追加を提案する。全体としてカバレッジは高く、既存項目の粒度・判定基準も客観的で実用に耐える。
A16: ソフトウェアセキュリティ | B16: 13_セキュリティ | C16: swebok-v4a.pdf ch13 Software Security | D16: =COUNTA('13_セキュリティ'!$A$2:$A$105) | E16: =COUNTIF('13_セキュリティ'!$D$2:$D$105,"Critical") | F16: =COUNTIF('13_セキュリティ'!$D$2:$D$105,"High") | G16: =COUNTIF('13_セキュリティ'!$D$2:$D$105,"Medium") | H16: =COUNTIF('13_セキュリティ'!$D$2:$D$105,"Low") | I16: チェックリストはSWEBOK v4 第13章の主要トピック(セキュリティ要件・設計・構築・テスト・脆弱性管理・ツール・ドメイン固有・マネジメント)をほぼ網羅し、特に4章(Security Engineering for Software Systems)と6章(Domain-Specific)は密度高くカバーしている。CERT Top 10やCVE/CWE/CVSS、ISMS、SSE-CMM、アジャイルプラクティスなど章内の具体的言及にも対応項目がある。一方、3.2 Common Criteria(ISO/IEC 15408)によるセキュリティ評価、1.3 サイバーセキュリティのソーシャルエンジニアリング系脅威、4.2 の攻撃許容(被害限定・安全な復旧)の観点は手薄である。全体としてSWEBOK準拠度は高く、OWASP ASVS/Top 10等の実務標準による補完も適切である。
A17: クラウド共通 | B17: 14_クラウド | C17: 各社Well-Architected系フレームワーク共通 | D17: =COUNTA('14_クラウド'!$A$2:$A$67) | E17: =COUNTIF('14_クラウド'!$D$2:$D$67,"Critical") | F17: =COUNTIF('14_クラウド'!$D$2:$D$67,"High") | G17: =COUNTIF('14_クラウド'!$D$2:$D$67,"Medium") | H17: =COUNTIF('14_クラウド'!$D$2:$D$67,"Low") | I17: 4フレームワークのcommonThemes計131件を意味的に統合し、信頼性・セキュリティ・コスト最適化・運用・パフォーマンス・持続可能性/ガバナンスの6カテゴリ64項目に集約した。IAM最小権限・マルチゾーン冗長・IaC・暗号化・タグ付けなど4FW共通の中核概念は1項目に統合し出典を併記、FMA・SLO/エラーバジェット・責任共有モデル等の特定FW固有の優良観点も漏れなく採録した。重要度は統合元の最高値を採用しており、131件すべてがいずれかの項目に対応付いている。
A18: AWS | B18: 15_AWS | C18: AWS Well-Architected Framework(+ Generative AI Lens) | D18: =COUNTA('15_AWS'!$A$2:$A$130) | E18: =COUNTIF('15_AWS'!$D$2:$D$130,"Critical") | F18: =COUNTIF('15_AWS'!$D$2:$D$130,"High") | G18: =COUNTIF('15_AWS'!$D$2:$D$130,"Medium") | H18: =COUNTIF('15_AWS'!$D$2:$D$130,"Low")
A19: Google Cloud | B19: 16_GoogleCloud | C19: Google Cloud Well-Architected Framework(+ Architecture Center AI & ML) | D19: =COUNTA('16_GoogleCloud'!$A$2:$A$123) | E19: =COUNTIF('16_GoogleCloud'!$D$2:$D$123,"Critical") | F19: =COUNTIF('16_GoogleCloud'!$D$2:$D$123,"High") | G19: =COUNTIF('16_GoogleCloud'!$D$2:$D$123,"Medium") | H19: =COUNTIF('16_GoogleCloud'!$D$2:$D$123,"Low")
A20: Azure | B20: 17_Azure | C20: Azure Well-Architected Framework(+ AI workloads) | D20: =COUNTA('17_Azure'!$A$2:$A$152) | E20: =COUNTIF('17_Azure'!$D$2:$D$152,"Critical") | F20: =COUNTIF('17_Azure'!$D$2:$D$152,"High") | G20: =COUNTIF('17_Azure'!$D$2:$D$152,"Medium") | H20: =COUNTIF('17_Azure'!$D$2:$D$152,"Low")
A21: OCI | B21: 18_OCI | C21: OCI Well-Architected Framework | D21: =COUNTA('18_OCI'!$A$2:$A$81) | E21: =COUNTIF('18_OCI'!$D$2:$D$81,"Critical") | F21: =COUNTIF('18_OCI'!$D$2:$D$81,"High") | G21: =COUNTIF('18_OCI'!$D$2:$D$81,"Medium") | H21: =COUNTIF('18_OCI'!$D$2:$D$81,"Low")
A22: AI(共通) | B22: 19_AI | C22: AWS GenAI Lens / Azure WAF AI workloads / Google Cloud AI&ML 横断 | D22: =COUNTA('19_AI'!$A$2:$A$81) | E22: =COUNTIF('19_AI'!$D$2:$D$81,"Critical") | F22: =COUNTIF('19_AI'!$D$2:$D$81,"High") | G22: =COUNTIF('19_AI'!$D$2:$D$81,"Medium") | H22: =COUNTIF('19_AI'!$D$2:$D$81,"Low") | I22: 3フレームワークの commonThemes 81件を意味的に統合し、AIライフサイクル(企画→データ→モデル→評価→デプロイ→運用→改善)と横断関心(セキュリティ、責任あるAI、信頼性、コスト)を10カテゴリ51項目に再構成した。プロンプトインジェクション・ガードレール・モデル評価基準・ドリフト監視・推論コスト管理など3社共通の中核テーマは1項目に統合し全出典を併記、単一フレームワーク由来の固有観点(セキュリティトリミング、チェックポイント戦略、サステナビリティ等)も漏れなく採録した。重要度は統合元の最高値を採用しており、生成AI・従来型MLの双方に適用可能なベンダー中立チェックリストとして網羅性は高い。
A23: 合計 | D23: =SUM(D5:D22) | E23: =SUM(E5:E22) | F23: =SUM(F5:F22) | G23: =SUM(G5:G22) | H23: =SUM(H5:H22) | I23: 件数は基準重要度の集計。案件重要度・判定結果は各レビュー実施時に記録する。

Sheet 利用ガイド
A1: 利用ガイド — 適用、判定、重複統制、リリースゲート
A3: 位置づけ | B3: SWEBOK Guide v4.0aと各社Well-Architected Frameworkを参照・整合させたレビュー観点マスター兼実施記録。規格認証や全SWEBOK KAへの完全準拠を表明するものではない。
A4: SWEBOK参照版 | B4: ローカルの .workspace/swebok-v4a.pdf を固定参照版とする（SHA-256: b3cb8028fecb9607f757504c861947fa3bf423087ea8bf08c58020f0ba3596dc）。PDF本体は再配布しない。
A5: SWEBOK対象範囲 | B5: 全18 KAを対応付ける。KA 1〜10・12・13は直接参照、KA 11・14・15は部分整合、KA 16〜18は前提知識として理由付き対象外。詳細は「KA対応表」を参照。
A6: WAFの扱い | B6: WAFは設計判断・リスク・トレードオフを評価する助言資料。各項目は案件のSLO、RTO/RPO、規制、データ分類、費用制約を入力に適用判定する。
A8: 適用プロファイル
A9: プロファイル | B9: 適用順 | C9: 対象 | D9: 利用シート | E9: 重複時の扱い
A10: CORE | B10: 1 | C10: 原則全案件 | D10: 01〜10、12、13 | E10: まず評価する
A11: CLOUD-COMMON | B11: 2 | C11: クラウド利用案件 | D11: 14_クラウド | E11: Coreの証跡を再利用可
A12: AWS/GCP/AZURE/OCI-DELTA | B12: 3 | C12: 採用ベンダーのみ | D12: 15〜18の該当1シート | E12: 共通で未評価の固有差分を追加
A13: AI-CONDITIONAL | B13: 4 | C13: AI/ML利用案件 | D13: 19_AI | E13: 従来ML・生成AI・Agenticの種別でN/A判断
A15: レビュー実施手順
A16: 1. 適用プロファイルを選び、各行の「適用判定」を適用／N/Aで記録する。N/Aは「証跡・参照箇所」に根拠を残す。
A17: 2. 基準重要度を助言値として、案件の重要度・データ分類・規制・SLOを反映した「案件重要度」と判断根拠を設定する。
A18: 3. Pass／Fail／未確認を記録し、Passは証跡、Failは指摘・Issue ID、対応方針、是正期限、担当情報を残す。
A19: 4. N/Aにもレビュアーと日付を残す。Fail是正後は明示的な再確認記録によりPassを確認し、変更履歴を保持する。
A21: 重要度とゲート
A22: 区分 | B22: 定義 | C22: 運用
A23: 基準重要度 | B23: 観点が一般に持つ潜在影響。マスター側の初期値。 | C23: 案件固有のリリース判定を単独では決めない。
A24: 案件重要度 | B24: 対象システムの重要度、規制、データ、SLO、露出度を反映した実行時評価。 | C24: レビュー責任者が根拠とともに設定する。
A25: 案件Critical | B25: 適用かつ未解決のFailが重大事故・法令違反・受入不能へ直結する。 | C25: 原則リリース停止。例外は記名承認と期限付きリスク受容が必要。
A27: 重複統制ルール
A28: • 同じリスクがCore、Cloud Common、ベンダー、AIに現れる場合、先に実施した証跡を再利用してよい。
A29: • 共通統制で十分に評価済みのベンダー行はN/Aとし、「証跡・参照箇所」に評価済みIDを記載する。ベンダー固有差分がある場合だけ別判定する。
A30: • 同じ根本リスクは同一のIssue IDを使用し、件数・リスク集計ではIssue IDを一意に数える。行数の合算をリスク件数にしない。
A31: • 「重複統制グループ」は候補を機械付与した補助情報。最終的な同一統制判断は証跡・対象資産・要求を確認して行う。
A33: 追加承認の移行注意
A34: 旧ブックで「追加承認」とされた65件は「追加項目管理」へ全件接続した。ただし旧ブックには承認者・承認日の原記録がないため、状態を「要原記録確認」としている。利用開始前に実在する承認記録で補完し、未確認のまま承認済みと扱わない。

Sheet 出典マスター
A1: 出典マスター
A3: Source ID | B3: 正式名称 | C3: 版・公開日 | D3: URL | E3: 参照日 | F3: 適用範囲 | G3: 変更確認日 | H3: 前版との差分 | I3: 固定参照物 | J3: 注記
A4: SRC-SWEBOK-V4A | B4: Guide to the Software Engineering Body of Knowledge (SWEBOK Guide) v4.0a | C4: v4.0a / 2025-09（ローカル固定参照版） | D4: https://www.computer.org/education/bodies-of-knowledge/software-engineering | E4: 46221 | F4: 全18KAを対応付け、KA 1〜10・12・13を直接参照、KA 11・14・15を部分整合、KA 16〜18を理由付き対象外とする。 | G4: 46221 | H4: v4.0から2025年9月の軽微改訂版v4.0aへ更新。完全準拠ではなく対象範囲を明示した参照・整合へ位置付けを修正。 | I4: .workspace/swebok-v4a.pdf / SHA-256 b3cb8028fecb9607f757504c861947fa3bf423087ea8bf08c58020f0ba3596dc | J4: 添付物の同一性だけを固定し、PDF本体は再配布しない。
A5: SRC-AWS-WAF | B5: AWS Well-Architected Framework | C5: 継続更新 | D5: https://docs.aws.amazon.com/wellarchitected/latest/framework/welcome.html | E5: 46221 | F5: AWSおよびクラウド共通 | G5: 46221 | H5: 前回登録内容から適用範囲・版の変更なし。 | J5: 継続更新型資料は変更確認日に再確認する。
A6: SRC-AWS-GENAI | B6: AWS Well-Architected Generative AI Lens | C6: 継続更新 | D6: https://docs.aws.amazon.com/wellarchitected/latest/generative-ai-lens/generative-ai-lens.html | E6: 46221 | F6: 生成AI | G6: 46221 | H6: 2025年11月19日公開の現行Generative AI Lensを生成AI用途へ対応付け。 | J6: 継続更新型資料は変更確認日に再確認する。
A7: SRC-AWS-RAI | B7: AWS Well-Architected Responsible AI Lens | C7: 2025-11-19 | D7: https://docs.aws.amazon.com/wellarchitected/latest/responsible-ai-lens/responsible-ai-lens.html | E7: 46221 | F7: 責任あるAI | G7: 46221 | H7: 2025年11月19日公開のResponsible AI Lensを追加し、案件固有の考慮事項として扱う。 | J7: 継続更新型資料は変更確認日に再確認する。
A8: SRC-AWS-ML | B8: AWS Well-Architected Machine Learning Lens | C8: 2025-11-19 | D8: https://docs.aws.amazon.com/wellarchitected/latest/machine-learning-lens/machine-learning-lens.html | E8: 46221 | F8: 従来型MLを含むML全般 | G8: 46221 | H8: 2025年11月19日公開のMachine Learning Lensを従来型ML用途へ追加。 | J8: 継続更新型資料は変更確認日に再確認する。
A9: SRC-AWS-AGENTIC | B9: AWS Well-Architected Agentic AI Lens | C9: 2026-06-10 | D9: https://docs.aws.amazon.com/wellarchitected/latest/agentic-ai-lens/agentic-ai-lens.html | E9: 46221 | F9: エージェントAI | G9: 46221 | H9: 2026年6月10日公開のAgentic AI Lensを追加し、自律性・追跡・監督の統制へ対応付け。 | J9: 継続更新型資料は変更確認日に再確認する。
A10: SRC-GCP-WAF | B10: Google Cloud Well-Architected Framework | C10: 継続更新 | D10: https://cloud.google.com/architecture/framework | E10: 46221 | F10: Google Cloudおよびクラウド共通 | G10: 46221 | H10: 前回登録内容から適用範囲・版の変更なし。 | J10: 継続更新型資料は変更確認日に再確認する。
A11: SRC-GCP-AIML | B11: Google Cloud Well-Architected Framework: AI and ML perspective | C11: 2024-10-11 review | D11: https://cloud.google.com/architecture/framework/perspectives/ai-ml | E11: 46221 | F11: AI/ML | G11: 46221 | H11: AI/ML perspectiveを一般WAFから分離してAI条件付きプロファイルへ対応付け。 | J11: 継続更新型資料は変更確認日に再確認する。
A12: SRC-AZR-WAF | B12: Microsoft Azure Well-Architected Framework | C12: 継続更新 | D12: https://learn.microsoft.com/en-us/azure/well-architected/ | E12: 46221 | F12: Azureおよびクラウド共通 | G12: 46221 | H12: 前回登録内容から適用範囲・版の変更なし。 | J12: 継続更新型資料は変更確認日に再確認する。
A13: SRC-AZR-AI | B13: AI Workload Documentation - Azure Well-Architected Framework | C13: 継続更新 | D13: https://learn.microsoft.com/en-us/azure/well-architected/ai/ | E13: 46221 | F13: Azure AI/ML | G13: 46221 | H13: Azure AI Workload資料を一般WAFから分離してAI条件付きプロファイルへ対応付け。 | J13: 継続更新型資料は変更確認日に再確認する。
A14: SRC-OCI-WAF | B14: Well-architected framework for Oracle Cloud Infrastructure | C14: F29550-09 / 2025-05 | D14: https://docs.oracle.com/en/solutions/oci-best-practices/toc.htm | E14: 46221 | F14: OCIおよびクラウド共通 | G14: 46221 | H14: 前回登録内容から適用範囲・版の変更なし。 | J14: 継続更新型資料は変更確認日に再確認する。
A15: SRC-ISO-29148 | B15: ISO/IEC/IEEE 29148 Systems and software engineering — Life cycle processes — Requirements engineering | C15: 参照記載版 | D15: https://www.iso.org/standard/72089.html | E15: 46221 | F15: 要求工学の実務補完 | G15: 46221 | H15: 前回登録内容から適用範囲・版の変更なし。 | J15: 継続更新型資料は変更確認日に再確認する。
A16: SRC-ISO-25010 | B16: ISO/IEC 25010 Systems and software Quality Requirements and Evaluation | C16: 参照記載版 | D16: https://www.iso.org/standard/78176.html | E16: 46221 | F16: 品質モデルの実務補完 | G16: 46221 | H16: 前回登録内容から適用範囲・版の変更なし。 | J16: 継続更新型資料は変更確認日に再確認する。
... A25: SRC-IEEE-GENERAL | B25: IEEE standards and guidance（項目の参照箇所に規格番号を記載） | C25: 各参照記載版 | D25: https://standards.ieee.org/ | E25: 46221 | F25: その他IEEE参照 | G25: 46221 | H25: 前回登録内容から適用範囲・版の変更なし。 | J25: 継続更新型資料は変更確認日に再確認する。
A26: SRC-PRACTICE | B26: 組織・案件固有の実務補完 | C26: 案件ごとに根拠を登録 | E26: 46221 | F26: 外部規範ではない。証跡欄に組織標準・意思決定記録を添付する。 | G26: 46221 | H26: 前回登録内容から適用範囲・版の変更なし。 | J26: 継続更新型資料は変更確認日に再確認する。

Sheet KA対応表
A1: SWEBOK v4.0a Knowledge Area 対応表
A3: KA | B3: Knowledge Area | C3: 扱い | D3: 対応シート | E3: 適用範囲・除外根拠 | F3: 主な証跡 | G3: 備考
A4: 1 | B4: Software Requirements | C4: 直接参照 | D4: 01_要件定義 | E4: レビュー対象 | F4: 要求仕様・トレーサビリティ
A5: 2 | B5: Software Architecture | C5: 直接参照 | D5: 02_アーキテクチャ | E5: レビュー対象 | F5: アーキテクチャ記述・意思決定
A6: 3 | B6: Software Design | C6: 直接参照 | D6: 03_詳細設計 | E6: レビュー対象 | F6: 詳細設計・API/DB/UI設計
A7: 4 | B7: Software Construction | C7: 直接参照 | D7: 04_実装 | E7: レビュー対象 | F7: コード・実装規約・ビルド
A8: 5 | B8: Software Testing | C8: 直接参照 | D8: 05_テスト | E8: レビュー対象 | F8: テスト計画・設計・結果
A9: 6 | B9: Software Engineering Operations | C9: 直接参照 | D9: 06_運用 | E9: レビュー対象 | F9: 運用設計・Runbook・SLO
A10: 7 | B10: Software Maintenance | C10: 直接参照 | D10: 07_保守 | E10: レビュー対象 | F10: 保守計画・変更・廃止
A11: 8 | B11: Software Configuration Management | C11: 直接参照 | D11: 08_構成管理 | E11: レビュー対象 | F11: 構成識別・変更・リリース
A12: 9 | B12: Software Engineering Management | C12: 直接参照 | D12: 09_マネジメント | E12: レビュー対象 | F12: 計画・見積・リスク・測定
A13: 10 | B13: Software Engineering Process | C13: 直接参照 | D13: 10_プロセス | E13: レビュー対象 | F13: プロセス定義・評価・改善
A14: 11 | B14: Software Engineering Models and Methods | C14: 部分整合（独立シートなし） | D14: 02/03/05/10/12 | E14: モデル・形式手法・レビュー方法を各工程で条件付き評価。方法論全体の網羅は対象外。 | F14: モデル、分析・レビュー記録 | G14: 独立KA準拠は表明しない
A15: 12 | B15: Software Quality | C15: 直接参照 | D15: 12_品質保証 | E15: レビュー対象 | F15: 品質計画・保証・測定
A16: 13 | B16: Software Security | C16: 直接参照 | D16: 13_セキュリティ | E16: レビュー対象 | F16: 脅威モデル・セキュリティ設計/試験
A17: 14 | B17: Software Engineering Professional Practice | C17: 部分整合（独立シートなし） | D17: 01/09/10/12/19 | E17: コミュニケーション、倫理、責任あるAIの成果物化された部分のみ。専門職実践全体は対象外。 | F17: 合意記録・役割・倫理審査 | G17: 独立KA準拠は表明しない
A18: 15 | B18: Software Engineering Economics | C18: 部分整合（独立シートなし） | D18: 09/14〜19 | E18: 見積、投資、クラウド/AIコスト、トレードオフのみ。経済学体系全体は対象外。 | F18: Business case・TCO・予算 | G18: 独立KA準拠は表明しない
A19: 16 | B19: Computing Foundations | C19: 対象外（前提知識） | D19: — | E19: 個別成果物レビューではなく実務者の基礎知識。必要な技術事項は各工程で評価。 | F19: — | G19: 適用除外
A20: 17 | B20: Mathematical Foundations | C20: 対象外（前提知識） | D20: — | E20: 個別成果物レビューではなく基礎知識。安全・形式検証案件では条件付きで方法を評価。 | F20: — | G20: 適用除外
A21: 18 | B21: Engineering Foundations | C21: 対象外（前提知識） | D21: — | E21: 個別成果物レビューではなく工学基礎。安全・規制領域は案件プロファイルで補完。 | F21: — | G21: 適用除外

Sheet 追加項目管理
A1: 追加承認項目の由来・承認記録
A3: 追加ID | B3: シート | C3: 追加理由／不足トピック | D3: 追加チェック項目 | E3: 根拠資料 | F3: 出典ID | G3: 承認状態 | H3: 承認者 | I3: 承認日 | J3: 変更理由 | K3: 注記
A4: REQ-901 | B4: 01_要件定義 | C4: 旧ブックで追加承認として登録（カテゴリ: 10. 妥当性確認(SWEBOK 5.1〜5.3)） | D4: 要求レビューが実施され記録がある | E4: swebok-v4a.pdf ch01 Software Requirements > 5.1 Requirements Reviews | F4: SRC-SWEBOK-V4A | G4: 要原記録確認 | H4: 未記録 | I4: 未記録 | J4: 旧ブックに追加理由・原承認記録なし。原記録の確認が必要。 | K4: 旧ブックの「追加承認」表記を移行。承認者・日付を推測で補完しない。
A5: REQ-902 | B5: 01_要件定義 | C5: 旧ブックで追加承認として登録（カテゴリ: 10. 妥当性確認(SWEBOK 5.1〜5.3)） | D5: レビューが複数視点で行われている | E5: swebok-v4a.pdf ch01 Software Requirements > 5.1 Requirements Reviews(review from multiple perspectives) | F5: SRC-SWEBOK-V4A | G5: 要原記録確認 | H5: 未記録 | I5: 未記録 | J5: 旧ブックに追加理由・原承認記録なし。原記録の確認が必要。 | K5: 旧ブックの「追加承認」表記を移行。承認者・日付を推測で補完しない。
A6: REQ-903 | B6: 01_要件定義 | C6: 旧ブックで追加承認として登録（カテゴリ: 10. 妥当性確認(SWEBOK 5.1〜5.3)） | D6: Critical/High 指摘がクローズされている | E6: swebok-v4a.pdf ch01 Software Requirements > 5.1 Requirements Reviews / 実務補完(レビュープロセス実務) | F6: SRC-SWEBOK-V4A;SRC-PRACTICE | G6: 要原記録確認 | H6: 未記録 | I6: 未記録 | J6: 旧ブックに追加理由・原承認記録なし。原記録の確認が必要。 | K6: 旧ブックの「追加承認」表記を移行。承認者・日付を推測で補完しない。
A7: REQ-904 | B7: 01_要件定義 | C7: 旧ブックで追加承認として登録（カテゴリ: 10. 妥当性確認(SWEBOK 5.1〜5.3)） | D7: 主要ステークホルダーの承認記録がある | E7: swebok-v4a.pdf ch01 Software Requirements > 1.11 Software Requirements Activities(reaching an agreement)/ 5. Requirements Validation | F7: SRC-SWEBOK-V4A | G7: 要原記録確認 | H7: 未記録 | I7: 未記録 | J7: 旧ブックに追加理由・原承認記録なし。原記録の確認が必要。 | K7: 旧ブックの「追加承認」表記を移行。承認者・日付を推測で補完しない。
A8: REQ-905 | B8: 01_要件定義 | C8: 旧ブックで追加承認として登録（カテゴリ: 10. 妥当性確認(SWEBOK 5.1〜5.3)） | D8: 誤解リスクの高い箇所にプロトタイプ等の確認が行われている | E8: swebok-v4a.pdf ch01 Software Requirements > 5.2 Simulation and Execution / 5.3 Prototyping | F8: SRC-SWEBOK-V4A | G8: 要原記録確認 | H8: 未記録 | I8: 未記録 | J8: 旧ブックに追加理由・原承認記録なし。原記録の確認が必要。 | K8: 旧ブックの「追加承認」表記を移行。承認者・日付を推測で補完しない。
A9: REQ-906 | B9: 01_要件定義 | C9: 旧ブックで追加承認として登録（カテゴリ: 10. 妥当性確認(SWEBOK 5.1〜5.3)） | D9: プロトタイプ確認の論点が事前定義されていた | E9: swebok-v4a.pdf ch01 Software Requirements > 5.3 Prototyping(cosmetic issues への警告) | F9: SRC-SWEBOK-V4A | G9: 要原記録確認 | H9: 未記録 | I9: 未記録 | J9: 旧ブックに追加理由・原承認記録なし。原記録の確認が必要。 | K9: 旧ブックの「追加承認」表記を移行。承認者・日付を推測で補完しない。
A10: REQ-9901 | B10: 01_要件定義 | C10: 3.4 Addressing Conflict in Requirements(要求間対立の識別と解決) | D10: ステークホルダー間で対立した要求について、解決の経緯と合意記録がある | E10: swebok-v4a.pdf ch01 Software Requirements > 3.4 Addressing Conflict in Requirements(要求間対立の識別と解決) | F10: SRC-SWEBOK-V4A | G10: 要原記録確認 | H10: 未記録 | I10: 未記録 | J10: REQ-201は矛盾の不在を検査するが、SWEBOK 3.4はさらに、対立発見時にエンジニアが単独裁定せずステークホルダー間で交渉して合意し、契約上その決定を顧客まで遡れる形で記録することを求める。解決記録がないと同じ対立が蒸し返され、独断解決が後の紛争になる。 | K10: 旧ブックの「追加承認」表記を移行。承認者・日付を推測で補完しない。
A11: REQ-9902 | B11: 01_要件定義 | C11: 1.5 / 3.2 QoS制約間の相互関係・トレードオフ | D11: QoS制約間のトレードオフ(相互に負の影響を与える組)が検討されている | E11: swebok-v4a.pdf ch01 Software Requirements > 1.5 / 3.2 QoS制約間の相互関係・トレードオフ | F11: SRC-SWEBOK-V4A | G11: 要原記録確認 | H11: 未記録 | I11: 未記録 | J11: SWEBOKは非機能要求の変更時に他への影響を必ず考慮すべきとし、QoS制約間の正負の関係(例: 速度最適化は保守性を下げる)への注意を明示する。個々の数値が妥当でも、組合せとして同時達成不能な非機能要求集合を合意してしまう事故を既存項目は検出できない。 | K11: 旧ブックの「追加承認」表記を移行。承認者・日付を推測で補完しない。
A12: REQ-9903 | B12: 01_要件定義 | C12: 7.6 Requirements Process Quality and Improvement(要求プロセスの品質と改善) | D12: 要求プロセス自体の振り返り・改善の仕組みがある | E12: swebok-v4a.pdf ch01 Software Requirements > 7.6 Requirements Process Quality and Improvement(要求プロセスの品質と改善) | F12: SRC-SWEBOK-V4A | G12: 要原記録確認 | H12: 未記録 | I12: 未記録 | J12: SWEBOK 7.6は要求プロセス自体の計測・ベンチマーク・改善計画を独立トピックとして扱うが、チェックリストは成果物の品質のみを対象とし、プロセスの振り返り・改善の観点が欠けている。プロセス起因の欠陥(獲得不足の常態化等)は成果物検査だけでは再発し続ける。 | K12: 旧ブックの「追加承認」表記を移行。承認者・日付を推測で補完しない。
A13: REQ-9904 | B13: 01_要件定義 | C13: 3.3 Formal Analysis(高インテグリティシステムでの形式的分析) | D13: 高インテグリティ要求に対して形式的仕様・分析の適用が検討されている(該当案件のみ) | E13: swebok-v4a.pdf ch01 Software Requirements > 3.3 Formal Analysis(高インテグリティシステムでの形式的分析) | F13: SRC-SWEBOK-V4A | G13: 要原記録確認 | H13: 未記録 | I13: 未記録 | J13: SWEBOKは高インテグリティ領域では形式的意味論を持つ仕様言語により、デッドロック不在等の性質を静的に証明できる利点を示す。安全性・高信頼性が要求される案件で形式手法の適用可否を検討した形跡がないと、テストでは実証不能な性質が未検証のまま残る。 | K13: 旧ブックの「追加承認」表記を移行。承認者・日付を推測で補完しない。
A14: ARC-901 | B14: 02_アーキテクチャ | C14: 1.3 Uses of Architecture — 再利用・プロダクトライン(共通性と可変性の設計) | D14: 再利用・派生開発における共通性と可変性が設計されている | E14: swebok-v4a.pdf ch02 Software Architecture > 1.3 Uses of Architecture — 再利用・プロダクトライン(共通性と可変性の設計) | F14: SRC-SWEBOK-V4A | G14: 要原記録確認 | H14: 未記録 | I14: 未記録 | J14: SWEBOKはアーキテクチャの主要用途として、共通性の識別と可変性に対応した再利用可能コンポーネントの設計によるプログラムファミリー/ソフトウェアプロダクトラインの基盤形成を挙げているが、チェックリストには再利用・派生開発の観点がない。複数製品・複数環境への展開が想定される場合、共通/可変の設計を怠るとコピー派生が乱立し保守コストが倍増する。 | K14: 旧ブックの「追加承認」表記を移行。承認者・日付を推測で補完しない。
... A68: SEC-954 | B68: 13_セキュリティ | C68: 旧ブックで追加承認として登録（カテゴリ: 11. ドキュメント品質・トレーサビリティ(SEC-951〜)） | D68: 文書に改訂履歴と承認状態があり、機微情報を含まない | E68: swebok-v4a.pdf ch13 Software Security > 2.2 ISMS(文書化された計画)/ 実務補完(文書管理) | F68: SRC-SWEBOK-V4A;SRC-PRACTICE | G68: 要原記録確認 | H68: 未記録 | I68: 未記録 | J68: 旧ブックに追加理由・原承認記録なし。原記録の確認が必要。 | K68: 旧ブックの「追加承認」表記を移行。承認者・日付を推測で補完しない。

Sheet 01_要件定義
A1: ID | B1: 区分 | C1: カテゴリ | D1: 基準重要度 | E1: チェック項目 | F1: 合格基準 | G1: 意図(なぜ確認するか) | H1: 対象ドキュメント(参照箇所) | I1: 適用プロファイル | J1: 適用条件 | K1: 出典ID | L1: 重複統制グループ | M1: 案件重要度 | N1: 適用判定 | O1: 判定 | P1: 証跡・参照箇所 | Q1: 指摘・Issue ID | R1: 対応方針 | S1: 例外・リスク受容承認者 | T1: 是正期限 | U1: レビュアー | V1: レビュー日 | W1: 再確認結果
A2: REQ-001 | B2: SWEBOK | C2: 1. 文書構成・全体(SWEBOK 1章全般 / ISO 29148) | D2: Critical | E2: すべての要求に一意IDが付与されている | F2: 全要求文にIDがあり、文書全体でIDの重複・欠番の未管理がない | G2: IDのない要求はトレース・変更管理・テスト対応付けの起点を持てず、変更漏れや検証漏れが下流で静かに発生する。SWEBOKが要求管理の前提とする「個々の要求の構成管理」を成立させるための最低条件。 | H2: swebok-v4a.pdf ch01 Software Requirements > 4.5 Additional Attributes of Requirements(tag)/ 実務補完(ISO/IEC/IEEE 29148) | I2: CORE | J2: 原則適用。案件スコープ・成果物・規制・リスク上非該当の場合はN/A根拠を記録。 | K2: SRC-SWEBOK-V4A;SRC-ISO-29148;SRC-PRACTICE
A3: REQ-002 | B3: SWEBOK | C3: 1. 文書構成・全体(SWEBOK 1章全般 / ISO 29148) | D3: High | E3: 文書の目的・スコープ・対象読者が冒頭に記載されている | F3: 「はじめに」相当の節に目的・スコープ・対象読者の3点が明記されている | G3: SWEBOKは要求文書の意思決定を読者分析(audience analysis)に基づかせることを最重要推奨とする。目的・スコープ・読者が曖昧な文書は、スコープ外要望の混入や読者に届かない記述粒度を招く。 | H3: swebok-v4a.pdf ch01 Software Requirements > 4. Requirements Specification(audience analysis) | I3: CORE | J3: 原則適用。案件スコープ・成果物・規制・リスク上非該当の場合はN/A根拠を記録。 | K3: SRC-SWEBOK-V4A
A4: REQ-003 | B4: SWEBOK | C4: 1. 文書構成・全体(SWEBOK 1章全般 / ISO 29148) | D4: High | E4: 用語集または用語定義があり、ドメイン用語・略語が定義されている | F4: 本文で使われる略語・ドメイン固有語が用語集で引ける(未定義の略語が本文にない) | G4: SWEBOKが挙げる二大問題の一つ「曖昧性(複数解釈の余地)」の多くは用語の未定義に起因する。ドメイン用語の解釈違いは設計・テストまで波及して指数的な手戻りを生む。 | H4: swebok-v4a.pdf ch01 Software Requirements > 3.1 Basic Requirements Analysis(unambiguous)/ 実務補完(ISO 29148) | I4: CORE | J4: 原則適用。案件スコープ・成果物・規制・リスク上非該当の場合はN/A根拠を記録。 | K4: SRC-SWEBOK-V4A;SRC-ISO-29148;SRC-PRACTICE
A5: REQ-004 | B5: SWEBOK | C5: 1. 文書構成・全体(SWEBOK 1章全般 / ISO 29148) | D5: High | E5: 拘束力を示す語(shall/must/should/may 等)の使い分けが定義され、一貫して使われている | F5: 規約の定義節があり、本文の要求文がその規約に従っている | G5: 拘束力語の使い分けが不定だと、努力目標を必須要求と誤解して過剰実装したり、必須要求を任意と誤解して欠落させたりする。要求が「binding(拘束的)」であるかの判定基盤になる。 | H5: swebok-v4a.pdf ch01 Software Requirements > 3.1 Basic Requirements Analysis(binding)/ 実務補完(ISO 29148, RFC 2119) | I5: CORE | J5: 原則適用。案件スコープ・成果物・規制・リスク上非該当の場合はN/A根拠を記録。 | K5: SRC-SWEBOK-V4A;SRC-ISO-29148;SRC-RFC;SRC-PRACTICE
A6: REQ-005 | B6: SWEBOK | C6: 1. 文書構成・全体(SWEBOK 1章全般 / ISO 29148) | D6: Medium | E6: 参照文書(上位計画書、RFP、法令、標準)が版数付きで列挙されている | F6: 参照文書一覧に文書名と版数(または日付)がある | G6: SWEBOKは要求の後方トレース先として上位文書・標準・規制を挙げる。参照文書の版が不明だと外部一貫性の検証基準が動き、どの版と整合させたのかが変更時に再現できない。 | H6: swebok-v4a.pdf ch01 Software Requirements > 7.3 Requirements Tracing / 2.1 Requirements Sources(非人間源泉) | I6: CORE | J6: 原則適用。案件スコープ・成果物・規制・リスク上非該当の場合はN/A根拠を記録。 | K6: SRC-SWEBOK-V4A
A7: REQ-006 | B7: SWEBOK | C7: 1. 文書構成・全体(SWEBOK 1章全般 / ISO 29148) | D7: Medium | E7: 増分的仕様か包括的仕様かの方針が明記されている | F7: 差分記述か全量記述かが文書内に宣言され、実際の記述方式と一致している | G7: 増分仕様か包括仕様かが宣言されていないと、読者が「書かれていない要求は廃止されたのか前版有効なのか」を判断できず、廃止済み要求の実装や有効要求の欠落を招く。 | H7: swebok-v4a.pdf ch01 Software Requirements > 4.6 Incremental and Comprehensive Requirements Specification | I7: CORE | J7: 原則適用。案件スコープ・成果物・規制・リスク上非該当の場合はN/A根拠を記録。 | K7: SRC-SWEBOK-V4A
A8: REQ-007 | B8: SWEBOK | C8: 1. 文書構成・全体(SWEBOK 1章全般 / ISO 29148) | D8: Medium | E8: 未決事項(TBD/TBR)が識別子付きで一覧管理され、解決期限か担当が付いている | F8: TBDが本文に散在するだけでなく一覧化され、各件に担当または期限がある | G8: SWEBOKの言う「不完全性」問題の管理装置。TBDが本文に散在したまま放置されると、未決のまま設計・実装が進み、後工程での判明時に指数的な手戻りコストになる。 | H8: swebok-v4a.pdf ch01 Software Requirements > 3.1 Basic Requirements Analysis(complete)/ 実務補完(ISO 29148) | I8: CORE | J8: 原則適用。案件スコープ・成果物・規制・リスク上非該当の場合はN/A根拠を記録。 | K8: SRC-SWEBOK-V4A;SRC-ISO-29148;SRC-PRACTICE
A9: REQ-008 | B9: SWEBOK | C9: 1. 文書構成・全体(SWEBOK 1章全般 / ISO 29148) | D9: Low | E9: 変更履歴(版数・日付・変更者・変更概要)がある | F9: 変更履歴表が存在し、最新版の記録がある | G9: 要求文書は他の成果物と同様に構成管理の対象であるべきというSWEBOKの原則の最小形。履歴がないと、レビューや承認がどの版に対して行われたかを事後に特定できない。 | H9: swebok-v4a.pdf ch01 Software Requirements > 4. Requirements Specification(構成管理)/ 6.2 Requirements Change Control | I9: CORE | J9: 原則適用。案件スコープ・成果物・規制・リスク上非該当の場合はN/A根拠を記録。 | K9: SRC-SWEBOK-V4A
A10: REQ-101 | B10: SWEBOK | C10: 2. 個々の要求の記述品質(SWEBOK 3.1) | D10: Critical | E10: 要求文に曖昧語がない | F10: 「など」「等」「適切に」「可能な限り」「柔軟に」「高速に」「使いやすい」等の検証不能語が要求文(shall文)に含まれない。含む場合は数値・列挙・条件で具体化されている | G10: SWEBOKが実プロジェクトの二大要求問題の一つに挙げる「曖昧性」への直接の防御。曖昧語は複数解釈のうち誤った1つで実装される欠陥の温床であり、受入時の紛争原因にもなる。 | H10: swebok-v4a.pdf ch01 Software Requirements > 3.1 Basic Requirements Analysis(unambiguous) | I10: CORE | J10: 原則適用。案件スコープ・成果物・規制・リスク上非該当の場合はN/A根拠を記録。 | K10: SRC-SWEBOK-V4A
A11: REQ-102 | B11: SWEBOK | C11: 2. 個々の要求の記述品質(SWEBOK 3.1) | D11: Critical | E11: 各要求がテスト可能である | F11: 各要求について検証方法(テスト・検査・分析・デモのいずれか)が記載されているか、合否判定手順を第三者が書ける程度に具体的である | G11: テスト不能な要求は合否を客観的に示せず、実装完了の判定が主観論争になる。SWEBOKは「準拠・非準拠を明確に実証できる(testable/quantified)」ことを要求の望ましい性質として明示する。 | H11: swebok-v4a.pdf ch01 Software Requirements > 3.1 Basic Requirements Analysis(testable) | I11: CORE | J11: 原則適用。案件スコープ・成果物・規制・リスク上非該当の場合はN/A根拠を記録。 | K11: SRC-SWEBOK-V4A
A12: REQ-103 | B12: SWEBOK | C12: 2. 個々の要求の記述品質(SWEBOK 3.1) | D12: Critical | E12: 各要求が原子的である(1要求1事項) | F12: 1つの要求文に独立に検証すべき事項が2つ以上含まれない(「および」「かつ」で複数の別個の振る舞いを連結していない) | G12: 複数事項を束ねた要求は一部実装・一部未実装の状態を表現できず、トレースや優先順位付けの単位が壊れる。SWEBOKは「atomic(単一の決定を表す)」を望ましい性質に挙げる。 | H12: swebok-v4a.pdf ch01 Software Requirements > 3.1 Basic Requirements Analysis(atomic) | I12: CORE | J12: 原則適用。案件スコープ・成果物・規制・リスク上非該当の場合はN/A根拠を記録。 | K12: SRC-SWEBOK-V4A
A13: REQ-104 | B13: SWEBOK | C13: 2. 個々の要求の記述品質(SWEBOK 3.1) | D13: High | E13: 要求が解決手段でなく必要性(真のニーズ)を表している | F13: 実装手段の指定(特定ライブラリ・アルゴリズム等)が、意図的な技術制約として根拠付きで書かれている場合を除き要求文に現れない | G13: 手段として語られた要望をそのまま要求化すると、真の問題を解かない次善解を実装するリスクがある(SWEBOKが5-whysで警告する点)。設計の自由度も不必要に奪われる。 | H13: swebok-v4a.pdf ch01 Software Requirements > 3.1 Basic Requirements Analysis(represent true stakeholder needs / 5-whys) | I13: CORE | J13: 原則適用。案件スコープ・成果物・規制・リスク上非該当の場合はN/A根拠を記録。 | K13: SRC-SWEBOK-V4A
... A75: REQ-1004 | B75: SWEBOK | C75: 11. 要求管理・変更管理(SWEBOK 6.1〜6.3) | D75: Medium | E75: 要求スクラビングが実施されている | F75: スコープ外・低価値として除外した要求の一覧と除外理由が残っている(除外ゼロの場合はスクラビング実施の記録がある) | G75: SWEBOKのスクラビングは「ステークホルダーニーズを満たす最小の要求集合」を見つけて解の規模・コストを最小化する活動。実施しないとスコープ外・低ROIの要求が温存され、工数と納期を静かに侵食する。 | H75: swebok-v4a.pdf ch01 Software Requirements > 6.1 Requirements Scrubbing | I75: CORE | J75: 原則適用。案件スコープ・成果物・規制・リスク上非該当の場合はN/A根拠を記録。 | K75: SRC-SWEBOK-V4A
A76: REQ-1005 | B76: SWEBOK | C76: 11. 要求管理・変更管理(SWEBOK 6.1〜6.3) | D76: Medium | E76: スコープと制約(コスト・期間・要員)の整合が確認されている | F76: 要求規模(件数・ファンクショナルサイズ・ストーリーポイント等)と制約の突合記録があり、超過時の調整判断が記録されている | G76: SWEBOKのスコープマッチングに対応。要求スコープが制約を超えたまま進むと、破綻が開発後半に露見して最悪のタイミングでの削減交渉になる。定量的(機能規模単位)な突合が望ましいとされる。 | H76: swebok-v4a.pdf ch01 Software Requirements > 6.3 Scope Matching | I76: CORE | J76: 原則適用。案件スコープ・成果物・規制・リスク上非該当の場合はN/A根拠を記録。 | K76: SRC-SWEBOK-V4A | L76: COST
A77: REQ-1006 | B77: SWEBOK | C77: 11. 要求管理・変更管理(SWEBOK 6.1〜6.3) | D77: Low | E77: 要求ごとの安定性(変動しやすさ)が評価されている | F77: 変動リスクの高い要求に安定性属性または注記が付いている | G77: SWEBOKは変動しやすい要求の識別が「変更に強い設計」の確立を助けるとする。安定性評価がないと、変動必至の要求を硬直した構造で実装し、変更のたびに大規模改修を強いられる。 | H77: swebok-v4a.pdf ch01 Software Requirements > 7.4 Requirements Stability and Volatility | I77: CORE | J77: 原則適用。案件スコープ・成果物・規制・リスク上非該当の場合はN/A根拠を記録。 | K77: SRC-SWEBOK-V4A
A78: REQ-1101 | B78: SWEBOK | C78: 12. 優先順位付け・トレーサビリティ・計測(SWEBOK 7.2〜7.5) | D78: Critical | E78: RTMが存在し、要求⇔テストの対応が記録されている | F78: 承認済み要求の各行にテストケースID(または検証手段)が対応付いているか、対応付け予定が管理されている | G78: SWEBOKはトレーシングの第一の目的を成果物間の整合の検証に置く。要求⇔テストの対応がないと、検証されない要求(実装漏れの見逃し)と要求のないテスト(仕様の欠落か無駄)を検出できない。 | H78: swebok-v4a.pdf ch01 Software Requirements > 7.3 Requirements Tracing(forward to test cases) | I78: CORE | J78: 原則適用。案件スコープ・成果物・規制・リスク上非該当の場合はN/A根拠を記録。 | K78: SRC-SWEBOK-V4A
A79: REQ-1102 | B79: SWEBOK | C79: 12. 優先順位付け・トレーサビリティ・計測(SWEBOK 7.2〜7.5) | D79: Critical | E79: 全要求が上位要求・ビジネス目標にトレースされる(後方トレース) | F79: RTM上で源泉・上位目標が空欄の承認済み要求がない | G79: 上位にトレースできない要求は「存在理由を説明できない要求」であり、スコープクリープの典型的な侵入形態。SWEBOKは源泉文書への後方トレースを明示する。 | H79: swebok-v4a.pdf ch01 Software Requirements > 7.3 Requirements Tracing(back to source documentation) | I79: CORE | J79: 原則適用。案件スコープ・成果物・規制・リスク上非該当の場合はN/A根拠を記録。 | K79: SRC-SWEBOK-V4A | L79: OPS-OBSERVABILITY
A80: REQ-1103 | B80: SWEBOK | C80: 12. 優先順位付け・トレーサビリティ・計測(SWEBOK 7.2〜7.5) | D80: High | E80: 上位要求から下位要求への前方トレースが取れる | F80: ビジネス目標・システム要求の各項目が、少なくとも1つのソフトウェア要求に展開されているか、未展開が識別されている | G80: SWEBOKのトレーシング設問「各要求に対応する下位要素があるか」の適用。前方トレースの欠落は上位目標の未実現(要求の不完全性)をリリースまで隠す。 | H80: swebok-v4a.pdf ch01 Software Requirements > 7.3 Requirements Tracing(forward tracing) | I80: CORE | J80: 原則適用。案件スコープ・成果物・規制・リスク上非該当の場合はN/A根拠を記録。 | K80: SRC-SWEBOK-V4A | L80: OPS-OBSERVABILITY
A81: REQ-1104 | B81: SWEBOK | C81: 12. 優先順位付け・トレーサビリティ・計測(SWEBOK 7.2〜7.5) | D81: High | E81: すべての要求に優先度が付与され、差が付いている | F81: 優先度属性の空欄がなく、全件が同一優先度になっていない | G81: SWEBOKは優先順位付けが価値の高い機能の早期提供・対立解消・スコープマッチングを支えるとする。全件同一優先度は優先順位付けの放棄であり、削減交渉時に判断材料がなくなる。 | H81: swebok-v4a.pdf ch01 Software Requirements > 7.2 Requirements Prioritization | I81: CORE | J81: 原則適用。案件スコープ・成果物・規制・リスク上非該当の場合はN/A根拠を記録。 | K81: SRC-SWEBOK-V4A
A82: REQ-1105 | B82: SWEBOK | C82: 12. 優先順位付け・トレーサビリティ・計測(SWEBOK 7.2〜7.5) | D82: Medium | E82: 優先順位付けの基準が定義されている | F82: 価値・コスト・リスク・不満足度(Kanoモデル等)のうち何を基準にしたかが記録されている | G82: SWEBOKは満足度だけでなく「なければどれほど不満か」(Kanoモデル)まで考慮しないと誤った優先順位になると警告する。基準の記録がないと優先度が声の大きさで決まり、必須機能が後回しになる。 | H82: swebok-v4a.pdf ch01 Software Requirements > 7.2 Requirements Prioritization(価値・コスト・リスク・Kanoモデル) | I82: CORE | J82: 原則適用。案件スコープ・成果物・規制・リスク上非該当の場合はN/A根拠を記録。 | K82: SRC-SWEBOK-V4A
A83: REQ-1106 | B83: SWEBOK | C83: 12. 優先順位付け・トレーサビリティ・計測(SWEBOK 7.2〜7.5) | D83: Medium | E83: 要求の規模・件数が計測されている | F83: 要求件数、ファンクショナルサイズまたはストーリーポイント合計が記録されている | G83: SWEBOKは要求の量(機能規模・ストーリーポイント)が開発規模の評価・見積り・他計測の分母として有用とする。計測がないとスコープマッチングも変更規模の定量化もできない。 | H83: swebok-v4a.pdf ch01 Software Requirements > 7.5 Measuring Requirements(FSM, story points) | I83: CORE | J83: 原則適用。案件スコープ・成果物・規制・リスク上非該当の場合はN/A根拠を記録。 | K83: SRC-SWEBOK-V4A
A84: REQ-1107 | B84: SWEBOK | C84: 12. 優先順位付け・トレーサビリティ・計測(SWEBOK 7.2〜7.5) | D84: Medium | E84: RTMの状態列が運用されている | F84: 各要求の状態(提案/承認/実装済み/検証済み等)が定義された値集合で管理されている | G84: SWEBOKはマネジメントが要求の状態からプロジェクト完了度を評価できると述べる。状態列が運用されていないRTMは作成時点のスナップショットに過ぎず、進捗・検証状況の把握手段にならない。 | H84: swebok-v4a.pdf ch01 Software Requirements > 4.5(属性)/ 序論(要求の状態によるプロジェクト完了評価) | I84: CORE | J84: 原則適用。案件スコープ・成果物・規制・リスク上非該当の場合はN/A根拠を記録。 | K84: SRC-SWEBOK-V4A
A85: REQ-1108 | B85: SWEBOK | C85: 12. 優先順位付け・トレーサビリティ・計測(SWEBOK 7.2〜7.5) | D85: Low | E85: 要求変更率(volatility)が追跡されている | F85: ベースライン後の変更件数・変更率の記録または集計手段がある | G85: SWEBOKは要求の安定性・変動性の評価を実務上の考慮事項とする。変更率の追跡は、要求プロセスの品質問題(獲得不足・合意の脆さ)の早期警報であり、再見積りの根拠にもなる。 | H85: swebok-v4a.pdf ch01 Software Requirements > 7.4 Requirements Stability and Volatility / 7.5 Measuring Requirements | I85: CORE | J85: 原則適用。案件スコープ・成果物・規制・リスク上非該当の場合はN/A根拠を記録。 | K85: SRC-SWEBOK-V4A
A86: REQ-1201 | B86: SWEBOK | C86: 13. ツール・運用(SWEBOK 8章) | D86: Medium | E86: 要求の管理媒体・ツールが特定され関係者に共有されている | F86: 要求の正本がどこにあるか(ツール名・リポジトリ・文書)が文書化され、複数の正本が併存していない | G86: 正本が複数併存すると、どれを見て実装・テストするかが人によって分かれ、古い版に基づく作業が発生する。SWEBOKは要求管理ツールの役割(属性保存・トレース・変更管理)を明示し、正本の一元化を前提とする。 | H86: swebok-v4a.pdf ch01 Software Requirements > 8.1 Requirements Management Tools | I86: CORE | J86: 原則適用。案件スコープ・成果物・規制・リスク上非該当の場合はN/A根拠を記録。 | K86: SRC-SWEBOK-V4A
A87: REQ-1202 | B87: SWEBOK | C87: 13. ツール・運用(SWEBOK 8章) | D87: Medium | E87: 要求規模に対して管理方法が持続可能である | F87: 要求数百件超・高変更頻度の案件で手作業スプレッドシート運用の場合、属性管理・トレース更新の運用手順が定義されているか、ツール導入の検討記録がある | G87: SWEBOKは「トレースと変更管理はツール支援があって初めて実用的になり得る」とし、スプレッドシート等のアドホック管理を「満足度の低い方法」と明言する。規模に対して手作業運用が破綻すると、トレース・属性が更新されず形骸化する。 | H87: swebok-v4a.pdf ch01 Software Requirements > 8.1 Requirements Management Tools(ad hoc管理への警告) | I87: CORE | J87: 原則適用。案件スコープ・成果物・規制・リスク上非該当の場合はN/A根拠を記録。 | K87: SRC-SWEBOK-V4A
A88: REQ-1203 | B88: SWEBOK | C88: 13. ツール・運用(SWEBOK 8章) | D88: Low | E88: 仕様からテストケースを導出する方針が定義されている | F88: 受入基準・デシジョンテーブル・モデル等からのテストケース導出方法がテスト計画側と合意されている | G88: SWEBOKは形式性の高い仕様(BDDシナリオ・状態モデル等)ほどテストケースを機械的に導出できるとする。導出方針をテスト側と事前合意しないと、仕様化技法の選択がテスト工程で活かされず二重作業になる。 | H88: swebok-v4a.pdf ch01 Software Requirements > 8.3 Functional Test Case Generation Tools / 4.3(BDDシナリオからのテスト導出) | I88: CORE | J88: 原則適用。案件スコープ・成果物・規制・リスク上非該当の場合はN/A根拠を記録。 | K88: SRC-SWEBOK-V4A
A89: REQ-9903 | B89: 追加承認 | C89: 13. ツール・運用(SWEBOK 8章) | D89: Low | E89: 要求プロセス自体の振り返り・改善の仕組みがある | F89: 要求起因の欠陥・変更の傾向を振り返る場(工程完了時レビュー、レトロスペクティブ等)が計画され、実施記録または改善アクションが残っている | G89: 要求起因の欠陥はプロセスの欠陥の症状であり、成果物検査だけでは同種の欠陥が案件のたびに再発する。プロセス改善のループを確認する。 | H89: swebok-v4a.pdf ch01 Software Requirements > 7.6 Requirements Process Quality and Improvement(要求プロセスの品質と改善) | I89: CORE | J89: 原則適用。案件スコープ・成果物・規制・リスク上非該当の場合はN/A根拠を記録。 | K89: SRC-SWEBOK-V4A

Sheet 02_アーキテクチャ
A1: ID | B1: 区分 | C1: カテゴリ | D1: 基準重要度 | E1: チェック項目 | F1: 合格基準 | G1: 意図(なぜ確認するか) | H1: 対象ドキュメント(参照箇所) | I1: 適用プロファイル | J1: 適用条件 | K1: 出典ID | L1: 重複統制グループ | M1: 案件重要度 | N1: 適用判定 | O1: 判定 | P1: 証跡・参照箇所 | Q1: 指摘・Issue ID | R1: 対応方針 | S1: 例外・リスク受容承認者 | T1: 是正期限 | U1: レビュアー | V1: レビュー日 | W1: 再確認結果
A2: ARC-001 | B2: SWEBOK | C2: 1. コンテキストとステークホルダー | D2: Critical | E2: ステークホルダーが特定されている | F2: 利用者・開発者・運用者・保守者を含む主要ステークホルダーが一覧化され、各々に少なくとも1つの関心事が対応付けられている | G2: 誰の関心事に応えるアーキテクチャかが不明だと、声の大きい一部の利害だけを反映した設計になり、運用者・保守者の要求が後工程で噴出して大規模な手戻りを招く。 | H2: swebok-v4a.pdf ch02 Software Architecture > 1.2 Stakeholders and Concerns | I2: CORE | J2: 原則適用。案件スコープ・成果物・規制・リスク上非該当の場合はN/A根拠を記録。 | K2: SRC-SWEBOK-V4A
A3: ARC-002 | B3: SWEBOK | C3: 1. コンテキストとステークホルダー | D3: Critical | E3: ステークホルダーの関心事が文書化されている | F3: 関心事が機能・非機能(品質属性)・制約のいずれかに分類され、一覧表または同等の形式で記録されている | G3: 関心事を分類・記録しないと非機能や制約が暗黙のまま設計が進み、後から性能・セキュリティ要求が判明して構造の作り直しが発生する。 | H3: swebok-v4a.pdf ch02 Software Architecture > 1.2 Stakeholders and Concerns(関心事の機能/非機能/制約への分類) | I3: CORE | J3: 原則適用。案件スコープ・成果物・規制・リスク上非該当の場合はN/A根拠を記録。 | K3: SRC-SWEBOK-V4A
A4: ARC-003 | B4: SWEBOK | C4: 1. コンテキストとステークホルダー | D4: High | E4: システムコンテキストが記述されている | F4: 外部システム・利用者・環境との境界と相互作用がコンテキスト図または文章で示され、システムの責務範囲が判別できる | G4: アーキテクチャは環境の中のシステムを外向きに捉えるものであり、境界が曖昧だと責務の押し付け合いや外部システム連携の設計漏れが起きる。 | H4: swebok-v4a.pdf ch02 Software Architecture > 1.1 The Senses of "Architecture"(環境の中のシステムという定義) | I4: CORE | J4: 原則適用。案件スコープ・成果物・規制・リスク上非該当の場合はN/A根拠を記録。 | K4: SRC-SWEBOK-V4A
A5: ARC-004 | B5: SWEBOK | C5: 1. コンテキストとステークホルダー | D5: High | E5: 関心事とビュー/ADRの対応が示されている | F5: 各関心事について、それを扱うビューまたはADRへの対応(トレーサビリティ)が確認できる。どこにも扱われない関心事がない | G5: 関心事とビュー/決定の対応が取れていないと、どこにも扱われない関心事が放置され、レビューでも見落とされたままリリースに至る。 | H5: swebok-v4a.pdf ch02 Software Architecture > 2. Software Architecture Description / 2.1 Architecture Views and Viewpoints | I5: CORE | J5: 原則適用。案件スコープ・成果物・規制・リスク上非該当の場合はN/A根拠を記録。 | K5: SRC-SWEBOK-V4A | L5: CONTINUITY-DR
A6: ARC-005 | B6: SWEBOK | C6: 1. コンテキストとステークホルダー | D6: Medium | E6: 運用・保守・テストの関心事が含まれている | F6: 開発時の関心事だけでなく、展開・運用・監視・保守・テスト容易性に関する関心事が少なくとも1つ以上記載されている | G6: 関心事は開発・運用・保守・テストなど広範な影響を含むため、開発時の視点だけで設計すると運用不能・テスト困難なシステムが本番で発覚する。 | H6: swebok-v4a.pdf ch02 Software Architecture > 1.2 Stakeholders and Concerns(developmental/operationalを含む関心事の範囲) | I6: CORE | J6: 原則適用。案件スコープ・成果物・規制・リスク上非該当の場合はN/A根拠を記録。 | K6: SRC-SWEBOK-V4A
A7: ARC-006 | B7: SWEBOK | C7: 1. コンテキストとステークホルダー | D7: Medium | E7: 組織構造が考慮されている | F7: チーム編成・組織間の責任分界とコンポーネント境界の関係(コンウェイの法則への言及または整合性の検討)が記録されている | G7: コンウェイの法則によりアーキテクチャは組織の通信構造を写し取るため、組織と構造の不整合を放置するとチーム間調整コストの爆発や責任の空白地帯を生む。 | H7: swebok-v4a.pdf ch02 Software Architecture > 1.3 Uses of Architecture(Conway's Law) | I7: CORE | J7: 原則適用。案件スコープ・成果物・規制・リスク上非該当の場合はN/A根拠を記録。 | K7: SRC-SWEBOK-V4A
A8: ARC-007 | B8: SWEBOK | C8: 1. コンテキストとステークホルダー | D8: Low | E8: 関心事の将来変化が考慮されている | F8: 事業環境・規制・技術動向による関心事の変化(例: 持続可能性、エネルギー効率)への言及または見直し方針がある | G8: 関心事は静的でなくライフサイクルや技術・政策の変化とともに進化するため、見直し観点がないと規制変更やエネルギー効率要求に構造が追随できなくなる。 | H8: swebok-v4a.pdf ch02 Software Architecture > 1.2 Stakeholders and Concerns(関心事の進化、持続可能性への言及) | I8: CORE | J8: 原則適用。案件スコープ・成果物・規制・リスク上非該当の場合はN/A根拠を記録。 | K8: SRC-SWEBOK-V4A
A9: ARC-903 | B9: 追加承認 | C9: 1. コンテキストとステークホルダー | D9: Medium | E9: 開発アプローチに応じたアーキテクチャ活動の位置付けが定義されている | F9: 採用する開発アプローチ(ウォーターフォール/アジャイル/プロダクトライン等)の中で、アーキテクチャの分析・統合・評価をいつ・どの程度行うかが定められている。アジャイルで創発的アーキテクチャに依る場合、ユーザーストーリーに現れない重要品質特性(安全性・性能等)の扱いが別途定義されている | G9: アジャイルで創発任せにすると、ユーザーストーリーに現れない安全性・性能などの重要特性が誰にも設計されず、後から構造レベルの作り直しが必要になる。 | H9: swebok-v4a.pdf ch02 Software Architecture > 3.1 Architecture in Context — ライフサイクルコンテキスト(アジャイル等での創発的アーキテクチャのリスク) | I9: CORE | J9: 原則適用。案件スコープ・成果物・規制・リスク上非該当の場合はN/A根拠を記録。 | K9: SRC-SWEBOK-V4A
A10: ARC-010 | B10: SWEBOK | C10: 2. アーキテクチャ上重要な要求(ASR) | D10: Critical | E10: ASRが識別されている | F10: アーキテクチャ上重要な要求が一般要求と区別して一覧化され、各ASRに識別子が付与されている | G10: ASRを一般要求と区別しないと、アーキテクチャを左右する要求が後工程に先送りされ、構造を壊さないと満たせない要求が実装後に見つかる。 | H10: swebok-v4a.pdf ch02 Software Architecture > 3.2.1 Architecture Analysis(ASRの収集と定式化) | I10: CORE | J10: 原則適用。案件スコープ・成果物・規制・リスク上非該当の場合はN/A根拠を記録。 | K10: SRC-SWEBOK-V4A
A11: ARC-011 | B11: SWEBOK | C11: 2. アーキテクチャ上重要な要求(ASR) | D11: Critical | E11: ASRの選定基準が妥当である | F11: 各ASRについて、変更困難性・高コスト・横断性・品質属性への直結のいずれかの根拠が説明されている、または選定基準が文書化されている | G11: 選定基準がないとASRの認定が恣意的になり、重要でない要求に設計労力を割く一方で真に構造を制約する要求を見落とす。 | H11: swebok-v4a.pdf ch02 Software Architecture > 3.2.1 Architecture Analysis(ASR=アーキテクチャに影響する要求の定義) | I11: CORE | J11: 原則適用。案件スコープ・成果物・規制・リスク上非該当の場合はN/A根拠を記録。 | K11: SRC-SWEBOK-V4A
A12: ARC-012 | B12: SWEBOK | C12: 2. アーキテクチャ上重要な要求(ASR) | D12: High | E12: ASRに優先度が付与されている | F12: 全ASRに優先度(高/中/低または同等の尺度)が付与され、優先度の判断基準が記載されている | G12: 全要求を同等に扱うと分析・統合の反復で焦点が定まらず、コストや納期との衝突時にどの要求を交渉・緩和すべきか判断できない。 | H12: swebok-v4a.pdf ch02 Software Architecture > 3.2.1 Architecture Analysis(要求と制約の衝突時の交渉) | I12: CORE | J12: 原則適用。案件スコープ・成果物・規制・リスク上非該当の場合はN/A根拠を記録。 | K12: SRC-SWEBOK-V4A
A13: ARC-013 | B13: SWEBOK | C13: 2. アーキテクチャ上重要な要求(ASR) | D13: Critical | E13: 優先度の高いASRすべてに対応方針がある | F13: 優先度「高」の各ASRについて、それを満たすアーキテクチャ上の対応(スタイル・戦術・構造)がADまたはADRで特定できる | G13: 高優先ASRに対応する構造・戦術が特定できないと、要求が「書かれただけ」で終わり、評価時に充足性を検証する手がかりも失われる。 | H13: swebok-v4a.pdf ch02 Software Architecture > 3.2.2 Architecture Synthesis(ASRが示す設計問題への解の展開) | I13: CORE | J13: 原則適用。案件スコープ・成果物・規制・リスク上非該当の場合はN/A根拠を記録。 | K13: SRC-SWEBOK-V4A
A14: ARC-014 | B14: SWEBOK | C14: 2. アーキテクチャ上重要な要求(ASR) | D14: High | E14: ASRと要求文書のトレーサビリティがある | F14: 各ASRが元の要求(要求仕様書の項番等)まで遡れる。出典のないASRがない | G14: 出典不明のASRは根拠の検証も変更時の影響分析もできず、要求変更がアーキテクチャへ伝播しない(またはその逆)事故を招く。 | H14: swebok-v4a.pdf ch02 Software Architecture > 3.2.1 Architecture Analysis(既知の要求・コンテキストに基づく分析) | I14: CORE | J14: 原則適用。案件スコープ・成果物・規制・リスク上非該当の場合はN/A根拠を記録。 | K14: SRC-SWEBOK-V4A
A15: ARC-015 | B15: SWEBOK | C15: 2. アーキテクチャ上重要な要求(ASR) | D15: Medium | E15: 非機能要求がISO/IEC 25010等の品質モデルに対応付けられている | F15: 品質属性が標準の品質特性分類(性能効率性・信頼性・セキュリティ・保守性等)で整理されている | G15: 品質属性を標準分類で整理しないと、関係者ごとに用語の解釈がずれ、性能とスケーラビリティの混同のような認識齟齬が評価段階まで残る。 | H15: swebok-v4a.pdf ch02 Software Architecture > 1.2 Stakeholders and Concerns(品質属性としての関心事)+ 実務補完(ISO/IEC 25010) | I15: CORE | J15: 原則適用。案件スコープ・成果物・規制・リスク上非該当の場合はN/A根拠を記録。 | K15: SRC-SWEBOK-V4A;SRC-ISO-25010;SRC-PRACTICE
A16: ARC-020 | B16: SWEBOK | C16: 3. 制約と前提条件 | D16: High | E16: 技術的制約が明記されている | F16: 既存資産・利用必須の技術・上位アーキテクチャ(EA/リファレンスアーキテクチャ)からの制約が列挙されている | G16: エンタープライズアーキテクチャや上位システムからの制約はASRとして反映すべきものであり、見落とすと適合性検査や統合段階で不適合が発覚し設計をやり直すことになる。 | H16: swebok-v4a.pdf ch02 Software Architecture > 3.1 Architecture in Context / 3.4 Architecting in the Large(上位アーキテクチャへの準拠) | I16: CORE | J16: 原則適用。案件スコープ・成果物・規制・リスク上非該当の場合はN/A根拠を記録。 | K16: SRC-SWEBOK-V4A
A17: ARC-021 | B17: SWEBOK | C17: 3. 制約と前提条件 | D17: High | E17: 組織的・事業的制約が明記されている | F17: 予算・納期・チームスキル・調達方針など、設計の選択肢を狭める非技術的制約が記録されている | G17: 予算・納期・スキルなどの事業的制約は設計の選択肢を実質的に決めるため、無視すると技術的には正しくても実現不能な机上の設計になる。 | H17: swebok-v4a.pdf ch02 Software Architecture > 1.2 Stakeholders and Concerns(business/organizational/economicな影響) | I17: CORE | J17: 原則適用。案件スコープ・成果物・規制・リスク上非該当の場合はN/A根拠を記録。 | K17: SRC-SWEBOK-V4A
... A20: ARC-024 | B20: SWEBOK | C20: 3. 制約と前提条件 | D20: Low | E20: 前提が崩れた場合の影響が検討されている | F20: 主要な前提条件について、成立しなくなった場合の影響または見直しトリガーが記載されている | G20: 前提が崩れたときの影響と見直しトリガーがないと、環境変化に誰も気づかず、破綻した前提の上に機能追加を積み重ねてしまう。 | H20: swebok-v4a.pdf ch02 Software Architecture > 2.4 Architecture as Significant Decisions(条件変化時の決定の再検討) | I20: CORE | J20: 原則適用。案件スコープ・成果物・規制・リスク上非該当の場合はN/A根拠を記録。 | K20: SRC-SWEBOK-V4A;SRC-CIS
A21: ARC-CO01 | B21: クラウド補完 | C21: 3. 制約と前提条件 | D21: Medium | E21: システムの配置先(リージョン/データセンター/国)の選定根拠として、データ所在地規制・ユーザー近接性(レイテンシ)・サービス提供状況・DR要件が制約条件として文書化されているか | F21: アーキテクチャ記述書の制約節に配置先選定の根拠と規制要件との対応が記載されていること | G21: データ主権・所在地規制の見落としは稼働後に発覚するとシステム移設という最大級の手戻りになる。 | H21: Well-Architected Framework for OCI > Operational Efficiency > Plan Your Deployment Strategy > Choose a Region Based on Your Customers and Data / Distributed Cloud > Follow Distributed Cloud Design Principles | I21: CORE | J21: 原則適用。案件スコープ・成果物・規制・リスク上非該当の場合はN/A根拠を記録。 | K21: SRC-OCI-WAF | L21: CONTINUITY-DR
A22: ARC-030 | B22: SWEBOK | C22: 4. アーキテクチャビューとビューポイント | D22: Critical | E22: 複数の関心事に対応するビューが存在する | F22: 少なくとも構造系ビュー(論理/モジュール)と配置系ビュー(デプロイメント)の2種類以上が作成されている | G22: 単一ビューでは多様な関心事を扱えない(multiple viewsの必要性)ため、構造と配置の最低2観点がないと運用・展開の関心事が設計から抜け落ちる。 | H22: swebok-v4a.pdf ch02 Software Architecture > 2.1 Architecture Views and Viewpoints(複数ビューによる関心事の分離) | I22: CORE | J22: 原則適用。案件スコープ・成果物・規制・リスク上非該当の場合はN/A根拠を記録。 | K22: SRC-SWEBOK-V4A
A23: ARC-031 | B23: SWEBOK | C23: 4. アーキテクチャビューとビューポイント | D23: Critical | E23: 各ビューの準拠ビューポイントが明示されている | F23: 各ビューに、対象とする関心事と使用する表記法・規約(ビューポイント定義または既知のビューポイントへの参照)が明記されている | G23: ビューポイントはビューの作成・解釈の規約を与えるものであり、これがないと図の読み方が人により異なり、誤読に基づく実装ミスを誘発する。 | H23: swebok-v4a.pdf ch02 Software Architecture > 2.1 Architecture Views and Viewpoints(ビューポイントによる規約の文書化) | I23: CORE | J23: 原則適用。案件スコープ・成果物・規制・リスク上非該当の場合はN/A根拠を記録。 | K23: SRC-SWEBOK-V4A
A24: ARC-032 | B24: SWEBOK | C24: 4. アーキテクチャビューとビューポイント | D24: High | E24: 図に凡例・記法の説明がある | F24: UML/ArchiMate等の標準記法の明記、または独自記法の場合は凡例があり、図中のすべての図形・線種の意味が判別できる | G24: 記法の定義がない図は書いた本人以外に正確に伝わらず、矢印の向きや線種の解釈違いがインタフェース設計の食い違いとして実装段階で顕在化する。 | H24: swebok-v4a.pdf ch02 Software Architecture > 2.1 Architecture Views and Viewpoints / 2.3 Architecture Description Languages and Architecture Frameworks | I24: CORE | J24: 原則適用。案件スコープ・成果物・規制・リスク上非該当の場合はN/A根拠を記録。 | K24: SRC-SWEBOK-V4A
A25: ARC-033 | B25: SWEBOK | C25: 4. アーキテクチャビューとビューポイント | D25: Critical | E25: 主要コンポーネントの責務が定義されている | F25: 構造系ビューに現れる各コンポーネントについて、責務の説明が1つ以上文章で記載されている。名前だけのコンポーネントがない | G25: アーキテクチャ設計の中核は主要コンポーネントの責務・特性・関係の特定であり、名前だけの箱は責務の重複や空白を隠し、チーム間の実装衝突を生む。 | H25: swebok-v4a.pdf ch02 Software Architecture > 3.2 Architectural Design(主要コンポーネントとその責務の特定) | I25: CORE | J25: 原則適用。案件スコープ・成果物・規制・リスク上非該当の場合はN/A根拠を記録。 | K25: SRC-SWEBOK-V4A
A26: ARC-034 | B26: SWEBOK | C26: 4. アーキテクチャビューとビューポイント | D26: High | E26: コンポーネント間のインタフェースが定義されている | F26: コンポーネント間の主要な相互作用について、インタフェース(API・プロトコル・データ形式のいずれか)が特定されている | G26: コンポーネント間の通信・相互作用が未定義だと、チームごとに勝手なプロトコル・データ形式を採用し、統合テストで初めて不整合が発覚する。 | H26: swebok-v4a.pdf ch02 Software Architecture > 3.2 Architectural Design(コンポーネントインタフェース、相互作用) | I26: CORE | J26: 原則適用。案件スコープ・成果物・規制・リスク上非該当の場合はN/A根拠を記録。 | K26: SRC-SWEBOK-V4A
A27: ARC-035 | B27: SWEBOK | C27: 4. アーキテクチャビューとビューポイント | D27: High | E27: ビュー間の整合性が確認されている | F27: 複数ビューに登場する同一要素の名前が一致している、またはビュー間対応表があり、既知の不整合が記録されている | G27: 複数ビュー導入の代償はビュー間不整合(multiple views problem)であり、対応関係の確認を怠ると「同じシステムを描いていない」図面群を根拠に実装が進む。 | H27: swebok-v4a.pdf ch02 Software Architecture > 2.1 Architecture Views and Viewpoints(multiple views problemと対応規則) | I27: CORE | J27: 原則適用。案件スコープ・成果物・規制・リスク上非該当の場合はN/A根拠を記録。 | K27: SRC-SWEBOK-V4A
A28: ARC-036 | B28: SWEBOK | C28: 4. アーキテクチャビューとビューポイント | D28: High | E28: 実行時の振る舞いが表現されている | F28: 主要ユースケースまたは品質シナリオについて、実行時の相互作用(シーケンス図、コンポーネント&コネクタビュー等)が少なくとも1つ示されている | G28: 静的構造だけでは並行性・実行時相互作用の妥当性を判断できず、性能・デッドロック等の問題が実行して初めて見つかる。 | H28: swebok-v4a.pdf ch02 Software Architecture > 2.1 Architecture Views and Viewpoints(component and connectorビューポイント、processビュー) | I28: CORE | J28: 原則適用。案件スコープ・成果物・規制・リスク上非該当の場合はN/A根拠を記録。 | K28: SRC-SWEBOK-V4A
A29: ARC-037 | B29: SWEBOK | C29: 4. アーキテクチャビューとビューポイント | D29: Medium | E29: デプロイメントビューが実行環境を具体化している | F29: ソフトウェア要素と実行環境(ノード・コンテナ・リージョン・ネットワーク境界)の対応が示され、冗長構成が関係する場合は多重度が読み取れる | G29: 配置ビューが抽象的なままだと、ネットワーク境界・冗長構成・リージョン配置の考慮漏れが本番構築時に発覚し、可用性目標が達成できない。 | H29: swebok-v4a.pdf ch02 Software Architecture > 2.1 Architecture Views and Viewpoints(deploymentビューポイント) | I29: CORE | J29: 原則適用。案件スコープ・成果物・規制・リスク上非該当の場合はN/A根拠を記録。 | K29: SRC-SWEBOK-V4A
A30: ARC-038 | B30: SWEBOK | C30: 4. アーキテクチャビューとビューポイント | D30: Medium | E30: データ/情報の観点が扱われている | F30: 主要データの所在・所有者・ライフサイクル(情報ビュー、ER概要、データフロー等)が、データが重要なシステムにおいて記述されている | G30: データの所在・所有者・ライフサイクルが不明だと、整合性責任の押し付け合いやデータ保護要件の適用漏れが起き、後からの是正コストが大きい。 | H30: swebok-v4a.pdf ch02 Software Architecture > 2.1 Architecture Views and Viewpoints(informationビューポイント) | I30: CORE | J30: 原則適用。案件スコープ・成果物・規制・リスク上非該当の場合はN/A根拠を記録。 | K30: SRC-SWEBOK-V4A
A31: ARC-039 | B31: SWEBOK | C31: 4. アーキテクチャビューとビューポイント | D31: Medium | E31: 図がソース管理可能な形式で保存されている | F31: 図の元データ(PlantUML/Mermaid/drawio等)がリポジトリで管理されている、または更新手段が明記されている | G31: 図の元データが管理されていないと更新できない「化石図」になり、ADが実態と乖離して評価・保守の情報源として機能しなくなる。 | H31: 実務補完(Docs as Code / 図のソース管理) | I31: CORE | J31: 原則適用。案件スコープ・成果物・規制・リスク上非該当の場合はN/A根拠を記録。 | K31: SRC-PRACTICE
A32: ARC-040 | B32: SWEBOK | C32: 4. アーキテクチャビューとビューポイント | D32: Low | E32: 図の粒度が適切に統一されている | F32: 1つの図の中で抽象度が混在していない(クラスレベルとシステムレベルの混在等がない)。要素数が概ね7±2〜20程度に収まるよう分割されている | G32: 1枚の図に抽象度が混在すると読者が着目すべき粒度を見失い、レビューで本質的な構造問題より枝葉の指摘に時間が費やされる。 | H32: 実務補完(C4モデル等の図解プラクティス)+ 2.1(ビューによる複雑さの管理) | I32: CORE | J32: 原則適用。案件スコープ・成果物・規制・リスク上非該当の場合はN/A根拠を記録。 | K32: SRC-PRACTICE
A33: ARC-050 | B33: SWEBOK | C33: 5. アーキテクチャスタイル・パターンと構造 | D33: High | E33: 採用したスタイル/パターンが明記されている | F33: 全体構成のアーキテクチャスタイル(レイヤード、マイクロサービス等)と主要パターンが名前付きで記載されている | G33: 採用スタイル・パターンの名前を明示することは共通語彙による共有理解の基盤であり、これがないと新規参画者が構造の意図を推測で補い誤った拡張をする。 | H33: swebok-v4a.pdf ch02 Software Architecture > 2.2 Architecture Patterns, Styles and Reference Architectures | I33: CORE | J33: 原則適用。案件スコープ・成果物・規制・リスク上非該当の場合はN/A根拠を記録。 | K33: SRC-SWEBOK-V4A
... A42: ARC-CZ01 | B42: クラウド補完 | C42: 5. アーキテクチャスタイル・パターンと構造 | D42: Medium | E42: スケールユニット(共に増減するリソースのまとまり)が設計され、成長時の拡張単位(Deployment Stamps等)としてアーキテクチャ記述に明記されている | F42: アーキテクチャ記述書にスケールユニットの構成要素・拡張増分・上限が定義されている | G42: 拡張単位が未定義だと、成長時に個別リソースの場当たり的増強となり、整合の取れないスケールで性能・信頼性が劣化する。 | H42: Azure Well-Architected Framework > パフォーマンス効率の柱 > PE:05 (Optimizing scaling and partitioning > scale unit design / Deployment Stamps pattern) | I42: CORE | J42: 原則適用。案件スコープ・成果物・規制・リスク上非該当の場合はN/A根拠を記録。 | K42: SRC-AZR-WAF
A43: ARC-060 | B43: SWEBOK | C43: 6. アーキテクチャ意思決定(ADR)と根拠 | D43: Critical | E43: 重要な意思決定がADRとして記録されている | F43: アーキテクチャに影響する主要決定(スタイル選定、主要技術選定、データ管理方針等)がそれぞれ識別子付きのADRとして存在する | G43: アーキテクチャは重要決定のネットワークとして捉えられ、決定を記録しないと後任者が理由不明の構造を壊す変更を加え、過去に棄却済みの悪手を繰り返す。 | H43: swebok-v4a.pdf ch02 Software Architecture > 2.4 Architecture as Significant Decisions | I43: CORE | J43: 原則適用。案件スコープ・成果物・規制・リスク上非該当の場合はN/A根拠を記録。 | K43: SRC-SWEBOK-V4A;SRC-CIS | L43: CONTINUITY-DR
A44: ARC-061 | B44: SWEBOK | C44: 6. アーキテクチャ意思決定(ADR)と根拠 | D44: Critical | E44: 各ADRに検討した代替案が記載されている | F44: 各ADRに採用案以外の代替案が1つ以上、利点・欠点とともに記載されている。代替案なしのADRがない | G44: 検討した代替案と棄却理由の記録は、忘れられた理由で棄却済みの案を将来再び選ぶ事故を防ぎ、条件変化時に決定を再検討する材料になる。 | H44: swebok-v4a.pdf ch02 Software Architecture > 2.4 Architecture as Significant Decisions(rationale: 検討した代替案・棄却理由の記録) | I44: CORE | J44: 原則適用。案件スコープ・成果物・規制・リスク上非該当の場合はN/A根拠を記録。 | K44: SRC-SWEBOK-V4A;SRC-CIS | L44: CONTINUITY-DR
A45: ARC-062 | B45: SWEBOK | C45: 6. アーキテクチャ意思決定(ADR)と根拠 | D45: Critical | E45: 決定の根拠(rationale)とトレードオフが記録されている | F45: 各ADRに「なぜこの案か」の理由と、犠牲にした特性(トレードオフ)が明記されている | G45: 品質属性間のトレードオフこそ設計決定の基盤であり、根拠と犠牲にした特性が残っていないと、決定の妥当性を評価も再検討もできない。 | H45: swebok-v4a.pdf ch02 Software Architecture > 2.4 Architecture as Significant Decisions(rationale、品質属性間のトレードオフ) | I45: CORE | J45: 原則適用。案件スコープ・成果物・規制・リスク上非該当の場合はN/A根拠を記録。 | K45: SRC-SWEBOK-V4A;SRC-CIS | L45: CONTINUITY-DR
A46: ARC-063 | B46: SWEBOK | C46: 6. アーキテクチャ意思決定(ADR)と根拠 | D46: High | E46: ADRにステータスと日付・決定者がある | F46: 各ADRにステータス(提案/承認/廃止/置換)、日付、決定者または合意した関係者が記載されている | G46: ステータス・日付・決定者がないと、その決定が現在有効か廃止済みかを判別できず、無効な決定に基づく実装や責任の所在不明を招く。 | H46: swebok-v4a.pdf ch02 Software Architecture > 2.4 Architecture as Significant Decisions + 実務補完(ADRテンプレート) | I46: CORE | J46: 原則適用。案件スコープ・成果物・規制・リスク上非該当の場合はN/A根拠を記録。 | K46: SRC-SWEBOK-V4A;SRC-CIS;SRC-PRACTICE | L46: CONTINUITY-DR
A47: ARC-064 | B47: SWEBOK | C47: 6. アーキテクチャ意思決定(ADR)と根拠 | D47: High | E47: ADRが対応するASR・制約に紐付いている | F47: 各ADRのコンテキスト欄に、関連するASR・関心事・制約への参照がある | G47: 決定がどの関心事・要求・制約に応えるものかが不明だと、要求変更時にどの決定を見直すべきか特定できず、影響分析が総当たりになる。 | H47: swebok-v4a.pdf ch02 Software Architecture > 2.4 Architecture as Significant Decisions(関心事・要求・資源が決定に影響) | I47: CORE | J47: 原則適用。案件スコープ・成果物・規制・リスク上非該当の場合はN/A根拠を記録。 | K47: SRC-SWEBOK-V4A;SRC-CIS | L47: CONTINUITY-DR
A48: ARC-065 | B48: SWEBOK | C48: 6. アーキテクチャ意思決定(ADR)と根拠 | D48: High | E48: 意図的な技術的負債が記録されている | F48: 期限・コスト都合で引き受けた妥協が、将来影響と返済方針(いつ・何をトリガーに解消するか)とともに記録されている。負債ゼロの場合はその旨の確認記録がある | G48: アーキテクチャ上の技術的負債は将来他者が支払うことになる経済的影響を持つため、記録しないと返済されないまま保守性・進化性を静かに侵食する。 | H48: swebok-v4a.pdf ch02 Software Architecture > 2.4 Architecture as Significant Decisions(architectural technical debt) | I48: CORE | J48: 原則適用。案件スコープ・成果物・規制・リスク上非該当の場合はN/A根拠を記録。 | K48: SRC-SWEBOK-V4A;SRC-CIS | L48: CONTINUITY-DR
A49: ARC-066 | B49: SWEBOK | C49: 6. アーキテクチャ意思決定(ADR)と根拠 | D49: Medium | E49: 廃止・置換されたADRが追跡できる | F49: 置換されたADRが削除されず「置換」ステータスで残り、後継ADRへの参照を持つ | G49: 置換された決定を消してしまうと決定のネットワーク(派生関係)の履歴が失われ、なぜ現在の構造に至ったかを追跡できなくなる。 | H49: swebok-v4a.pdf ch02 Software Architecture > 2.4 Architecture as Significant Decisions(決定のネットワーク、棄却決定の保存) | I49: CORE | J49: 原則適用。案件スコープ・成果物・規制・リスク上非該当の場合はN/A根拠を記録。 | K49: SRC-SWEBOK-V4A;SRC-CIS | L49: CONTINUITY-DR
A50: ARC-067 | B50: SWEBOK | C50: 6. アーキテクチャ意思決定(ADR)と根拠 | D50: Medium | E50: 決定の影響(正負両面)が記載されている | F50: 各ADRに、決定によって生じる正の影響と負の影響・新たな制約が記載されている | G50: 決定は後続の開発プロセスとシステムに深い影響を及ぼすため、負の影響・新たな制約を明示しないと、副作用が想定外の障害として下流工程を直撃する。 | H50: swebok-v4a.pdf ch02 Software Architecture > 2.4 Architecture as Significant Decisions(決定の帰結) | I50: CORE | J50: 原則適用。案件スコープ・成果物・規制・リスク上非該当の場合はN/A根拠を記録。 | K50: SRC-SWEBOK-V4A;SRC-CIS | L50: CONTINUITY-DR
A51: ARC-070 | B51: SWEBOK | C51: 7. 品質特性シナリオと品質属性 | D51: Critical | E51: 優先度の高い品質属性がシナリオ化されている | F51: 優先度「高」の品質属性それぞれについて、品質特性シナリオが少なくとも1つ作成されている | G51: 高優先の品質属性をシナリオ化しないと「高可用」「高性能」が合意なき標語のまま残り、評価もテストも不可能な要求として実装者に丸投げされる。 | H51: swebok-v4a.pdf ch02 Software Architecture > 4.1 "Goodness" in Architecture(ATAM: ユーティリティツリーと品質シナリオ) | I51: CORE | J51: 原則適用。案件スコープ・成果物・規制・リスク上非該当の場合はN/A根拠を記録。 | K51: SRC-SWEBOK-V4A
A52: ARC-071 | B52: SWEBOK | C52: 7. 品質特性シナリオと品質属性 | D52: Critical | E52: シナリオに定量的な応答測定がある | F52: 各シナリオの応答測定が数値または客観判定可能な条件(例: p99 500ms以下、RTO 1時間以内)で書かれている。「高速」「十分」等の定性表現のみのシナリオがない | G52: 応答測定が定量的でないシナリオは充足判定ができず、リリース判定時に「十分速いか」を巡る水掛け論と判断先送りを生む。 | H52: swebok-v4a.pdf ch02 Software Architecture > 4.1(品質シナリオによる評価)+ 実務補完(品質特性シナリオの応答測定、Bass et al.) | I52: CORE | J52: 原則適用。案件スコープ・成果物・規制・リスク上非該当の場合はN/A根拠を記録。 | K52: SRC-SWEBOK-V4A;SRC-PRACTICE
A53: ARC-072 | B53: SWEBOK | C53: 7. 品質特性シナリオと品質属性 | D53: High | E53: シナリオが6要素を備えている | F53: 各シナリオに刺激源・刺激・環境・対象・応答・応答測定が揃っている(表形式または同等の構造) | G53: 6要素が欠けたシナリオは刺激や環境が曖昧で解釈が割れ、設計者とテスト担当が異なる条件を想定して検証の齟齬が生じる。 | H53: 実務補完(品質特性シナリオの6要素、Bass et al.) | I53: CORE | J53: 原則適用。案件スコープ・成果物・規制・リスク上非該当の場合はN/A根拠を記録。 | K53: SRC-PRACTICE
A54: ARC-073 | B54: SWEBOK | C54: 7. 品質特性シナリオと品質属性 | D54: High | E54: 環境条件が通常時以外も扱われている | F54: 品質シナリオの中に、ピーク時・障害時・部分縮退時など通常時以外の環境を扱うものが含まれている | G54: 通常時のみのシナリオでは障害時・ピーク時の振る舞いが設計されず、平常時は健全でも高負荷や部分障害で連鎖的に崩壊するシステムになる。 | H54: 実務補完(品質特性シナリオの環境要素)+ 4.1(ライフタイムを通じた頑健性) | I54: CORE | J54: 原則適用。案件スコープ・成果物・規制・リスク上非該当の場合はN/A根拠を記録。 | K54: SRC-PRACTICE
A55: ARC-074 | B55: SWEBOK | C55: 7. 品質特性シナリオと品質属性 | D55: High | E55: シナリオに優先度が付与されている | F55: 各シナリオにビジネス価値と実現難易度(または同等の2軸)に基づく優先度があり、ユーティリティツリー等で整理されている | G55: シナリオに優先度がないと限られた設計・評価リソースの配分基準がなく、ビジネス価値の低いシナリオに労力を費やし重要リスクを見逃す。 | H55: swebok-v4a.pdf ch02 Software Architecture > 4.1 "Goodness" in Architecture(ATAMのユーティリティツリー) | I55: CORE | J55: 原則適用。案件スコープ・成果物・規制・リスク上非該当の場合はN/A根拠を記録。 | K55: SRC-SWEBOK-V4A
A56: ARC-075 | B56: SWEBOK | C56: 7. 品質特性シナリオと品質属性 | D56: High | E56: 性能・スケーラビリティの根拠がある | F56: 性能要求に対し、想定負荷(スループット・同時利用者数・データ量)と処理方式・スケール方式の対応が数値ベースで説明されている | G56: スケーリング・性能・資源消費の分析はアーキテクチャ設計の典型的関心事であり、数値根拠なしでは容量不足が本番負荷で初めて露呈する。 | H56: swebok-v4a.pdf ch02 Software Architecture > 3.2 Architectural Design(scaling/performance/resource consumptionの分析) | I56: CORE | J56: 原則適用。案件スコープ・成果物・規制・リスク上非該当の場合はN/A根拠を記録。 | K56: SRC-SWEBOK-V4A
A57: ARC-076 | B57: SWEBOK | C57: 7. 品質特性シナリオと品質属性 | D57: Critical | E57: 可用性・障害時の振る舞いが設計されている | F57: 単一障害点の有無が分析され、可用性目標(SLO/RTO/RPO等)と冗長化・フェイルオーバー・復旧の方式が対応付けられている(可用性が関心事であるシステムの場合) | G57: 単一障害点と復旧方式を設計段階で分析しないと、可用性目標が構造で担保されず、障害発生時に復旧手順がその場しのぎになる。 | H57: swebok-v4a.pdf ch02 Software Architecture > 3.2 Architectural Design(信頼性特性の分析)+ 2.1(availabilityビューポイント) | I57: CORE | J57: 原則適用。案件スコープ・成果物・規制・リスク上非該当の場合はN/A根拠を記録。 | K57: SRC-SWEBOK-V4A | L57: RELIABILITY-HA
A58: ARC-077 | B58: SWEBOK | C58: 7. 品質特性シナリオと品質属性 | D58: Critical | E58: セキュリティの主要対策が構造に反映されている | F58: 認証・認可・データ保護(保存時/転送時)・信頼境界がビューまたはADRで特定できる(セキュリティが関心事であるシステムの場合) | G58: セキュリティはシステム全体で扱うべき支配的関心事であり、構造に反映されていないと後付けの対策となり、信頼境界の欠陥が侵害事故に直結する。 | H58: swebok-v4a.pdf ch02 Software Architecture > 3.2 Architectural Design(safety/securityへのシステム全体アプローチ) | I58: CORE | J58: 原則適用。案件スコープ・成果物・規制・リスク上非該当の場合はN/A根拠を記録。 | K58: SRC-SWEBOK-V4A
A59: ARC-078 | B59: SWEBOK | C59: 7. 品質特性シナリオと品質属性 | D59: Medium | E59: 保守性・進化性が検討されている | F59: 将来の変更シナリオ(機能追加・技術更改等)が少なくとも1つ検討され、変更コストの見積もりまたは影響範囲の説明がある | G59: 将来の変更シナリオを検討しないと今日の決定の負債性に気づけず、進化性を欠いた構造が数年後の機能追加コストを跳ね上げる。 | H59: swebok-v4a.pdf ch02 Software Architecture > 4.1 "Goodness" in Architecture(進化への頑健性)/ 2.4(技術的負債) | I59: CORE | J59: 原則適用。案件スコープ・成果物・規制・リスク上非該当の場合はN/A根拠を記録。 | K59: SRC-SWEBOK-V4A
A60: ARC-079 | B60: SWEBOK | C60: 7. 品質特性シナリオと品質属性 | D60: Medium | E60: 観測可能性が設計されている | F60: ログ・メトリクス・トレース等の監視手段と、品質シナリオの応答測定を実運用で計測する方法が記述されている | G60: 品質シナリオの応答測定を実運用で計測する手段がないと、目標達成の検証が永遠にできず、劣化の兆候にも気づけない。 | H60: 実務補完(オブザーバビリティ)+ 4.4 Architecture Metrics(継続的開発でのメトリクス) | I60: CORE | J60: 原則適用。案件スコープ・成果物・規制・リスク上非該当の場合はN/A根拠を記録。 | K60: SRC-PRACTICE
A61: ARC-080 | B61: SWEBOK | C61: 8. アーキテクチャ評価 | D61: Critical | E61: アーキテクチャ評価が実施されている | F61: シナリオベース評価(ATAM/SAAM/QAW等)、構造化レビュー、アクティブレビューのいずれかの実施記録(日付・参加者・手法)がある | G61: 評価をマイルストーンで実施しないと欠陥あるアーキテクチャのまま実装が進み、構造レベルの欠陥は実装後の修正コストが桁違いに大きくなる。 | H61: swebok-v4a.pdf ch02 Software Architecture > 4. Software Architecture Evaluation / 4.3 Architecture Reviews | I61: CORE | J61: 原則適用。案件スコープ・成果物・規制・リスク上非該当の場合はN/A根拠を記録。 | K61: SRC-SWEBOK-V4A
A62: ARC-081 | B62: SWEBOK | C62: 8. アーキテクチャ評価 | D62: Critical | E62: 評価結果がASR/シナリオ単位で記録されている | F62: 優先度「高」のASR・品質シナリオごとに評価結果(充足/リスクあり/未充足)が記録されている | G62: 評価は選択した解がASRを満たすかの検証であり、ASR単位の結果がないと「何となく良さそう」で終わり、リワークが必要な箇所を特定できない。 | H62: swebok-v4a.pdf ch02 Software Architecture > 3.2.3 Architecture Evaluation(ASR充足の検証とリワーク箇所の特定) | I62: CORE | J62: 原則適用。案件スコープ・成果物・規制・リスク上非該当の場合はN/A根拠を記録。 | K62: SRC-SWEBOK-V4A
A63: ARC-082 | B63: SWEBOK | C63: 8. アーキテクチャ評価 | D63: High | E63: リスク・感度点・トレードオフ点が識別されている | F63: 評価から得られたリスク、感度点、トレードオフ点が一覧化され、リスクには対応方針(回避/軽減/受容)が付与されている | G63: 競合する品質要求間のトレードオフ分析が評価の鍵であり、リスク・感度点・トレードオフ点を残さないと、危険な決定がどれか関係者に伝わらない。 | H63: swebok-v4a.pdf ch02 Software Architecture > 4.1 "Goodness" in Architecture(ATAM) | I63: CORE | J63: 原則適用。案件スコープ・成果物・規制・リスク上非該当の場合はN/A根拠を記録。 | K63: SRC-SWEBOK-V4A
A64: ARC-083 | B64: SWEBOK | C64: 8. アーキテクチャ評価 | D64: High | E64: 複数の候補が比較検討された記録がある | F64: 全体アーキテクチャまたは主要決定について、2案以上の候補の比較(評価基準付き)が確認できる | G64: アーキテクチャは代替案の分析・評価の基盤であり、単一案しか検討しない設計は最初の思い付きの追認となり、より良い解を体系的に逃す。 | H64: swebok-v4a.pdf ch02 Software Architecture > 1.3 Uses of Architecture(代替案の分析・評価)/ 3.2.2 Architecture Synthesis(候補解の開発) | I64: CORE | J64: 原則適用。案件スコープ・成果物・規制・リスク上非該当の場合はN/A根拠を記録。 | K64: SRC-SWEBOK-V4A
A65: ARC-084 | B65: SWEBOK | C65: 8. アーキテクチャ評価 | D65: High | E65: 評価者に作成者以外が含まれている | F65: 評価・レビューの参加者に、アーキテクチャ作成者以外のレビューア(可能なら運用・セキュリティ等の別観点)が含まれている | G65: 評価は典型的には第三者による査定として行われるものであり、作成者のみの自己評価では思い込みによる盲点(暗黙の前提)を検出できない。 | H65: swebok-v4a.pdf ch02 Software Architecture > 4.1 "Goodness" in Architecture(第三者による評価)/ 4.3 Architecture Reviews | I65: CORE | J65: 原則適用。案件スコープ・成果物・規制・リスク上非該当の場合はN/A根拠を記録。 | K65: SRC-SWEBOK-V4A
A66: ARC-085 | B66: SWEBOK | C66: 8. アーキテクチャ評価 | D66: Medium | E66: ユースケースによる完全性・一貫性確認が行われている | F66: 主要ユースケースをアーキテクチャ上でウォークスルーし、要素・インタフェースの欠落がないことを確認した記録がある | G66: ユースケースの各ステップと構成要素の突き合わせは完全性・一貫性の実証的な確認手段であり、怠るとインタフェースや要素の欠落が実装で発覚する。 | H66: swebok-v4a.pdf ch02 Software Architecture > 4.2 Reasoning about Architectures(ユースケースによる完全性・一貫性の確認) | I66: CORE | J66: 原則適用。案件スコープ・成果物・規制・リスク上非該当の場合はN/A根拠を記録。 | K66: SRC-SWEBOK-V4A
A67: ARC-086 | B67: SWEBOK | C67: 8. アーキテクチャ評価 | D67: Medium | E67: 評価指摘のフォローアップが管理されている | F67: 評価で挙がった指摘・課題が課題管理(チケット等)に登録され、対応状況が追跡できる | G67: レビューの目的はリスクの識別であり、指摘を追跡管理しないと発見済みのリスクが放置され、評価の実施自体が形骸化する。 | H67: swebok-v4a.pdf ch02 Software Architecture > 4.3 Architecture Reviews + 実務補完(指摘のトラッキング) | I67: CORE | J67: 原則適用。案件スコープ・成果物・規制・リスク上非該当の場合はN/A根拠を記録。 | K67: SRC-SWEBOK-V4A;SRC-PRACTICE
A68: ARC-087 | B68: SWEBOK | C68: 8. アーキテクチャ評価 | D68: Low | E68: 実現可能性がプロトタイプ等で裏付けられている | F68: 技術的に不確実な箇所について、PoC・技術スパイク・ベンチマークによる裏付け、または未実施の場合はリスクとしての記録がある | G68: 技術的に不確実な箇所を検証なしに採用すると、実現不能性がプロジェクト後半に発覚し、実現可能性・費用対効果という評価基準を満たせない。 | H68: swebok-v4a.pdf ch02 Software Architecture > 4.1 "Goodness" in Architecture(実現可能性・費用対効果)+ 実務補完(PoC/技術スパイク) | I68: CORE | J68: 原則適用。案件スコープ・成果物・規制・リスク上非該当の場合はN/A根拠を記録。 | K68: SRC-SWEBOK-V4A;SRC-PRACTICE
A69: ARC-090 | B69: SWEBOK | C69: 9. 技術選定 | D69: Critical | E69: 主要技術の選定理由が文書化されている | F69: 言語・フレームワーク・データストア・クラウドサービス等の主要技術それぞれに選定理由(技術選定書またはADR)が存在する | G69: 主要技術の選定はアーキテクチャに深い影響を与える重要決定であり、理由が残っていないと更改時に採用意図が分からず、安易な置き換えや不合理な固執を招く。 | H69: swebok-v4a.pdf ch02 Software Architecture > 2.4 Architecture as Significant Decisions(技術選定を含む重要決定の文書化) | I69: CORE | J69: 原則適用。案件スコープ・成果物・規制・リスク上非該当の場合はN/A根拠を記録。 | K69: SRC-SWEBOK-V4A;SRC-CIS
... A71: ARC-092 | B71: SWEBOK | C71: 9. 技術選定 | D71: High | E71: 選定基準にASR・制約との対応がある | F71: 評価基準がASR・品質属性・制約から導出されており、恣意的な基準のみで選定されていない | G71: 評価基準がASR・制約から導出されていないと、システムの品質要求と無関係な好みで技術が選ばれ、選定した技術がASRを満たせないリスクを見逃す。 | H71: swebok-v4a.pdf ch02 Software Architecture > 3.2.1 Architecture Analysis(ASR)+ 2.4(要求・制約が決定に影響) | I71: CORE | J71: 原則適用。案件スコープ・成果物・規制・リスク上非該当の場合はN/A根拠を記録。 | K71: SRC-SWEBOK-V4A
A72: ARC-093 | B72: SWEBOK | C72: 9. 技術選定 | D72: Medium | E72: ライセンス・コストが確認されている | F72: 採用技術のライセンス条件(商用利用可否・コピーレフト等)と、ランニングコストの見積もりが記録されている | G72: ライセンス条件の見落としはソース公開義務や商用利用不可という法的問題に、コスト未見積もりは運用予算の破綻に直結する。 | H72: 実務補完(OSSライセンス・TCO評価) | I72: CORE | J72: 原則適用。案件スコープ・成果物・規制・リスク上非該当の場合はN/A根拠を記録。 | K72: SRC-PRACTICE | L72: COST
A73: ARC-094 | B73: SWEBOK | C73: 9. 技術選定 | D73: Medium | E73: 技術の継続性リスクが評価されている | F73: 採用技術のEOL・メンテナンス状況・コミュニティ/ベンダーサポートが確認され、撤退・移行の困難さ(ロックイン)が言及されている | G73: EOLやベンダーロックインを評価しないと、採用技術の突然のサポート終了で計画外の大規模移行を強いられ、進化性が外部要因で失われる。 | H73: 実務補完(技術ライフサイクル・ロックイン評価)+ 4.1(ライフタイムを通じた頑健性) | I73: CORE | J73: 原則適用。案件スコープ・成果物・規制・リスク上非該当の場合はN/A根拠を記録。 | K73: SRC-PRACTICE
A74: ARC-095 | B74: SWEBOK | C74: 9. 技術選定 | D74: Low | E74: 検証結果が選定根拠に含まれている | F74: 比較の根拠に一次情報(公式ドキュメント、実測ベンチマーク、PoC結果)が含まれ、伝聞のみで決定されていない | G74: 伝聞や評判のみに基づく選定は自環境での適合性を保証せず、想定と異なる性能・制約が導入後に発覚して撤退コストを支払うことになる。 | H74: 実務補完(一次情報・実測による裏付け) | I74: CORE | J74: 原則適用。案件スコープ・成果物・規制・リスク上非該当の場合はN/A根拠を記録。 | K74: SRC-PRACTICE
A75: ARC-100 | B75: SWEBOK | C75: 10. 記述品質・管理・実装統制 | D75: High | E75: ADが版管理されている | F75: ADにバージョン・変更履歴があり、構成管理(リポジトリ等)下に置かれている | G75: ADはシステムの進化や人の入れ替わりの中で共有理解を支える作業成果物であり、版管理がないとどれが現行かが分からず、古い記述に基づく判断ミスを生む。 | H75: swebok-v4a.pdf ch02 Software Architecture > 2. Software Architecture Description(作業成果物としてのAD)+ 実務補完(構成管理) | I75: CORE | J75: 原則適用。案件スコープ・成果物・規制・リスク上非該当の場合はN/A根拠を記録。 | K75: SRC-SWEBOK-V4A;SRC-PRACTICE
A76: ARC-101 | B76: SWEBOK | C76: 10. 記述品質・管理・実装統制 | D76: High | E76: ステークホルダーの承認記録がある | F76: ADについて、主要ステークホルダーによるレビュー・承認の記録(日付・承認者)がある | G76: ADは関心事を持つステークホルダーに向けた文書であり、承認記録がないと合意なき設計として後から覆され、実装済み部分の手戻りが発生する。 | H76: swebok-v4a.pdf ch02 Software Architecture > 2. Software Architecture Description(ステークホルダーへの対応)+ 実務補完(承認プロセス) | I76: CORE | J76: 原則適用。案件スコープ・成果物・規制・リスク上非該当の場合はN/A根拠を記録。 | K76: SRC-SWEBOK-V4A;SRC-PRACTICE
A77: ARC-102 | B77: SWEBOK | C77: 10. 記述品質・管理・実装統制 | D77: High | E77: 用語が定義され一貫している | F77: 用語集があり、同一概念に複数の名称を使っていない。SWEBOK/JIS等の定訳がある用語は定訳を使用している | G77: ビューポイントの語彙は関係者の共有された表現手段であり、同一概念に複数名称が混在すると別物と誤認され、設計議論と実装の齟齬を生む。 | H77: swebok-v4a.pdf ch02 Software Architecture > 2.1 Architecture Views and Viewpoints(共有語彙としてのビューポイント言語) | I77: CORE | J77: 原則適用。案件スコープ・成果物・規制・リスク上非該当の場合はN/A根拠を記録。 | K77: SRC-SWEBOK-V4A
A78: ARC-103 | B78: SWEBOK | C78: 10. 記述品質・管理・実装統制 | D78: High | E78: 実装統制の仕組みが定義されている | F78: 実装がADに準拠していることを確認する方法(依存関係チェック、適合性テスト、レビュー観点等)が文書化されている | G78: 実装がアーキテクチャに準拠していることの監督・認証(architecture implementation)を欠くと、ADと実装が乖離し、設計上の品質保証が実体を失う。 | H78: swebok-v4a.pdf ch02 Software Architecture > 3.4 Architecting in the Large(architecture implementation: 準拠の認証) | I78: CORE | J78: 原則適用。案件スコープ・成果物・規制・リスク上非該当の場合はN/A根拠を記録。 | K78: SRC-SWEBOK-V4A
A79: ARC-104 | B79: SWEBOK | C79: 10. 記述品質・管理・実装統制 | D79: Medium | E79: アーキテクチャメトリクスが定義されている | F79: 構造メトリクス(循環依存、結合度・凝集度、準拠度等)またはプロセスメトリクス(リードタイム、デプロイ頻度、MTTR、変更失敗率等)のうち、計測するものと計測方法が定義されている | G79: 依存・結合度などの構造メトリクスやDevOps系プロセスメトリクスを定義しないと、アーキテクチャの劣化を定量的に検知できず、気づいたときには修復困難になっている。 | H79: swebok-v4a.pdf ch02 Software Architecture > 4.4 Architecture Metrics | I79: CORE | J79: 原則適用。案件スコープ・成果物・規制・リスク上非該当の場合はN/A根拠を記録。 | K79: SRC-SWEBOK-V4A | L79: OPS-OBSERVABILITY
A80: ARC-105 | B80: SWEBOK | C80: 10. 記述品質・管理・実装統制 | D80: Medium | E80: ADの更新・見直しプロセスがある | F80: ADを更新するトリガー(重要決定の追加、乖離の検知、定期見直し)と更新責任者が定められている | G80: 実装後のアーキテクチャの管理・拡張(architecture maintenance)の仕組みがないと、ADが初回リリース時点で凍結され、以降の変更が無統制に積み重なる。 | H80: swebok-v4a.pdf ch02 Software Architecture > 3.4 Architecting in the Large(architecture maintenance) | I80: CORE | J80: 原則適用。案件スコープ・成果物・規制・リスク上非該当の場合はN/A根拠を記録。 | K80: SRC-SWEBOK-V4A
A81: ARC-106 | B81: SWEBOK | C81: 10. 記述品質・管理・実装統制 | D81: Medium | E81: 文書が自己完結的に読める | F81: 対象読者が前提知識・参照文書を辿れる(参照文書一覧がある)、略語が初出で展開されている、リンク切れ・参照先欠落がない | G81: 参照を辿れない・略語が展開されない文書は新規参画者の理解を阻害し、ADの主目的である共有理解の形成が果たせない。 | H81: 実務補完(ドキュメント品質)+ 1.3 Uses of Architecture(共有理解の形成) | I81: CORE | J81: 原則適用。案件スコープ・成果物・規制・リスク上非該当の場合はN/A根拠を記録。 | K81: SRC-PRACTICE
A82: ARC-107 | B82: SWEBOK | C82: 10. 記述品質・管理・実装統制 | D82: Low | E82: 表・図のマークダウン/フォーマットが正しい | F82: 表が崩れていない、見出し階層が正しい、図が参照どおりに存在する | G82: 表崩れや参照切れは内容以前に文書の信頼性を損ない、読者が細部の正確さ全体を疑って文書自体が使われなくなる。 | H82: 実務補完(ドキュメント品質) | I82: CORE | J82: 原則適用。案件スコープ・成果物・規制・リスク上非該当の場合はN/A根拠を記録。 | K82: SRC-PRACTICE
A83: ARC-902 | B83: 追加承認 | C83: 10. 記述品質・管理・実装統制 | D83: Low | E83: アーキテクチャ知識が組織で共有・再利用できる形で管理されている | F83: ADR・教訓・ビューポイント定義・技術評価結果などのアーキテクチャ資産の保管場所と共有方法(リポジトリ、ナレッジベース等)が定められ、他プロジェクトから参照可能である。または本プロジェクト内で完結する理由が記載されている | G83: 決定や教訓がプロジェクト内に閉じると、組織内の別チームが同じ技術評価や失敗を繰り返し、アーキテクチャ検討のコストが毎回ゼロから発生する。 | H83: swebok-v4a.pdf ch02 Software Architecture > 3.4 Architecting in the Large — アーキテクチャ知識管理(architecture knowledge management) | I83: CORE | J83: 原則適用。案件スコープ・成果物・規制・リスク上非該当の場合はN/A根拠を記録。 | K83: SRC-SWEBOK-V4A

Sheet 03_詳細設計
A1: ID | B1: 区分 | C1: カテゴリ | D1: 基準重要度 | E1: チェック項目 | F1: 合格基準 | G1: 意図(なぜ確認するか) | H1: 対象ドキュメント(参照箇所) | I1: 適用プロファイル | J1: 適用条件 | K1: 出典ID | L1: 重複統制グループ | M1: 案件重要度 | N1: 適用判定 | O1: 判定 | P1: 証跡・参照箇所 | Q1: 指摘・Issue ID | R1: 対応方針 | S1: 例外・リスク受容承認者 | T1: 是正期限 | U1: レビュアー | V1: レビュー日 | W1: 再確認結果
A2: DES-001 | B2: SWEBOK | C2: 1. 全般・トレーサビリティ | D2: Critical | E2: 要求から設計へのトレーサビリティが確保されている | F2: 要求ID と設計項目の対応表が存在し、対象範囲の全機能要求が少なくとも1つの設計項目に対応付いている | G2: 要求に対応しない設計(実装漏れ)や、要求のない勝手な作り込みを防ぐ。対応表がないと、テスト工程で要求の実現有無を検証できず大規模な手戻りになる。 | H2: swebok-v4a.pdf ch03 Software Design > 1.2 Context of Software Design(要求との関係)/ 1.4 Completeness(要求に対する設計の完全性) | I2: CORE | J2: 原則適用。案件スコープ・成果物・規制・リスク上非該当の場合はN/A根拠を記録。 | K2: SRC-SWEBOK-V4A
A3: DES-002 | B3: SWEBOK | C3: 1. 全般・トレーサビリティ | D3: Critical | E3: アーキテクチャ設計との整合が取れている | F3: アーキテクチャ設計書に記載されたレイヤ構造・技術選定・通信方式・横断的関心事の戦略に反する設計記述がない | G3: アーキテクチャが定めた制約(構成要素・API・スタイル・原則)に反する詳細設計は、統合時に構造の破綻や作り直しを招く。上位設計との矛盾を実装前に検出する。 | H3: swebok-v4a.pdf ch03 Software Design > 1.2 Context of Software Design(アーキテクチャとの関係)/ 2.2 Detailed Design(上位設計の制約下で進める) | I3: CORE | J3: 原則適用。案件スコープ・成果物・規制・リスク上非該当の場合はN/A根拠を記録。 | K3: SRC-SWEBOK-V4A
A4: DES-003 | B4: SWEBOK | C4: 1. 全般・トレーサビリティ | D4: High | E4: 非機能要求が設計に反映されている | F4: 性能・可用性・セキュリティ等の非機能要求それぞれについて、対応する設計方針の記載箇所を指し示せる | G4: 性能・セキュリティ等の品質懸念は全設計アプローチが扱うべき基本課題であり、後付け対応はほぼ不可能。設計時点で対応方針を持たないと本番で品質要求未達が露見する。 | H4: swebok-v4a.pdf ch03 Software Design > 1.3 Key Issues in Software Design / 3. Software Design Qualities | I4: CORE | J4: 原則適用。案件スコープ・成果物・規制・リスク上非該当の場合はN/A根拠を記録。 | K4: SRC-SWEBOK-V4A
A5: DES-004 | B5: SWEBOK | C5: 1. 全般・トレーサビリティ | D5: High | E5: 設計書の対象範囲と対象外が明記されている | F5: 「目的」「対象読者」「対象範囲」「対象外」の節が存在し、対象外項目には理由が書かれている | G5: 範囲が曖昧だと「書かれていない部分」が設計漏れなのか対象外なのか判別できず、レビューの網羅性が保証できない。読者と用途を意識した設計記述の前提となる。 | H5: swebok-v4a.pdf ch03 Software Design > 4. Recording Software Designs(読者・主題・用途に応じた設計仕様の決定) | I5: CORE | J5: 原則適用。案件スコープ・成果物・規制・リスク上非該当の場合はN/A根拠を記録。 | K5: SRC-SWEBOK-V4A
A6: DES-005 | B6: SWEBOK | C6: 1. 全般・トレーサビリティ | D6: High | E6: 用語が統一されている | F6: 同一概念に複数の名称が使われていない(用語定義または用語集があり、本文がそれに従っている) | G6: 設計は問題と解を表現する語彙を作る言語的活動であり、同一概念に複数名称があると実装者間で解釈が割れ、命名の不整合がそのままコードの不整合になる。 | H6: swebok-v4a.pdf ch03 Software Design > 1.1 Design Thinking(語彙の創出)/ 1.4 Uniformity | I6: CORE | J6: 原則適用。案件スコープ・成果物・規制・リスク上非該当の場合はN/A根拠を記録。 | K6: SRC-SWEBOK-V4A
A7: DES-006 | B7: SWEBOK | C7: 1. 全般・トレーサビリティ | D7: Medium | E7: 参照文書が特定可能である | F7: 参照する要求仕様書・アーキテクチャ設計書等が文書名+版数で列挙されている | G7: 参照文書の版が特定できないと、古い要求仕様を前提に設計・実装してしまう事故が起きる。設計変更時の影響追跡の起点にもなる。 | H7: 実務補完(IEEE 1016 SDD 実務・構成管理) | I7: CORE | J7: 原則適用。案件スコープ・成果物・規制・リスク上非該当の場合はN/A根拠を記録。 | K7: SRC-IEEE-GENERAL;SRC-PRACTICE
A8: DES-007 | B8: SWEBOK | C8: 1. 全般・トレーサビリティ | D8: Medium | E8: 実装可能な粒度まで詳細化されている | F8: 実装者の裁量として残る事項がアルゴリズムの局所的な実装詳細に限られる(モジュール責務・インタフェース・データ構造に未決定事項がない) | G8: 詳細設計は「プログラマが構築工程でコーディングできる十分な詳細さ」が完了条件。粒度不足は実装者ごとの独自判断を生み、結合時の不整合と手戻りを招く。 | H8: swebok-v4a.pdf ch03 Software Design > 2.2 Detailed Design(構築を可能にする詳細度) | I8: CORE | J8: 原則適用。案件スコープ・成果物・規制・リスク上非該当の場合はN/A根拠を記録。 | K8: SRC-SWEBOK-V4A
A9: DES-008 | B9: SWEBOK | C9: 1. 全般・トレーサビリティ | D9: Low | E9: 版管理情報がある | F9: 版数・改訂日・改訂内容の履歴が記載されている | G9: 版管理がないと、どの版をレビュー・承認したのか、実装がどの版に基づくのかが追えず、変更の見落としによる実装差異が発生する。 | H9: 実務補完(構成管理実務) | I9: CORE | J9: 原則適用。案件スコープ・成果物・規制・リスク上非該当の場合はN/A根拠を記録。 | K9: SRC-PRACTICE
A10: DES-010 | B10: SWEBOK | C10: 2. モジュール構造・設計原則 | D10: Critical | E10: モジュール一覧と責務が定義されている | F10: 対象コンポーネント内の全モジュールについて、名称と1〜2文の責務記述が存在する | G10: モジュール化は大きなソフトウェアを理解・保守可能にする基本原則。責務が未定義のモジュールは責務の重複・漏れを生み、どこに何を実装すべきか実装者が判断できない。 | H10: swebok-v4a.pdf ch03 Software Design > 1.4 Modularization / 2.2 Detailed Design(モジュールへの設計責務の割当て) | I10: CORE | J10: 原則適用。案件スコープ・成果物・規制・リスク上非該当の場合はN/A根拠を記録。 | K10: SRC-SWEBOK-V4A
A11: DES-011 | B11: SWEBOK | C11: 2. モジュール構造・設計原則 | D11: Critical | E11: モジュール間に循環依存がない | F11: 依存関係図において循環(A→B→A 等)が存在しない。存在する場合は解消策が明記されている | G11: 循環依存は疎結合の原則に反し、単体テスト不能・ビルド順序の破綻・修正影響の波及拡大を招く。設計段階でしか安価に解消できない。 | H11: swebok-v4a.pdf ch03 Software Design > 1.4 Coupling(疎結合の原則) | I11: CORE | J11: 原則適用。案件スコープ・成果物・規制・リスク上非該当の場合はN/A根拠を記録。 | K11: SRC-SWEBOK-V4A
A12: DES-012 | B12: SWEBOK | C12: 2. モジュール構造・設計原則 | D12: High | E12: 単一責任の原則に適合している | F12: 各モジュールの責務記述が単一の関心事で表現でき、「〜と〜と〜を行う」のような複数責務の羅列になっていない | G12: 複数責務を抱えるモジュールは変更理由が複数になり、無関係な修正が相互に影響して劣化が加速する。Parnas の単一責任と高凝集の原則の実地検証。 | H12: swebok-v4a.pdf ch03 Software Design > 1.4 Modularization(Parnasの単一責任)・Cohesion / 5.4 Object-Oriented Design(SOLID) | I12: CORE | J12: 原則適用。案件スコープ・成果物・規制・リスク上非該当の場合はN/A根拠を記録。 | K12: SRC-SWEBOK-V4A
A13: DES-013 | B13: SWEBOK | C13: 2. モジュール構造・設計原則 | D13: High | E13: カプセル化(情報隠蔽)が守られている | F13: 各モジュールの公開インタフェースと内部(非公開)要素が区別して記述され、内部データ構造への外部からの直接アクセスがない | G13: 内部構造が外部から直接触られると、内部変更が広範囲の呼び出し元を壊す。情報隠蔽により利用者がインタフェースの本質だけに集中でき、変更の影響が局所化される。 | H13: swebok-v4a.pdf ch03 Software Design > 1.4 Encapsulation (information hiding) | I13: CORE | J13: 原則適用。案件スコープ・成果物・規制・リスク上非該当の場合はN/A根拠を記録。 | K13: SRC-SWEBOK-V4A
... A21: DES-020 | B21: SWEBOK | C21: 3. インターフェース仕様(API仕様) | D21: Critical | E21: 全エンドポイントの入出力が型レベルで定義されている | F21: 各API について、リクエスト/レスポンスの全フィールドに型・必須/任意・制約(桁、範囲、形式)が定義されている | G21: 型・制約が未定義のAPIは、クライアント側とサーバ側で解釈が食い違い、結合テストで大量の不整合が噴出する。インタフェース定義は部品間契約の根幹。 | H21: swebok-v4a.pdf ch03 Software Design > 2.1 High-Level Design(データ形式・プロトコルの仕様化)/ 4.2 Structural Design Descriptions(IDL) | I21: CORE | J21: 原則適用。案件スコープ・成果物・規制・リスク上非該当の場合はN/A根拠を記録。 | K21: SRC-SWEBOK-V4A
A22: DES-021 | B22: SWEBOK | C22: 3. インターフェース仕様(API仕様) | D22: Critical | E22: 認証・認可方式が定義されている | F22: 認証方式(トークン形式、取得・更新方法)と、API/リソースごとの必要権限が記述されている | G22: 認証・認可が仕様化されていないAPIは、認可漏れによる不正アクセス・情報漏えいに直結する。誰が何にアクセスできるかは設計時に決めるべきセキュリティの基本。 | H22: swebok-v4a.pdf ch03 Software Design > 3.7 Assurance, Security, and Safety(不正な開示・変更・アクセスの防止) | I22: CORE | J22: 原則適用。案件スコープ・成果物・規制・リスク上非該当の場合はN/A根拠を記録。 | K22: SRC-SWEBOK-V4A | L22: SEC-IAM
A23: DES-022 | B23: SWEBOK | C23: 3. インターフェース仕様(API仕様) | D23: Critical | E23: エラーレスポンスが仕様化されている | F23: エラーコード体系、HTTPステータスとの対応、エラーレスポンスのスキーマが定義され、各APIで発生しうるエラーが列挙されている | G23: エラー仕様がないとクライアントは異常時の挙動を実装できず、障害時に原因不明のまま処理が続行される。エラーの体系化は例外処理設計の外部仕様側の要。 | H23: swebok-v4a.pdf ch03 Software Design > 3.5 Errors and Exception Handling, Fault Tolerance | I23: CORE | J23: 原則適用。案件スコープ・成果物・規制・リスク上非該当の場合はN/A根拠を記録。 | K23: SRC-SWEBOK-V4A
A24: DES-023 | B24: SWEBOK | C24: 3. インターフェース仕様(API仕様) | D24: High | E24: 呼び出し側が仕様のみで実装可能である | F24: 実装コードを参照しなくても、リクエスト例・レスポンス例からクライアントを実装できる(主要APIに具体例が付いている) | G24: SWEBOKは「クライアント側の設計者がコードを読まずにサービスを正しく利用できる詳細度」を求める。仕様だけで実装できないAPIは、問い合わせと実装の相互参照でチーム間の待ちが発生する。 | H24: swebok-v4a.pdf ch03 Software Design > 2. Software Design Processes(high-level design stage:コードを読まずに利用可能な定義) | I24: CORE | J24: 原則適用。案件スコープ・成果物・規制・リスク上非該当の場合はN/A根拠を記録。 | K24: SRC-SWEBOK-V4A
A25: DES-024 | B25: SWEBOK | C25: 3. インターフェース仕様(API仕様) | D25: High | E25: 冪等性・リトライ方針が定義されている | F25: 更新系APIごとに冪等性の有無が明記され、非冪等なAPIには二重実行対策(冪等キー等)またはリトライ禁止の記述がある | G25: ネットワーク越しの呼び出しは失敗と再送が前提。冪等性が未定義だとリトライで二重決済・二重登録などの業務事故が起きる。 | H25: swebok-v4a.pdf ch03 Software Design > 3.4 Distribution of Components(信頼性)/ 実務補完(分散システム設計実務) | I25: CORE | J25: 原則適用。案件スコープ・成果物・規制・リスク上非該当の場合はN/A根拠を記録。 | K25: SRC-SWEBOK-V4A;SRC-PRACTICE
A26: DES-025 | B26: SWEBOK | C26: 3. インターフェース仕様(API仕様) | D26: High | E26: バリデーション仕様が記述されている | F26: 入力チェックの内容(形式・範囲・相関チェック)と、違反時のエラーコードが項目ごとに定義されている | G26: 入力検証の仕様が曖昧だと、チェック漏れがインジェクション等の脆弱性やデータ汚染につながり、また画面側とAPI側で検証基準が食い違う。 | H26: swebok-v4a.pdf ch03 Software Design > 3.7 Assurance, Security, and Safety / 実務補完(入力検証実務) | I26: CORE | J26: 原則適用。案件スコープ・成果物・規制・リスク上非該当の場合はN/A根拠を記録。 | K26: SRC-SWEBOK-V4A;SRC-PRACTICE
A27: DES-026 | B27: SWEBOK | C27: 3. インターフェース仕様(API仕様) | D27: High | E27: 互換性・バージョニング方針がある | F27: APIバージョンの付与方法と、後方互換性を壊す変更/壊さない変更の扱いが定義されている | G27: バージョニング方針がないと、API変更のたびに既存クライアントが黙って壊れる。互換性の線引きを事前に決めることが変更容易性の前提になる。 | H27: 実務補完(API管理実務)/ 3.8 Variability(変種の管理) | I27: CORE | J27: 原則適用。案件スコープ・成果物・規制・リスク上非該当の場合はN/A根拠を記録。 | K27: SRC-PRACTICE
A28: DES-027 | B28: SWEBOK | C28: 3. インターフェース仕様(API仕様) | D28: Medium | E28: 共通規約が定義されている | F28: データ形式(JSON等)、文字コード、日時形式(タイムゾーン含む)、ページネーション、ソート指定の共通規約が1箇所に定義されている | G28: 日時形式・ページネーション等がAPIごとにバラバラだと、クライアント実装の分岐が増えタイムゾーン起因等の不具合が量産される。共通問題には共通解を与える一貫性の原則。 | H28: swebok-v4a.pdf ch03 Software Design > 1.4 Uniformity(共通・反復する問題への共通解) | I28: CORE | J28: 原則適用。案件スコープ・成果物・規制・リスク上非該当の場合はN/A根拠を記録。 | K28: SRC-SWEBOK-V4A
A29: DES-028 | B29: SWEBOK | C29: 3. インターフェース仕様(API仕様) | D29: Medium | E29: 機械可読な仕様(OpenAPI 等)と本文が一致している | F29: OpenAPI 等の定義ファイルが存在する場合、設計書本文との間で エンドポイント・スキーマの不一致がない | G29: 文書とモデル(OpenAPI等)が乖離すると、どちらを信じるかで実装が割れる。モデルベースの記録では情報源間の整合が担保されて初めて分析・自動化の利点が生きる。 | H29: swebok-v4a.pdf ch03 Software Design > 4.1 Model-Based Design(文書ベース記述の曖昧さ・分散の克服) | I29: CORE | J29: 原則適用。案件スコープ・成果物・規制・リスク上非該当の場合はN/A根拠を記録。 | K29: SRC-SWEBOK-V4A
A30: DES-029 | B30: SWEBOK | C30: 3. インターフェース仕様(API仕様) | D30: Medium | E30: レート制限・ペイロード上限が定義されている | F30: 上限値(件数、サイズ、頻度)と超過時の応答が記述されている。不要な場合は対象外の根拠がある | G30: 上限が未定義だと、大量リクエストや巨大ペイロードで資源枯渇・サービス停止が起き、超過時挙動が実装依存になってクライアントが対処できない。 | H30: 実務補完(API運用実務)/ 3.4 Distribution of Components(スケーラビリティ・可用性) | I30: CORE | J30: 原則適用。案件スコープ・成果物・規制・リスク上非該当の場合はN/A根拠を記録。 | K30: SRC-PRACTICE
A31: DES-030 | B31: SWEBOK | C31: 3. インターフェース仕様(API仕様) | D31: Low | E31: 非推奨化(deprecation)の手順が定義されている | F31: API 廃止時の告知方法・猶予期間の方針が記載されている | G31: 廃止手順がないと、利用中のクライアントに予告なくAPIが消えて障害になる。互換性維持と廃止のライフサイクル管理はAPI提供側の責務。 | H31: 実務補完(APIライフサイクル管理) | I31: CORE | J31: 原則適用。案件スコープ・成果物・規制・リスク上非該当の場合はN/A根拠を記録。 | K31: SRC-PRACTICE
A32: DES-903 | B32: 追加承認 | C32: 3. インターフェース仕様(API仕様) | D32: High | E32: 外部システムとの連携仕様が定義されている | F32: 連携する外部システムごとに、接続方式(プロトコル)、データ形式と変換規則、連携タイミング(リアルタイム/バッチ)、責任分界点が記載され、相手方仕様書(版数付き)への参照がある | G32: 外部連携の仕様齟齬は結合テスト終盤や本番稼働後に発覚しやすく、相手方調整を伴うため修正コストが極めて高い。設計時に双方の合意事項を明文化して手戻りを防ぐ。 | H32: swebok-v4a.pdf ch03 Software Design > 3.6 Integration and Interoperability — 異種システム間の統合・相互運用性の設計 | I32: CORE | J32: 原則適用。案件スコープ・成果物・規制・リスク上非該当の場合はN/A根拠を記録。 | K32: SRC-SWEBOK-V4A
A33: DES-031 | B33: SWEBOK | C33: 4. データモデル/ER図 | D33: Critical | E33: 全エンティティに主キーが定義されている | F33: ER図/テーブル定義の全エンティティに主キー(または一意識別子)が明示されている | G33: 主キーのないエンティティは行の同一性を識別できず、更新・削除の誤対象や重複データの温床になる。データ永続化設計の最低条件。 | H33: swebok-v4a.pdf ch03 Software Design > 3.3 Data Persistence / 4.2 Structural Design Descriptions(ERD) | I33: CORE | J33: 原則適用。案件スコープ・成果物・規制・リスク上非該当の場合はN/A根拠を記録。 | K33: SRC-SWEBOK-V4A
A34: DES-032 | B34: SWEBOK | C34: 4. データモデル/ER図 | D34: Critical | E34: リレーションシップと多重度が定義されている | F34: エンティティ間の関係すべてに多重度(1:1, 1:N, N:M)が記載され、N:M は交差エンティティで解決されている | G34: 多重度が曖昧だと「1件か複数か」の解釈違いがテーブル構造・画面・APIの全域に波及する。N:M の未解決は物理設計に落とせない。 | H34: swebok-v4a.pdf ch03 Software Design > 4.2 Structural Design Descriptions(ERD:概念・論理・物理モデル) | I34: CORE | J34: 原則適用。案件スコープ・成果物・規制・リスク上非該当の場合はN/A根拠を記録。 | K34: SRC-SWEBOK-V4A
... A39: DES-037 | B39: SWEBOK | C39: 4. データモデル/ER図 | D39: High | E39: データライフサイクルが定義されている | F39: 各エンティティについて作成・更新・削除の契機、保持期間、アーカイブ/物理削除の方針が記述されている | G39: データの生成から廃棄までの管理はデータ永続化設計の一部。保持期間・削除方針がないと、データが無限に増えて性能・コスト・法令(保存義務/消去義務)の問題を起こす。 | H39: swebok-v4a.pdf ch03 Software Design > 3.3 Data Persistence(システム全体を通じたデータの保存と管理) | I39: CORE | J39: 原則適用。案件スコープ・成果物・規制・リスク上非該当の場合はN/A根拠を記録。 | K39: SRC-SWEBOK-V4A
A40: DES-038 | B40: SWEBOK | C40: 4. データモデル/ER図 | D40: High | E40: 個人情報・機密データの保護方針が定義されている | F40: 個人情報・秘密情報に該当するカラムが識別され、暗号化・マスキング・アクセス制御の方針が記載されている。該当がない場合はその旨の明記がある | G40: 個人情報カラムの識別漏れは、漏えい時の被害拡大と法令違反に直結する。情報の不正開示防止はセキュリティ設計の中心課題であり、後付けの暗号化は移行が困難。 | H40: swebok-v4a.pdf ch03 Software Design > 3.7 Assurance, Security, and Safety(不正な開示の防止) | I40: CORE | J40: 原則適用。案件スコープ・成果物・規制・リスク上非該当の場合はN/A根拠を記録。 | K40: SRC-SWEBOK-V4A | L40: PRIVACY
A41: DES-039 | B41: SWEBOK | C41: 4. データモデル/ER図 | D41: Medium | E41: 論理削除・履歴管理の方式が統一されている | F41: 論理削除フラグ、履歴テーブル、監査カラム(作成者・更新日時等)の方式が全テーブルで統一されている | G41: 論理削除や監査カラムの方式がテーブルごとに異なると、共通処理(検索条件の deleted 除外等)が書けず、削除済みデータの誤表示などの不具合が散発する。 | H41: swebok-v4a.pdf ch03 Software Design > 1.4 Uniformity / 実務補完(データ設計実務) | I41: CORE | J41: 原則適用。案件スコープ・成果物・規制・リスク上非該当の場合はN/A根拠を記録。 | K41: SRC-SWEBOK-V4A;SRC-PRACTICE
A42: DES-040 | B42: SWEBOK | C42: 4. データモデル/ER図 | D42: Medium | E42: コード値(区分値)が定義されている | F42: 区分・ステータス等のコード値について、値と意味の一覧が存在する | G42: コード値の定義がないと、実装者・テスターが値の意味を推測し、システム間・画面間で同じ区分に異なる値が使われる事故が起きる。 | H42: 実務補完(データ項目設計実務)/ 1.1 Design Thinking(問題領域の語彙の明文化) | I42: CORE | J42: 原則適用。案件スコープ・成果物・規制・リスク上非該当の場合はN/A根拠を記録。 | K42: SRC-PRACTICE
A43: DES-041 | B43: SWEBOK | C43: 4. データモデル/ER図 | D43: Medium | E43: 概念モデルと物理モデルが対応している | F43: 概念/論理モデルのエンティティと物理テーブルの対応が追跡でき、根拠なき乖離がない | G43: 概念モデルと物理テーブルの対応が追えないと、業務要求の変更をどのテーブルに反映すべきか判断できず、モデルが形骸化して保守時の分析コストが増える。 | H43: swebok-v4a.pdf ch03 Software Design > 4.2 Structural Design Descriptions(ERD:概念・論理・物理の各モデル) | I43: CORE | J43: 原則適用。案件スコープ・成果物・規制・リスク上非該当の場合はN/A根拠を記録。 | K43: SRC-SWEBOK-V4A
A44: DES-042 | B44: SWEBOK | C44: 4. データモデル/ER図 | D44: Low | E44: データ移行の要否が判断されている | F44: 既存データが存在する場合、移行対象・変換規則・移行手順への言及がある | G44: 移行の検討漏れはリリース直前に発覚し、変換規則の設計・リハーサルをやり直す大きな手戻りになる。新スキーマ設計と移行設計は不可分。 | H44: 実務補完(データ移行実務) | I44: CORE | J44: 原則適用。案件スコープ・成果物・規制・リスク上非該当の場合はN/A根拠を記録。 | K44: SRC-PRACTICE
A45: DES-050 | B45: SWEBOK | C45: 5. 振る舞い設計(シーケンス・状態遷移) | D45: Critical | E45: 主要ユースケースにシーケンス図がある | F45: 主要ユースケース/主要APIごとにシーケンス図が存在し、対応する要求ID/API IDが図に明記されている | G45: コンポーネント間の相互作用と時間順序はシーケンス図でしか正確に共有できない。主要フローの動的設計がないと、呼び出し順序・責務分担の解釈が実装者ごとに割れる。 | H45: swebok-v4a.pdf ch03 Software Design > 4.3 Behavioral Design Descriptions(シーケンス図)/ 2.1 High-Level Design(エンドツーエンドのトランザクション追跡) | I45: CORE | J45: 原則適用。案件スコープ・成果物・規制・リスク上非該当の場合はN/A根拠を記録。 | K45: SRC-SWEBOK-V4A
A46: DES-051 | B46: SWEBOK | C46: 5. 振る舞い設計(シーケンス・状態遷移) | D46: Critical | E46: 状態を持つエンティティに状態遷移図/表がある | F46: 状態(ステータス)を持つ全エンティティについて、全状態と遷移イベントを網羅した状態遷移図または遷移表が存在する | G46: 設計はソフトウェアのモードと状態に関して完全であるべき、というのが完全性の原則。状態遷移が図示されないと、遷移の抜けが不正な状態遷移バグとして本番で発覚する。 | H46: swebok-v4a.pdf ch03 Software Design > 4.3 Behavioral Design Descriptions(状態遷移図・ステートチャート)/ 1.4 Completeness(モード・状態に関する完全性) | I46: CORE | J46: 原則適用。案件スコープ・成果物・規制・リスク上非該当の場合はN/A根拠を記録。 | K46: SRC-SWEBOK-V4A
A47: DES-052 | B47: SWEBOK | C47: 5. 振る舞い設計(シーケンス・状態遷移) | D47: High | E47: 異常系のシーケンスが記述されている | F47: 主要フローについて、タイムアウト・外部システム障害・業務エラー時の流れ(リトライ、ロールバック、補償処理)が図または本文で記述されている | G47: 正常系だけの設計では、障害時の挙動が実装者の即興になり、データ不整合や無限リトライ等の重大障害を生む。異常条件の処理は独立した設計品質課題である。 | H47: swebok-v4a.pdf ch03 Software Design > 3.5 Errors and Exception Handling, Fault Tolerance | I47: CORE | J47: 原則適用。案件スコープ・成果物・規制・リスク上非該当の場合はN/A根拠を記録。 | K47: SRC-SWEBOK-V4A
A48: DES-053 | B48: SWEBOK | C48: 5. 振る舞い設計(シーケンス・状態遷移) | D48: High | E48: 状態遷移が網羅的である | F48: 状態×イベントの全組合せについて、遷移先または「遷移不可(エラー)」が定義されており、未定義の組合せがない | G48: 状態×イベントの未定義の組合せは「起きないはず」の前提であり、実際に起きたとき未定義動作になる。網羅表はテスト観点の導出元にもなる。 | H48: swebok-v4a.pdf ch03 Software Design > 1.4 Completeness / 4.3 Behavioral Design Descriptions(決定表・状態遷移図) | I48: CORE | J48: 原則適用。案件スコープ・成果物・規制・リスク上非該当の場合はN/A根拠を記録。 | K48: SRC-SWEBOK-V4A
A49: DES-054 | B49: SWEBOK | C49: 5. 振る舞い設計(シーケンス・状態遷移) | D49: High | E49: トランザクション境界が明示されている | F49: 更新処理のシーケンスにおいて、トランザクションの開始・コミット・ロールバックの位置が図または本文で特定できる | G49: トランザクション境界が曖昧だと、部分コミットによるデータ不整合や、境界の広すぎによるロック競合が起きる。原子性の設計は並行性設計の中核。 | H49: swebok-v4a.pdf ch03 Software Design > 3.1 Concurrency(原子性・同期)/ 3.3 Data Persistence | I49: CORE | J49: 原則適用。案件スコープ・成果物・規制・リスク上非該当の場合はN/A根拠を記録。 | K49: SRC-SWEBOK-V4A
A50: DES-055 | B50: SWEBOK | C50: 5. 振る舞い設計(シーケンス・状態遷移) | D50: High | E50: 同期/非同期の別が明示されている | F50: 呼び出しごとに同期・非同期の別が図上で区別され、非同期処理には完了通知・結果確認の方法が定義されている | G50: 同期/非同期の区別(暗黙的起動・コールバック等の制御方式)が曖昧だと、完了前のデータ参照や応答待ちのブロックなど、時序に起因する不具合を作り込む。 | H50: swebok-v4a.pdf ch03 Software Design > 3.2 Control and Event Handling(同期・暗黙的起動・コールバック) | I50: CORE | J50: 原則適用。案件スコープ・成果物・規制・リスク上非該当の場合はN/A根拠を記録。 | K50: SRC-SWEBOK-V4A
A51: DES-056 | B51: SWEBOK | C51: 5. 振る舞い設計(シーケンス・状態遷移) | D51: Medium | E51: シーケンス図の参加者が構造設計と一致している | F51: シーケンス図に登場するオブジェクト/コンポーネントが、モジュール構成(クラス図・コンポーネント図)に定義されたものと一致している | G51: 構造図(静的ビュー)と振る舞い図(動的ビュー)は同一設計の別表現であり、参加者が食い違うとどちらかが古いか誤りで、実装者が誤った方を信じるリスクがある。 | H51: swebok-v4a.pdf ch03 Software Design > 4.2/4.3 構造記述と振る舞い記述の整合 / 4.1 Model-Based Design | I51: CORE | J51: 原則適用。案件スコープ・成果物・規制・リスク上非該当の場合はN/A根拠を記録。 | K51: SRC-SWEBOK-V4A
A52: DES-057 | B52: SWEBOK | C52: 5. 振る舞い設計(シーケンス・状態遷移) | D52: Medium | E52: 時間制約が記述されている | F52: タイムアウト値、応答時間目標、スケジュール実行時刻など時間に関する制約が数値で記載されている | G52: 入出力イベント間の順序・タイミング関係の仕様化は上位設計の必須項目。タイムアウト等が数値化されていないと実装値がバラバラになり、障害時の挙動が予測不能になる。 | H52: swebok-v4a.pdf ch03 Software Design > 2.1 High-Level Design(イベント・メッセージ間の順序とタイミング関係の仕様化) | I52: CORE | J52: 原則適用。案件スコープ・成果物・規制・リスク上非該当の場合はN/A根拠を記録。 | K52: SRC-SWEBOK-V4A
... A57: DES-063 | B57: SWEBOK | C57: 6. エラー・例外処理・耐障害性 | D57: High | E57: 外部依存先の障害への対処が設計されている | F57: 依存する外部システム/サービスごとに、障害時の挙動(フェイルファスト、フォールバック、縮退運転)が定義されている | G57: 異種システム連携では相手側の障害は必ず起きる。依存先ごとの縮退方針がないと、一つの外部障害が全機能停止に波及する。 | H57: swebok-v4a.pdf ch03 Software Design > 3.5 Fault Tolerance / 3.6 Integration and Interoperability | I57: CORE | J57: 原則適用。案件スコープ・成果物・規制・リスク上非該当の場合はN/A根拠を記録。 | K57: SRC-SWEBOK-V4A
A58: DES-064 | B58: SWEBOK | C58: 6. エラー・例外処理・耐障害性 | D58: High | E58: ログ出力設計が定義されている | F58: ログレベルの使い分け、出力項目(トレースID等)、エラー時に原因調査へ必要な情報が出力される設計が記述されている | G58: ログ設計がないと障害時に原因調査ができず復旧が長引く。監視可能性(monitorability)は分散システムに求められる品質特性の一つ。 | H58: swebok-v4a.pdf ch03 Software Design > 3.4 Distribution of Components(monitorability)/ 実務補完(可観測性設計) | I58: CORE | J58: 原則適用。案件スコープ・成果物・規制・リスク上非該当の場合はN/A根拠を記録。 | K58: SRC-SWEBOK-V4A;SRC-PRACTICE | L58: OPS-OBSERVABILITY
A59: DES-065 | B59: SWEBOK | C59: 6. エラー・例外処理・耐障害性 | D59: Medium | E59: ユーザーへのエラー提示が設計されている | F59: エラー発生時にユーザー/呼び出し元へ返すメッセージが定義され、内部情報(スタックトレース、SQL等)を露出しない | G59: 内部情報(スタックトレース・SQL)の露出は攻撃者への情報提供になり、不親切なエラーはユーザーの誤操作と問い合わせを増やす。 | H59: swebok-v4a.pdf ch03 Software Design > 3.7 Assurance, Security, and Safety(情報の不正開示防止)/ 3.5 Errors and Exception Handling | I59: CORE | J59: 原則適用。案件スコープ・成果物・規制・リスク上非該当の場合はN/A根拠を記録。 | K59: SRC-SWEBOK-V4A
A60: DES-066 | B60: SWEBOK | C60: 6. エラー・例外処理・耐障害性 | D60: Medium | E60: 監視・アラートの契機が定義されている | F60: 検知すべき異常(エラー率、滞留、遅延)と通知の契機が記述されている。運用設計側に委譲する場合は参照先が明記されている | G60: 検知契機が設計されていないと、異常はユーザーからの申告で発覚し対応が後手に回る。何を異常とみなすかは設計時にしか正確に定義できない。 | H60: swebok-v4a.pdf ch03 Software Design > 3.4 Distribution of Components(monitorability・事業継続性) | I60: CORE | J60: 原則適用。案件スコープ・成果物・規制・リスク上非該当の場合はN/A根拠を記録。 | K60: SRC-SWEBOK-V4A | L60: OPS-OBSERVABILITY
A61: DES-067 | B61: SWEBOK | C61: 6. エラー・例外処理・耐障害性 | D61: Low | E61: 障害復旧手順への入力が提供されている | F61: 再実行・リカバリに必要な情報(再実行可能地点、手動介入手順)が設計書から特定できる | G61: セキュリティ・耐障害設計は「修復と復旧の支援」まで含む。再実行可能地点が設計から読み取れないと、障害復旧が属人的な手探り作業になる。 | H61: swebok-v4a.pdf ch03 Software Design > 3.7 Assurance, Security, and Safety(repair and recovery の支援)/ 3.5 Fault Tolerance | I61: CORE | J61: 原則適用。案件スコープ・成果物・規制・リスク上非該当の場合はN/A根拠を記録。 | K61: SRC-SWEBOK-V4A
A62: DES-070 | B62: SWEBOK | C62: 7. 並行性・性能 | D62: Critical | E62: 排他制御が設計されている | F62: 同一データへの同時更新が起こりうる箇所が識別され、方式(楽観/悲観ロック、一意制約)と競合時の挙動が定義されている | G62: 同時更新の競合を設計しないと、後勝ちによる更新消失(lost update)が静かに起き、発見が極めて困難なデータ破壊になる。同期は並行性設計の中心課題。 | H62: swebok-v4a.pdf ch03 Software Design > 3.1 Concurrency(原子性・同期) | I62: CORE | J62: 原則適用。案件スコープ・成果物・規制・リスク上非該当の場合はN/A根拠を記録。 | K62: SRC-SWEBOK-V4A
A63: DES-071 | B63: SWEBOK | C63: 7. 並行性・性能 | D63: High | E63: デッドロックの回避策がある | F63: 複数リソースをロックする処理についてロック順序の規約、またはデッドロック検出時の対処が定義されている。該当処理がなければ対象外の根拠がある | G63: デッドロックは負荷が上がった本番でのみ再現する典型的な並行性障害で、事後対処が難しい。ロック順序の規約は設計時に決めるのが唯一安価な対策。 | H63: swebok-v4a.pdf ch03 Software Design > 3.1 Concurrency(同期・スケジューリング) | I63: CORE | J63: 原則適用。案件スコープ・成果物・規制・リスク上非該当の場合はN/A根拠を記録。 | K63: SRC-SWEBOK-V4A
A64: DES-072 | B64: SWEBOK | C64: 7. 並行性・性能 | D64: High | E64: 性能要件に対する設計上の根拠がある | F64: 応答時間・スループット等の性能要件に対し、それを満たすための設計判断(インデックス、キャッシュ、非同期化、バッチ化)が対応付けて記述されている | G64: 性能は実装後の計測任せにすると、アーキテクチャレベルの作り直しを強いられる。要件と設計判断の対応付けにより、性能達成の見込みを設計段階で説明可能にする。 | H64: swebok-v4a.pdf ch03 Software Design > 6.2 Quality Attributes(性能)/ 6.3 Quality Analysis and Evaluation Techniques(シミュレーション・形式的分析) | I64: CORE | J64: 原則適用。案件スコープ・成果物・規制・リスク上非該当の場合はN/A根拠を記録。 | K64: SRC-SWEBOK-V4A
A65: DES-073 | B65: SWEBOK | C65: 7. 並行性・性能 | D65: Medium | E65: データ量の見積りがある | F65: 主要テーブル/データの初期件数・増加率の見積りが数値で記載され、設計(インデックス、パーティション、アーカイブ)がそれと整合している | G65: データ量の前提がない設計は少量データでしか検証されず、本番のデータ増加で性能・容量の問題が突然顕在化する。見積りは性能設計とデータ設計の検証可能性の土台。 | H65: 実務補完(容量・性能設計実務)/ 1.4 Verifiability | I65: CORE | J65: 原則適用。案件スコープ・成果物・規制・リスク上非該当の場合はN/A根拠を記録。 | K65: SRC-PRACTICE
A66: DES-074 | B66: SWEBOK | C66: 7. 並行性・性能 | D66: Medium | E66: 並行実行単位が定義されている | F66: プロセス・スレッド・ワーカー等の並行実行単位と多重度、共有資源(コネクションプール等)の上限が定義されている | G66: 並行性の設計とは、プロセス・タスク・スレッドへの分割とその効率・同期への帰結を決めること。多重度や共有資源上限が未定義だと資源枯渇や性能劣化を招く。 | H66: swebok-v4a.pdf ch03 Software Design > 3.1 Concurrency(プロセス・タスク・スレッドへの分割) | I66: CORE | J66: 原則適用。案件スコープ・成果物・規制・リスク上非該当の場合はN/A根拠を記録。 | K66: SRC-SWEBOK-V4A
A67: DES-075 | B67: SWEBOK | C67: 7. 並行性・性能 | D67: Medium | E67: キャッシュの一貫性方針がある | F67: キャッシュを使う場合、対象データ・有効期限・無効化の契機が定義されている。使わない場合は N/A | G67: キャッシュの無効化契機を決めないと、古いデータの表示・古い権限での認可といった発見しにくい不整合が起きる。 | H67: swebok-v4a.pdf ch03 Software Design > 3.3 Data Persistence / 実務補完(キャッシュ設計実務) | I67: CORE | J67: 原則適用。案件スコープ・成果物・規制・リスク上非該当の場合はN/A根拠を記録。 | K67: SRC-SWEBOK-V4A;SRC-PRACTICE
A68: DES-076 | B68: SWEBOK | C68: 7. 並行性・性能 | D68: Low | E68: スケールアウト時の制約が明記されている | F68: 複数インスタンス実行時に問題となる要素(ローカル状態、二重起動)の有無と対処が記述されている | G68: ローカル状態や二重起動の問題を放置すると、スケールアウトした瞬間にセッション消失やバッチ二重実行が起きる。分散配置とスケーラビリティへの配慮は設計品質の一つ。 | H68: swebok-v4a.pdf ch03 Software Design > 3.4 Distribution of Components(スケーラビリティ・可用性) | I68: CORE | J68: 原則適用。案件スコープ・成果物・規制・リスク上非該当の場合はN/A根拠を記録。 | K68: SRC-SWEBOK-V4A
A69: DES-080 | B69: SWEBOK | C69: 8. セキュリティ | D69: Critical | E69: 認可チェックの実施箇所が設計されている | F69: 保護対象の操作・データごとに、認可チェックを行う層・モジュールが特定されており、チェック漏れ経路(内部API直呼び等)がないことが確認できる | G69: 認可チェックの実施層が決まっていないと、チェックされない迂回経路(内部API直呼び等)が残り、権限昇格・情報漏えいの脆弱性になる。 | H69: swebok-v4a.pdf ch03 Software Design > 3.7 Assurance, Security, and Safety(不正アクセスの防止) | I69: CORE | J69: 原則適用。案件スコープ・成果物・規制・リスク上非該当の場合はN/A根拠を記録。 | K69: SRC-SWEBOK-V4A | L69: SEC-IAM
A70: DES-081 | B70: SWEBOK | C70: 8. セキュリティ | D70: Critical | E70: インジェクション対策が設計されている | F70: SQL/OSコマンド/パス等の外部入力を使う処理について、プレースホルダ・エスケープ等の対策方式が規定されている | G70: インジェクションは外部入力を扱う全処理に共通する代表的攻撃で、対策方式を設計で規定しないと実装者ごとの対策漏れが必ず発生する。 | H70: swebok-v4a.pdf ch03 Software Design > 3.7 Assurance, Security, and Safety / 実務補完(OWASP) | I70: CORE | J70: 原則適用。案件スコープ・成果物・規制・リスク上非該当の場合はN/A根拠を記録。 | K70: SRC-SWEBOK-V4A;SRC-OWASP;SRC-PRACTICE
A71: DES-082 | B71: SWEBOK | C71: 8. セキュリティ | D71: High | E71: 機密情報の取り扱いが設計されている | F71: パスワード・トークン・鍵の保存方式(ハッシュ、暗号化、シークレット管理)と、ログ・エラーメッセージへの非出力が規定されている | G71: パスワード平文保存やログへのトークン出力は、一度作り込むと全データの再取得・失効が必要な重大事故になる。機密情報の保存方式は後から変えにくい設計判断。 | H71: swebok-v4a.pdf ch03 Software Design > 3.7 Assurance, Security, and Safety(情報の不正開示・作成・変更の防止) | I71: CORE | J71: 原則適用。案件スコープ・成果物・規制・リスク上非該当の場合はN/A根拠を記録。 | K71: SRC-SWEBOK-V4A
A72: DES-083 | B72: SWEBOK | C72: 8. セキュリティ | D72: High | E72: 通信の保護が設計されている | F72: 外部・内部通信の暗号化方針(TLS等)と、証明書検証の扱いが記述されている | G72: 異なるプロトコル・媒体で通信する分散アプリケーションではセキュリティが鍵となる、とSWEBOKが明示する領域。平文通信や証明書検証の無効化は盗聴・なりすましに直結する。 | H72: swebok-v4a.pdf ch03 Software Design > 3.7 Assurance, Security, and Safety(分散アプリケーションの通信保護) | I72: CORE | J72: 原則適用。案件スコープ・成果物・規制・リスク上非該当の場合はN/A根拠を記録。 | K72: SRC-SWEBOK-V4A
A73: DES-084 | B73: SWEBOK | C73: 8. セキュリティ | D73: High | E73: セッション/トークンのライフサイクルが定義されている | F73: 有効期限、更新、失効(ログアウト・権限変更時)の仕様が定義されている | G73: 失効設計がないと、ログアウト後・権限剥奪後もトークンが有効なまま残り、退職者アクセス等のインシデントになる。 | H73: swebok-v4a.pdf ch03 Software Design > 3.7 Assurance, Security, and Safety / 実務補完(セッション管理実務) | I73: CORE | J73: 原則適用。案件スコープ・成果物・規制・リスク上非該当の場合はN/A根拠を記録。 | K73: SRC-SWEBOK-V4A;SRC-PRACTICE
A74: DES-085 | B74: SWEBOK | C74: 8. セキュリティ | D74: Medium | E74: 監査ログが設計されている | F74: 誰が・いつ・何をしたかを記録すべき操作(ログイン、権限変更、重要データ更新)が識別され、記録項目が定義されている | G74: 監査ログがないと、不正操作の検知も事後の原因究明もできず、被害範囲を特定できないまま全件影響として扱う羽目になる。攻撃時の被害限定と修復支援の一部。 | H74: swebok-v4a.pdf ch03 Software Design > 3.7 Assurance, Security, and Safety(被害の限定・修復の支援)/ 実務補完(監査要件) | I74: CORE | J74: 原則適用。案件スコープ・成果物・規制・リスク上非該当の場合はN/A根拠を記録。 | K74: SRC-SWEBOK-V4A;SRC-PRACTICE | L74: OPS-OBSERVABILITY
A75: DES-086 | B75: SWEBOK | C75: 8. セキュリティ | D75: Medium | E75: 最小権限の原則が適用されている | F75: アプリケーションが使用する DB アカウント・クラウド権限等が必要最小限に設計されている(付与権限の一覧がある) | G75: 過剰権限は、脆弱性を突かれた際の被害範囲をアプリの必要範囲を超えて拡大させる。権限一覧の明文化が被害限定設計の証拠になる。 | H75: swebok-v4a.pdf ch03 Software Design > 3.7 Assurance, Security, and Safety(被害の限定)/ 実務補完(最小権限の原則) | I75: CORE | J75: 原則適用。案件スコープ・成果物・規制・リスク上非該当の場合はN/A根拠を記録。 | K75: SRC-SWEBOK-V4A;SRC-PRACTICE | L75: SEC-IAM
A76: DES-087 | B76: SWEBOK | C76: 8. セキュリティ | D76: Low | E76: セキュリティ要件の参照元が明記されている | F76: 準拠すべき社内規程・標準(ISO/IEC 27001 等)への参照が記載されている | G76: 準拠すべき規程が不明だと、監査・認証の段階で設計のやり直しが発生する。参照元の明記はセキュリティ設計の検証可能性を支える。 | H76: 実務補完(ISO/IEC 27001等の社内規程準拠)/ 1.4 Verifiability | I76: CORE | J76: 原則適用。案件スコープ・成果物・規制・リスク上非該当の場合はN/A根拠を記録。 | K76: SRC-ISO-GENERAL;SRC-PRACTICE
A77: DES-902 | B77: 追加承認 | C77: 8. セキュリティ | D77: Medium | E77: セーフティ(安全性)の該当有無が判断され、該当時はハザード対策が設計されている | F77: ソフトウェアの誤動作が人身・財産・環境への危害につながりうるかの判断が明記され、該当する場合はハザードの識別と対策(フェイルセーフ、インターロック等)が設計されている。非該当の場合はその根拠がある | G77: 安全関連機能の見落としは人身事故等の重大な結果に直結する。該当有無の判断自体を記録させることで「検討しなかった」状態を防ぐ。 | H77: swebok-v4a.pdf ch03 Software Design > 3.7 Assurance, Security, and Safety — セーフティ(人命・財産・環境への危害の防止) | I77: CORE | J77: 原則適用。案件スコープ・成果物・規制・リスク上非該当の場合はN/A根拠を記録。 | K77: SRC-SWEBOK-V4A
A78: DES-090 | B78: SWEBOK | C78: 9. UI設計 | D78: Critical | E78: 画面一覧と画面遷移図が存在する | F78: 全画面が ID 付きで列挙され、画面間の遷移(条件含む)が図で表現されている | G78: UI設計は画面の構造的レイアウトと画面遷移の振る舞いロジックが混在する特殊領域。全体像(一覧と遷移)がないと、画面の作成漏れ・行き止まり遷移が実装後に発覚する。 | H78: swebok-v4a.pdf ch03 Software Design > 4.5 Specialized and Domain-Specific Languages(UI設計=構造+遷移の振る舞い) | I78: CORE | J78: 原則適用。案件スコープ・成果物・規制・リスク上非該当の場合はN/A根拠を記録。 | K78: SRC-SWEBOK-V4A
A79: DES-091 | B79: SWEBOK | C79: 9. UI設計 | D79: Critical | E79: 入力項目定義が完備している | F79: 全入力項目に項目ID、型、桁、必須/任意、初期値、バリデーション規則、エラーメッセージが定義されている | G79: 入力項目定義の欠落は、実装者ごとの独自バリデーションとエラーメッセージを生み、API側の検証仕様(DES-025)との不一致も引き起こす。 | H79: swebok-v4a.pdf ch03 Software Design > 5.5 User-Centered Design / 実務補完(画面設計実務) | I79: CORE | J79: 原則適用。案件スコープ・成果物・規制・リスク上非該当の場合はN/A根拠を記録。 | K79: SRC-SWEBOK-V4A;SRC-PRACTICE
A80: DES-092 | B80: SWEBOK | C80: 9. UI設計 | D80: High | E80: 画面とAPIの対応が定義されている | F80: 各画面の操作(表示、ボタン押下)と呼び出すAPIの対応表が存在する | G80: 画面とAPIの対応が未定義だと、フロントとバックエンドの分担する結合部分が宙に浮き、必要なAPIの作成漏れや過剰なAPI乱立が起きる。 | H80: 実務補完(Webアプリケーション設計実務)/ 3.6 Integration and Interoperability | I80: CORE | J80: 原則適用。案件スコープ・成果物・規制・リスク上非該当の場合はN/A根拠を記録。 | K80: SRC-PRACTICE
A81: DES-093 | B81: SWEBOK | C81: 9. UI設計 | D81: High | E81: エラー・例外時の画面挙動が定義されている | F81: 入力エラー、業務エラー、システムエラーそれぞれの表示方法(項目単位/画面単位、遷移先)が定義されている | G81: エラー時の画面挙動が未定義だと、エラーの握りつぶしや白画面などユーザーが対処不能な状態に陥る。例外処理設計のUI側の受け口。 | H81: swebok-v4a.pdf ch03 Software Design > 3.5 Errors and Exception Handling / 5.5 User-Centered Design | I81: CORE | J81: 原則適用。案件スコープ・成果物・規制・リスク上非該当の場合はN/A根拠を記録。 | K81: SRC-SWEBOK-V4A
A82: DES-094 | B82: SWEBOK | C82: 9. UI設計 | D82: High | E82: 権限による表示・操作制御が定義されている | F82: ロールごとに表示/非表示・活性/非活性となる要素が定義されている。権限差がない場合はその旨の明記がある | G82: 表示制御だけで認可を済ませる設計事故(サーバ側チェック省略)や、ロール別表示の実装漏れを防ぐ。認可設計(DES-080)のUI面での具体化。 | H82: swebok-v4a.pdf ch03 Software Design > 3.7 Assurance, Security, and Safety(不正アクセスの防止) | I82: CORE | J82: 原則適用。案件スコープ・成果物・規制・リスク上非該当の場合はN/A根拠を記録。 | K82: SRC-SWEBOK-V4A
A83: DES-095 | B83: SWEBOK | C83: 9. UI設計 | D83: Medium | E83: 二重送信・再読み込み対策が設計されている | F83: 更新系操作についてボタン二重押下・ブラウザ再読み込み時の挙動と対策が定義されている | G83: 二重送信は更新系操作で二重登録・二重決済を引き起こす頻出事故であり、対策の有無は設計時に決めないと画面ごとに対応がバラつく。 | H83: 実務補完(Web UI 実務)/ 3.5 Errors and Exception Handling | I83: CORE | J83: 原則適用。案件スコープ・成果物・規制・リスク上非該当の場合はN/A根拠を記録。 | K83: SRC-PRACTICE
A84: DES-096 | B84: SWEBOK | C84: 9. UI設計 | D84: Medium | E84: 主要ユーザーフローが検証されている | F84: 主要フローについてワイヤーフレームまたはプロトタイプによる確認(レビュー記録)が存在する | G84: ユーザー中心設計はプロトタイプ作成と要求に対する評価までを含む。机上のUI設計だけでは使い勝手の問題が受入段階で発覚し、画面の作り直しになる。 | H84: swebok-v4a.pdf ch03 Software Design > 5.5 User-Centered Design(プロトタイプ作成と設計解の評価) | I84: CORE | J84: 原則適用。案件スコープ・成果物・規制・リスク上非該当の場合はN/A根拠を記録。 | K84: SRC-SWEBOK-V4A
A85: DES-097 | B85: SWEBOK | C85: 9. UI設計 | D85: Medium | E85: アクセシビリティ・対応環境が定義されている | F85: 対応ブラウザ/デバイス/画面サイズと、アクセシビリティ要件(該当する場合は WCAG 等の参照)が記載されている | G85: 対応環境が未定義だと、テスト対象ブラウザが決められず、リリース後に特定環境での表示崩れが発覚する。ユーザビリティは設計品質属性の一つ。 | H85: swebok-v4a.pdf ch03 Software Design > 6.2 Quality Attributes(usability)/ 実務補完(WCAG) | I85: CORE | J85: 原則適用。案件スコープ・成果物・規制・リスク上非該当の場合はN/A根拠を記録。 | K85: SRC-SWEBOK-V4A;SRC-PRACTICE
A86: DES-098 | B86: SWEBOK | C86: 9. UI設計 | D86: Low | E86: 文言・表記のガイドラインがある | F86: ボタン名・メッセージの文体、日付・数値の表示形式の規約が定義されている | G86: 文言・表記の不統一は製品の一貫性を損ない、ユーザーの混乱と翻訳・修正コストの増大を招く。共通問題への共通解という一貫性原則のUI適用。 | H86: swebok-v4a.pdf ch03 Software Design > 1.4 Uniformity / 5.5 User-Centered Design | I86: CORE | J86: 原則適用。案件スコープ・成果物・規制・リスク上非該当の場合はN/A根拠を記録。 | K86: SRC-SWEBOK-V4A
A87: DES-100 | B87: SWEBOK | C87: 10. 設計の記録・設計根拠 | D87: High | E87: 重要な設計決定に根拠が記録されている | F87: 技術選定・方式選定などの重要決定について、決定内容・理由・検討した代替案・トレードオフが記録されている(ADR等の形式) | G87: 設計根拠(前提・代替案・トレードオフ)の記録は、保守者が決定の理由を知らずに壊す事故を防ぎ、前提が変わったとき棄却案を再検討可能にする。長期保守性を直接高める。 | H87: swebok-v4a.pdf ch03 Software Design > 4.6 Design Rationale | I87: CORE | J87: 原則適用。案件スコープ・成果物・規制・リスク上非該当の場合はN/A根拠を記録。 | K87: SRC-SWEBOK-V4A
... A97: DES-113 | B97: SWEBOK | C97: 11. 品質評価・構築への引き渡し | D97: Medium | E97: 変更容易性の観点で将来変更点が識別されている | F97: 変わりやすい要素(外部仕様、料率、区分値等)が識別され、設定化・局所化などの対応が設計されている | G97: 可変性はほとんどのソフトウェアの基本的側面であり、変わりやすい要素を局所化しないと、小さな仕様変更のたびに広範囲の修正が必要になる。 | H97: swebok-v4a.pdf ch03 Software Design > 3.8 Variability / 6.2 Quality Attributes(modifiability) | I97: CORE | J97: 原則適用。案件スコープ・成果物・規制・リスク上非該当の場合はN/A根拠を記録。 | K97: SRC-SWEBOK-V4A
A98: DES-114 | B98: SWEBOK | C98: 11. 品質評価・構築への引き渡し | D98: Low | E98: 設計メトリクスが確認されている | F98: モジュール数、依存数、画面数、API数、テーブル数等の規模が把握され、極端な偏り(1モジュールへの依存集中等)がレビューで確認されている | G98: 規模・構造の測定は設計の偏り(依存集中・巨大モジュール)を定量的に可視化する。測定なしのレビューは主観に頼り、構造的な問題を見逃す。 | H98: swebok-v4a.pdf ch03 Software Design > 6.4 Measures and Metrics | I98: CORE | J98: 原則適用。案件スコープ・成果物・規制・リスク上非該当の場合はN/A根拠を記録。 | K98: SRC-SWEBOK-V4A | L98: OPS-OBSERVABILITY

Sheet 04_実装
A1: ID | B1: 区分 | C1: カテゴリ | D1: 基準重要度 | E1: チェック項目 | F1: 合格基準 | G1: 意図(なぜ確認するか) | H1: 対象ドキュメント(参照箇所) | I1: 適用プロファイル | J1: 適用条件 | K1: 出典ID | L1: 重複統制グループ | M1: 案件重要度 | N1: 適用判定 | O1: 判定 | P1: 証跡・参照箇所 | Q1: 指摘・Issue ID | R1: 対応方針 | S1: 例外・リスク受容承認者 | T1: 是正期限 | U1: レビュアー | V1: レビュー日 | W1: 再確認結果
A2: CON-001 | B2: SWEBOK | C2: 1. 複雑性の最小化(SWEBOK 4-1.1, 4-3.1) | D2: High | E2: 関数・メソッドの循環的複雑度が規定内である | F2: 循環的複雑度が規約の上限(未規定なら10)以下。超える関数には静的解析設定上の明示的な除外理由がある | G2: 複雑度の高い関数はテストパス数が爆発し、理解・修正時の欠陥混入率が上がる。数値基準で機械的に検出し、レビューの主観に依存した見逃しを防ぐ。 | H2: swebok-v4a.pdf ch04 Software Construction > 4-1.1 Minimizing Complexity(McCabe循環的複雑度) | I2: CORE | J2: 原則適用。案件スコープ・成果物・規制・リスク上非該当の場合はN/A根拠を記録。 | K2: SRC-SWEBOK-V4A
A3: CON-002 | B3: SWEBOK | C3: 1. 複雑性の最小化(SWEBOK 4-1.1, 4-3.1) | D3: High | E3: 関数が単一の責務を持つ | F3: 関数名が「動詞+目的語」1つで説明でき、抽象度の異なる処理(入出力・業務ロジック・整形等)が1関数に混在していない | G3: 複数責務が混在した関数は変更時の影響範囲が読めず、片方の修正がもう片方を壊す退行を生む。責務単位の分割で変更とテストの単位を小さく保つ。 | H3: swebok-v4a.pdf ch04 Software Construction > 4-1.1 Minimizing Complexity / 4-3.1 Construction Design | I3: CORE | J3: 原則適用。案件スコープ・成果物・規制・リスク上非該当の場合はN/A根拠を記録。 | K3: SRC-SWEBOK-V4A
A4: CON-003 | B4: SWEBOK | C4: 1. 複雑性の最小化(SWEBOK 4-1.1, 4-3.1) | D4: Medium | E4: ネストの深さが規定内である | F4: 条件分岐・ループのネストが4段以下。深いネストは早期return・関数抽出で平坦化されている | G4: 深いネストは人間のワーキングメモリの限界を超え、条件の組み合わせ漏れ(特に異常系)がレビューをすり抜ける原因になる。 | H4: swebok-v4a.pdf ch04 Software Construction > 4-1.1 Minimizing Complexity / 4-3.3 Coding(制御構造の使用) | I4: CORE | J4: 原則適用。案件スコープ・成果物・規制・リスク上非該当の場合はN/A根拠を記録。 | K4: SRC-SWEBOK-V4A
A5: CON-004 | B5: SWEBOK | C5: 1. 複雑性の最小化(SWEBOK 4-1.1, 4-3.1) | D5: Medium | E5: 関数の長さが読解可能な範囲である | F5: 1関数がおおむね50行(規約に規定があればその値)以下。超える場合は分割不能な理由がコメントかレビュー記録にある | G5: 画面に収まらない長大関数は全体の把握が不可能になり、修正時に離れた行間の暗黙の依存を壊す事故を招く。 | H5: swebok-v4a.pdf ch04 Software Construction > 4-1.1 Minimizing Complexity / 4-3.3 Coding(ルーチンへの構成) | I5: CORE | J5: 原則適用。案件スコープ・成果物・規制・リスク上非該当の場合はN/A根拠を記録。 | K5: SRC-SWEBOK-V4A
A6: CON-005 | B6: SWEBOK | C6: 1. 複雑性の最小化(SWEBOK 4-1.1, 4-3.1) | D6: High | E6: 重複コードがない | F6: 同一・準同一のロジック(数行以上)が2箇所以上にコピーされていない。共通化されているか、重複を許容する明示的理由がある | G6: コードクローンは一方だけ修正される「片修正」バグの温床であり、SWEBOKも再利用可能な断片のライブラリ化によるクローン回避を明示している。 | H6: swebok-v4a.pdf ch04 Software Construction > 4-1.4 Reusing Assets / 4-3.5 Reuse in Construction(コードクローン問題) | I6: CORE | J6: 原則適用。案件スコープ・成果物・規制・リスク上非該当の場合はN/A根拠を記録。 | K6: SRC-SWEBOK-V4A
A7: CON-006 | B7: SWEBOK | C7: 1. 複雑性の最小化(SWEBOK 4-1.1, 4-3.1) | D7: Medium | E7: 引数の数が抑制されている | F7: 関数の引数が5個以下。超える場合はパラメータオブジェクト等に集約されている | G7: 引数が多い関数は呼び出し側で順序取り違え・意味の誤解を誘発し、責務過多のシグナルでもある。凝集した型への集約で誤用を構造的に防ぐ。 | H7: swebok-v4a.pdf ch04 Software Construction > 4-1.1 Minimizing Complexity / 4-4.1 API Design and Use(誤用しにくい設計) | I7: CORE | J7: 原則適用。案件スコープ・成果物・規制・リスク上非該当の場合はN/A根拠を記録。 | K7: SRC-SWEBOK-V4A
A8: CON-007 | B8: SWEBOK | C8: 1. 複雑性の最小化(SWEBOK 4-1.1, 4-3.1) | D8: Low | E8: マジックナンバー・マジック文字列がない | F8: リテラル値(0/1/空文字と自明な値を除く)が名前付き定数・設定値として定義されている | G8: 裸のリテラルは意味と変更箇所が追えず、仕様変更時の修正漏れ・二重管理を生む。名前付き定数化で意図と変更点を一元化する。 | H8: swebok-v4a.pdf ch04 Software Construction > 4-3.3 Coding(名前付き定数等の使用) | I8: CORE | J8: 原則適用。案件スコープ・成果物・規制・リスク上非該当の場合はN/A根拠を記録。 | K8: SRC-SWEBOK-V4A
A9: CON-010 | B9: SWEBOK | C9: 2. 命名とコーディング規約(SWEBOK 4-1.5, 4-3.3) | D9: Critical | E9: コーディング規約が存在し機械的に適用されている | F9: 規約文書があり、リンタ・フォーマッタの設定ファイルがリポジトリに存在し、CIで実行されている | G9: 規約が文書だけで自動適用されないと、レビューがスタイル指摘で浪費され、指摘のばらつきがチーム摩擦と品質のムラを生む。機械化で人間のレビューを設計・ロジックに集中させる。 | H9: swebok-v4a.pdf ch04 Software Construction > 4-1.5 Applying Standards in Construction(コーディング標準) | I9: CORE | J9: 原則適用。案件スコープ・成果物・規制・リスク上非該当の場合はN/A根拠を記録。 | K9: SRC-SWEBOK-V4A
A10: CON-011 | B10: SWEBOK | C10: 2. 命名とコーディング規約(SWEBOK 4-1.5, 4-3.3) | D10: High | E10: 命名規則が規約と一致している | F10: 型・関数・変数・定数・ファイル名が規約の命名規則(ケース規約・接頭辞等)に100%一致している | G10: 命名規則の不統一はコード検索・自動リファクタリングの妨げとなり、読み手に「これは別物か」という誤った推測をさせる。 | H10: swebok-v4a.pdf ch04 Software Construction > 4-1.5 Applying Standards in Construction / 4-3.3 Coding(命名規約) | I10: CORE | J10: 原則適用。案件スコープ・成果物・規制・リスク上非該当の場合はN/A根拠を記録。 | K10: SRC-SWEBOK-V4A
A11: CON-012 | B11: SWEBOK | C11: 2. 命名とコーディング規約(SWEBOK 4-1.5, 4-3.3) | D11: High | E11: 名前が意図を表している | F11: 変数・関数名から役割が読み取れる(`data`, `tmp`, `flag`, `doProcess` のような無情報名が新規コードにない) | G11: 無情報名は読み手に実装を全読させるコストを課し、変数の役割の誤解による誤修正を招く。名前だけで意図が伝わればレビューと保守が速くなる。 | H11: swebok-v4a.pdf ch04 Software Construction > 4-3.3 Coding(理解可能なソースコード作成技法) | I11: CORE | J11: 原則適用。案件スコープ・成果物・規制・リスク上非該当の場合はN/A根拠を記録。 | K11: SRC-SWEBOK-V4A
A12: CON-013 | B12: SWEBOK | C12: 2. 命名とコーディング規約(SWEBOK 4-1.5, 4-3.3) | D12: Medium | E12: 名前の一貫性がある | F12: 同一概念に同一の語が使われている(例: 取得を get/fetch/retrieve と混在させていない)。対義語ペア(open/close, begin/end)が対応している | G12: 同一概念への異なる語の混在は「別の振る舞いがあるのでは」という誤読を誘い、grep漏れによる修正漏れも起こす。 | H12: swebok-v4a.pdf ch04 Software Construction > 4-3.3 Coding(命名規約) | I12: CORE | J12: 原則適用。案件スコープ・成果物・規制・リスク上非該当の場合はN/A根拠を記録。 | K12: SRC-SWEBOK-V4A
A13: CON-014 | B13: SWEBOK | C13: 2. 命名とコーディング規約(SWEBOK 4-1.5, 4-3.3) | D13: Medium | E13: 略語・造語が管理されている | F13: 使用される略語がプロジェクトの用語集または規約に定義されているか、ドメインで周知のもの(ID, URL 等)に限られる | G13: 未定義の略語・造語は新規参画者の理解を阻害し、同じ概念に別名が増殖して用語の分裂を招く。 | H13: swebok-v4a.pdf ch04 Software Construction > 4-1.5 Applying Standards in Construction(コミュニケーション標準) | I13: CORE | J13: 原則適用。案件スコープ・成果物・規制・リスク上非該当の場合はN/A根拠を記録。 | K13: SRC-SWEBOK-V4A
... A24: CON-027 | B24: SWEBOK | C24: 3. エラー処理・例外処理・フォールトトレランス(SWEBOK 4-4.5) | D24: High | E24: エラー経路でも後処理が保証される | F24: 例外発生時もクリーンアップ(finally/defer/using/with 等)が実行され、部分的な状態変更が残らない(またはロールバックされる) | G24: エラー経路でのクリーンアップ漏れはリソースリークと中途半端な状態(半端に更新されたデータ)を残し、後続処理の不可解な失敗として跳ね返る。 | H24: swebok-v4a.pdf ch04 Software Construction > 4-4.5 Error Handling / 4-4.14(リソース規律) | I24: CORE | J24: 原則適用。案件スコープ・成果物・規制・リスク上非該当の場合はN/A根拠を記録。 | K24: SRC-SWEBOK-V4A
A25: CON-030 | B25: SWEBOK | C25: 4. 防御的プログラミング・アサーション・契約(SWEBOK 4-4.4) | D25: Critical | E25: 外部入力が信頼境界で検証されている | F25: 外部由来の入力(ユーザ入力・API引数・ファイル・環境変数)が、型・範囲・長さ・形式について使用前に検証され、不合格時の挙動が定義されている | G25: 信頼境界での入力検証の欠如は、不正データによる誤動作にとどまらずインジェクション等の攻撃起点になる。防御的プログラミングの第一原則。 | H25: swebok-v4a.pdf ch04 Software Construction > 4-4.4 Defensive Programming(不正入力からルーチンを守る) | I25: CORE | J25: 原則適用。案件スコープ・成果物・規制・リスク上非該当の場合はN/A根拠を記録。 | K25: SRC-SWEBOK-V4A | L25: OPS-OBSERVABILITY
A26: CON-031 | B26: SWEBOK | C26: 4. 防御的プログラミング・アサーション・契約(SWEBOK 4-4.4) | D26: High | E26: 公開関数の事前条件が明示されている | F26: 公開API・公開メソッドの引数制約(null可否・値域)がdocコメントに記述され、違反時に定義済みのエラー(例外・エラー値)を返す | G26: 事前条件が暗黙だと呼び出し側は推測で使うことになり、境界値での未定義動作や「nullを渡したら壊れた」型の欠陥が統合時に多発する。 | H26: swebok-v4a.pdf ch04 Software Construction > 4-4.4 Design by Contract(事前条件・事後条件による契約) | I26: CORE | J26: 原則適用。案件スコープ・成果物・規制・リスク上非該当の場合はN/A根拠を記録。 | K26: SRC-SWEBOK-V4A | L26: OPS-OBSERVABILITY
A27: CON-032 | B27: SWEBOK | C27: 4. 防御的プログラミング・アサーション・契約(SWEBOK 4-4.4) | D27: Medium | E27: 内部不変条件にアサーションが使われている | F27: 内部ロジックの「起こりえないはず」の状態がアサーションで表明されている。アサーションを外部入力の検証に流用していない | G27: 内部不変条件のアサーションは、修正時に紛れ込む前提破壊やインタフェース想定の不一致を開発段階で即座に炙り出す。外部入力検証への流用は本番で無効化され防御が消える。 | H27: swebok-v4a.pdf ch04 Software Construction > 4-4.4 Assertions(高信頼プログラムでの実行時チェック) | I27: CORE | J27: 原則適用。案件スコープ・成果物・規制・リスク上非該当の場合はN/A根拠を記録。 | K27: SRC-SWEBOK-V4A | L27: OPS-OBSERVABILITY
A28: CON-033 | B28: SWEBOK | C28: 4. 防御的プログラミング・アサーション・契約(SWEBOK 4-4.4) | D28: High | E28: アサーションに副作用がない | F28: アサーション式の中で状態変更・I/O を行っていない(無効化時に挙動が変わらない) | G28: アサーションはリリースビルドでコンパイルアウトされ得るため、副作用があると開発時と本番で挙動が変わる再現困難なバグ(ハイゼンバグ)を生む。 | H28: swebok-v4a.pdf ch04 Software Construction > 4-4.4 Assertions(開発時に組み込み、後に除去される特性) | I28: CORE | J28: 原則適用。案件スコープ・成果物・規制・リスク上非該当の場合はN/A根拠を記録。 | K28: SRC-SWEBOK-V4A | L28: OPS-OBSERVABILITY
A29: CON-034 | B29: SWEBOK | C29: 4. 防御的プログラミング・アサーション・契約(SWEBOK 4-4.4) | D29: High | E29: null/未定義値の扱いが一貫している | F29: null許容の方針(Optional型・null注釈・ガード節)が統一され、null由来の実行時エラーの可能性が静的に検出できる形になっている | G29: null方針の不統一は最も頻度の高い実行時エラー(NPE等)の温床。静的に検出可能な形へ寄せることで、実行して初めて分かる欠陥をコンパイル時に前倒しする。 | H29: swebok-v4a.pdf ch04 Software Construction > 4-4.4 Defensive Programming(実務補完: null安全機構) | I29: CORE | J29: 原則適用。案件スコープ・成果物・規制・リスク上非該当の場合はN/A根拠を記録。 | K29: SRC-SWEBOK-V4A;SRC-PRACTICE | L29: OPS-OBSERVABILITY
A30: CON-035 | B30: SWEBOK | C30: 4. 防御的プログラミング・アサーション・契約(SWEBOK 4-4.4) | D30: Medium | E30: 数値演算の危険が防御されている | F30: ゼロ除算・オーバーフロー・精度(金額への浮動小数点使用禁止等)が考慮され、境界での挙動がテストされている | G30: ゼロ除算・オーバーフロー・浮動小数点の丸めは正常系テストでは顕在化せず、本番の境界データで金額不一致等の重大インシデントとして発覚する。 | H30: swebok-v4a.pdf ch04 Software Construction > 4-4.4 Defensive Programming / 4-3.3 Coding(データ型の適切な使用) | I30: CORE | J30: 原則適用。案件スコープ・成果物・規制・リスク上非該当の場合はN/A根拠を記録。 | K30: SRC-SWEBOK-V4A | L30: OPS-OBSERVABILITY
A31: CON-040 | B31: SWEBOK | C31: 5. セキュアコーディング(SWEBOK 4-3.3, ISO/IEC 27034, NIST SSDF) | D31: Critical | E31: インジェクションが防止されている | F31: SQL・OSコマンド・パス・テンプレートへの外部入力の埋め込みが、プレースホルダ/パラメータ化API/エスケープ関数経由に限定され、文字列連結による組み立てがない | G31: インジェクションは外部入力の文字列連結一箇所でデータ全件漏洩・改ざんに直結する最重要脆弱性。パラメータ化APIの強制で構造的に排除する。 | H31: swebok-v4a.pdf ch04 Software Construction > 4-3.3 Coding(コードレベルのセキュリティ侵害防止)/ 実務補完(OWASP Top 10) | I31: CORE | J31: 原則適用。案件スコープ・成果物・規制・リスク上非該当の場合はN/A根拠を記録。 | K31: SRC-SWEBOK-V4A;SRC-OWASP;SRC-PRACTICE
A32: CON-041 | B32: SWEBOK | C32: 5. セキュアコーディング(SWEBOK 4-3.3, ISO/IEC 27034, NIST SSDF) | D32: Critical | E32: 機密情報がコードに埋め込まれていない | F32: パスワード・APIキー・秘密鍵がソースコード・設定ファイル・ログ出力・テストコードに平文で存在しない(シークレット管理機構経由である) | G32: コードに埋め込まれた秘密情報はリポジトリ履歴に永久に残り、リポジトリ閲覧権限者全員やフォーク先へ漏洩する。漏洩後のローテーションコストは極めて高い。 | H32: 実務補完(NIST SSDF PW.1 / OWASP ASVS) | I32: CORE | J32: 原則適用。案件スコープ・成果物・規制・リスク上非該当の場合はN/A根拠を記録。 | K32: SRC-OWASP;SRC-NIST;SRC-PRACTICE
A33: CON-042 | B33: SWEBOK | C33: 5. セキュアコーディング(SWEBOK 4-3.3, ISO/IEC 27034, NIST SSDF) | D33: Critical | E33: バッファ・メモリ安全性が確保されている | F33: (該当言語で)境界チェックのない文字列/配列操作関数を使用せず、確保・解放が対で管理されている。静的解析のメモリ安全性警告がゼロ | G33: バッファオーバーフロー・解放後使用は任意コード実行に至る最悪クラスの脆弱性で、SWEBOKもC/C++ライブラリ関数の安全でない使用を明示的に警告している。 | H33: swebok-v4a.pdf ch04 Software Construction > 4-3.2 Construction Languages / 4-3.3 Coding(バッファオーバーフロー・配列境界) | I33: CORE | J33: 原則適用。案件スコープ・成果物・規制・リスク上非該当の場合はN/A根拠を記録。 | K33: SRC-SWEBOK-V4A
A34: CON-043 | B34: SWEBOK | C34: 5. セキュアコーディング(SWEBOK 4-3.3, ISO/IEC 27034, NIST SSDF) | D34: High | E34: 出力時のエンコード・エスケープがある | F34: HTML/JSON/ログ等への出力時に文脈に応じたエスケープが行われている(XSS・ログ改ざん防止) | G34: 出力時エスケープの欠如はXSSやログインジェクションとして、入力検証をすり抜けたデータが利用者・運用者への攻撃に転化する経路を作る。 | H34: swebok-v4a.pdf ch04 Software Construction > 4-3.3 Coding(セキュリティ侵害防止)/ 実務補完(OWASP: 文脈依存エンコード) | I34: CORE | J34: 原則適用。案件スコープ・成果物・規制・リスク上非該当の場合はN/A根拠を記録。 | K34: SRC-SWEBOK-V4A;SRC-OWASP;SRC-PRACTICE
A35: CON-044 | B35: SWEBOK | C35: 5. セキュアコーディング(SWEBOK 4-3.3, ISO/IEC 27034, NIST SSDF) | D35: High | E35: 認可チェックが処理側にある | F35: 保護対象の操作・データアクセスの直前でサーバ側の認可検証が行われている(クライアント側チェックのみに依存していない) | G35: クライアント側チェックのみの認可はリクエスト改変で容易に迂回され、権限のないデータ閲覧・操作(IDOR)を許す。サーバ側の処理直前チェックが唯一の防衛線。 | H35: 実務補完(OWASP Top 10: Broken Access Control) | I35: CORE | J35: 原則適用。案件スコープ・成果物・規制・リスク上非該当の場合はN/A根拠を記録。 | K35: SRC-OWASP;SRC-PRACTICE | L35: SEC-IAM
A36: CON-045 | B36: SWEBOK | C36: 5. セキュアコーディング(SWEBOK 4-3.3, ISO/IEC 27034, NIST SSDF) | D36: High | E36: 安全な暗号・乱数が使われている | F36: 独自暗号を実装せず、標準ライブラリの暗号APIを使用。セキュリティ用途に非暗号論的乱数(rand 等)を使っていない | G36: 独自暗号や非暗号論的乱数のセキュリティ用途使用は、専門家には既知の手法で突破される「守っているつもり」の状態を生む。実績ある標準実装のみを許す。 | H36: 実務補完(NIST SSDF / CWE-327, CWE-338) | I36: CORE | J36: 原則適用。案件スコープ・成果物・規制・リスク上非該当の場合はN/A根拠を記録。 | K36: SRC-NIST;SRC-PRACTICE | L36: SEC-CRYPTO
A37: CON-046 | B37: SWEBOK | C37: 5. セキュアコーディング(SWEBOK 4-3.3, ISO/IEC 27034, NIST SSDF) | D37: Medium | E37: 機密データがログ・エラーに漏れない | F37: 個人情報・認証情報がログ・例外メッセージ・スタックトレース経由で出力されない(マスキングされている) | G37: ログ・スタックトレースは監視基盤等アクセス制御の緩い場所へ複製されやすく、そこに載った個人情報・認証情報は漏洩事故と法令違反(個人情報保護)に直結する。 | H37: 実務補完(OWASP ASVS: ログ保護) | I37: CORE | J37: 原則適用。案件スコープ・成果物・規制・リスク上非該当の場合はN/A根拠を記録。 | K37: SRC-OWASP;SRC-PRACTICE | L37: OPS-OBSERVABILITY
A38: CON-050 | B38: SWEBOK | C38: 6. 並行処理(SWEBOK 4-4.10) | D38: Critical | E38: 共有可変状態が同期化されている | F38: 複数スレッド/タスクから読み書きされる可変データすべてに同期機構(ミューテックス・モニタ・アトミック型)または不変化・メッセージ渡しの対策があり、対策のない共有可変変数がない | G38: 無同期の共有可変状態はデータ競合を生み、負荷やタイミング依存で稀にしか再現しない破壊的バグとして本番でのみ顕在化する。SWEBOKの並行処理プリミティブはこの対策の道具立て。 | H38: swebok-v4a.pdf ch04 Software Construction > 4-4.10 Concurrency Primitives(セマフォ・モニタ・ミューテックス) | I38: CORE | J38: 原則適用。案件スコープ・成果物・規制・リスク上非該当の場合はN/A根拠を記録。 | K38: SRC-SWEBOK-V4A
A39: CON-051 | B39: SWEBOK | C39: 6. 並行処理(SWEBOK 4-4.10) | D39: Critical | E39: デッドロックの構造的予防がある | F39: 複数ロックの取得順序が全箇所で一定であるか、単一ロック設計になっている。ロック保持中の外部呼び出し(I/O・コールバック)がない | G39: デッドロックは発生すると系全体が無応答のまま固まり、再起動でしか復旧できない。ロック順序の統一など構造的予防でしか確実に防げない。 | H39: swebok-v4a.pdf ch04 Software Construction > 4-4.10 Concurrency Primitives / 4-3.3 Coding(排他機構の規律ある使用) | I39: CORE | J39: 原則適用。案件スコープ・成果物・規制・リスク上非該当の場合はN/A根拠を記録。 | K39: SRC-SWEBOK-V4A
A40: CON-052 | B40: SWEBOK | C40: 6. 並行処理(SWEBOK 4-4.10) | D40: High | E40: ロック解放が例外時も保証される | F40: ロック取得と解放が finally/RAII/using 等の言語機構で対になっており、早期return・例外で解放漏れが起きない | G40: 例外経路でのロック解放漏れは、以降そのロックを待つ全スレッドを永久ブロックさせる。言語機構による対の保証で人為ミスを排除する。 | H40: swebok-v4a.pdf ch04 Software Construction > 4-4.10 Concurrency Primitives / 4-4.5(エラー経路の後処理) | I40: CORE | J40: 原則適用。案件スコープ・成果物・規制・リスク上非該当の場合はN/A根拠を記録。 | K40: SRC-SWEBOK-V4A
A41: CON-053 | B41: SWEBOK | C41: 6. 並行処理(SWEBOK 4-4.10) | D41: High | E41: 自作同期機構を使っていない | F41: セマフォ・ミューテックス・並行コレクション等、言語/標準ライブラリの実績あるプリミティブを使用し、フラグ変数ポーリングや二重チェックロック等の自作機構がない | G41: 自作同期機構はメモリモデルの微妙な仕様(可視性・リオーダリング)を踏み外しやすく、テストでは検出不能な競合を埋め込む。実績あるプリミティブの使用が唯一安全。 | H41: swebok-v4a.pdf ch04 Software Construction > 4-4.10 Concurrency Primitives(言語/OS提供の抽象を使う) | I41: CORE | J41: 原則適用。案件スコープ・成果物・規制・リスク上非該当の場合はN/A根拠を記録。 | K41: SRC-SWEBOK-V4A
A42: CON-054 | B42: SWEBOK | C42: 6. 並行処理(SWEBOK 4-4.10) | D42: Medium | E42: チェックと使用の分離(TOCTOU)がない | F42: 「検査してから操作する」処理(存在確認→作成等)がアトミック操作または同一ロック内で行われている | G42: 検査と使用の間の割り込みは「存在確認したのに作成で失敗」等の間欠バグとなり、セキュリティ文脈では権限昇格(TOCTOU攻撃)にもつながる。 | H42: swebok-v4a.pdf ch04 Software Construction > 4-4.10 Concurrency Primitives(実務補完: CWE-367) | I42: CORE | J42: 原則適用。案件スコープ・成果物・規制・リスク上非該当の場合はN/A根拠を記録。 | K42: SRC-SWEBOK-V4A;SRC-PRACTICE
A43: CON-055 | B43: SWEBOK | C43: 6. 並行処理(SWEBOK 4-4.10) | D43: Medium | E43: スレッド安全性が文書化されている | F43: 公開クラス・関数のスレッド安全性(安全/条件付き/非安全)がdocコメントに明記されている | G43: スレッド安全性が不明なAPIは利用者に「たぶん安全」という賭けを強い、非安全なクラスのマルチスレッド利用という気づきにくい欠陥を生む。 | H43: swebok-v4a.pdf ch04 Software Construction > 4-4.10 Concurrency Primitives / 4-4.1 API Design(セマンティクスの明示) | I43: CORE | J43: 原則適用。案件スコープ・成果物・規制・リスク上非該当の場合はN/A根拠を記録。 | K43: SRC-SWEBOK-V4A
A44: CON-056 | B44: SWEBOK | C44: 6. 並行処理(SWEBOK 4-4.10) | D44: Medium | E44: 非同期処理の完了とキャンセルが扱われている | F44: 生成したスレッド・タスク・ゴルーチンの完了待ち/キャンセル/タイムアウトの経路があり、放置される(fire-and-forget の)処理には明示の理由がある | G44: fire-and-forgetのタスクは失敗が誰にも観測されず、シャットダウン時の処理中断やリソースリークの原因になる。完了・キャンセル経路の明示で制御下に置く。 | H44: swebok-v4a.pdf ch04 Software Construction > 4-4.10 Concurrency Primitives / 4-4.12(並行・分散の実務補完) | I44: CORE | J44: 原則適用。案件スコープ・成果物・規制・リスク上非該当の場合はN/A根拠を記録。 | K44: SRC-SWEBOK-V4A;SRC-PRACTICE
A45: CON-060 | B45: SWEBOK | C45: 7. リソース管理・性能(SWEBOK 4-4.14) | D45: Critical | E45: リソースの解放が保証されている | F45: ファイル・ソケット・DB接続・ハンドルの取得箇所すべてに、例外時も実行される解放処理(try-with-resources/defer/with/RAII)がある | G45: 解放されないファイル・接続・ハンドルは長時間稼働で枯渇し、「数日に一度落ちる」型の再現困難な本番障害を引き起こす。 | H45: swebok-v4a.pdf ch04 Software Construction > 4-3.3 Coding(直列再利用可能資源へのアクセス規律) | I45: CORE | J45: 原則適用。案件スコープ・成果物・規制・リスク上非該当の場合はN/A根拠を記録。 | K45: SRC-SWEBOK-V4A
A46: CON-061 | B46: SWEBOK | C46: 7. リソース管理・性能(SWEBOK 4-4.14) | D46: High | E46: ループ内の高コスト処理が排除されている | F46: ループ内での不変値の再計算、N+1クエリ、逐次的な文字列連結による再確保など、計算量を悪化させる定型パターンがない | G46: N+1クエリやループ内再計算は小規模データのテストでは気づかれず、本番データ量で応答時間が桁違いに悪化してから発覚する。コードレビュー段階の検出が最も安価。 | H46: swebok-v4a.pdf ch04 Software Construction > 4-4.14 Performance Analysis and Tuning(ループ・式のチューニング) | I46: CORE | J46: 原則適用。案件スコープ・成果物・規制・リスク上非該当の場合はN/A根拠を記録。 | K46: SRC-SWEBOK-V4A | L46: COST
A47: CON-062 | B47: SWEBOK | C47: 7. リソース管理・性能(SWEBOK 4-4.14) | D47: Medium | E47: データ構造・アルゴリズムの選択が妥当である | F47: データ量に対して計算量が成立する構造が選ばれている(大量データへの線形探索の繰り返し等がない)。大規模データはストリーミング/ページングで処理される | G47: 計算量が成立しないデータ構造の選択は、後からの差し替えコストが大きく、データ増加とともに静かに劣化するため早期のレビューで正す必要がある。 | H47: swebok-v4a.pdf ch04 Software Construction > 4-4.14 Performance Analysis(アルゴリズム・データ構造選択が効率を決定) | I47: CORE | J47: 原則適用。案件スコープ・成果物・規制・リスク上非該当の場合はN/A根拠を記録。 | K47: SRC-SWEBOK-V4A
A48: CON-063 | B48: SWEBOK | C48: 7. リソース管理・性能(SWEBOK 4-4.14) | D48: Medium | E48: チューニングは計測に基づいている | F48: 可読性を犠牲にした最適化コードには、プロファイリング結果等の根拠(コメントまたはレビュー記録)が添えられている | G48: 推測に基づく最適化は可読性を犠牲にしながら実際のホットスポットを外すことが多い。SWEBOKの性能分析(プロファイリングでホットスポット特定→チューニング)の順序を強制する。 | H48: swebok-v4a.pdf ch04 Software Construction > 4-4.14 Performance Analysis and Tuning / 4-5.4 Profiling Tools | I48: CORE | J48: 原則適用。案件スコープ・成果物・規制・リスク上非該当の場合はN/A根拠を記録。 | K48: SRC-SWEBOK-V4A
A49: CON-064 | B49: SWEBOK | C49: 7. リソース管理・性能(SWEBOK 4-4.14) | D49: Medium | E49: 接続・スレッドがプール管理されている | F49: DB接続・HTTPクライアント等の高コスト資源が都度生成されず、プール/共有インスタンスで管理され、上限が設定されている | G49: 高コスト資源の都度生成は接続確立オーバーヘッドとリソース枯渇を招き、上限のないプールは障害時に接続爆発で依存先を巻き込む。 | H49: swebok-v4a.pdf ch04 Software Construction > 4-4.14 Performance(実務補完: 接続プール管理) | I49: CORE | J49: 原則適用。案件スコープ・成果物・規制・リスク上非該当の場合はN/A根拠を記録。 | K49: SRC-SWEBOK-V4A;SRC-PRACTICE
A50: CON-065 | B50: SWEBOK | C50: 7. リソース管理・性能(SWEBOK 4-4.14) | D50: Low | E50: メモリ保持の上限がある | F50: 無制限に成長しうるキャッシュ・コレクションに上限・破棄方針(サイズ上限・TTL)がある | G50: 上限のないキャッシュ・コレクションは正常動作のままメモリを食い潰し、OOMによる突然死という最も切り分けにくい障害になる。 | H50: swebok-v4a.pdf ch04 Software Construction > 4-4.14 Performance(実務補完: メモリ管理) | I50: CORE | J50: 原則適用。案件スコープ・成果物・規制・リスク上非該当の場合はN/A根拠を記録。 | K50: SRC-SWEBOK-V4A;SRC-PRACTICE
A51: CON-070 | B51: SWEBOK | C51: 8. API設計・インタフェース(SWEBOK 4-4.1) | D51: High | E51: APIが誤用しにくい設計である | F51: 引数の順序・型で誤用が防がれている(同型引数の連続にはビルダー/名前付き引数を使用)。不正な状態を型レベルで表現できない設計になっている | G51: 誤用しやすいAPIは呼び出し側の数だけバグを量産する。SWEBOKはAPI設計の要件として「誤用が困難であること」を明示しており、型で不正状態を排除する設計はその実装手段。 | H51: swebok-v4a.pdf ch04 Software Construction > 4-4.1 API Design and Use(difficult to misuse) | I51: CORE | J51: 原則適用。案件スコープ・成果物・規制・リスク上非該当の場合はN/A根拠を記録。 | K51: SRC-SWEBOK-V4A
A52: CON-071 | B52: SWEBOK | C52: 8. API設計・インタフェース(SWEBOK 4-4.1) | D52: High | E52: 後方互換性が維持されている | F52: 公開APIの変更が互換(追加のみ)であるか、非互換変更にバージョニング(セマンティックバージョニング・APIバージョン)と非推奨期間が設けられている | G52: APIは実装より長生きするため、無断の非互換変更は全クライアントを同時に壊す。SWEBOKもAPIの後方互換性維持と安定性を設計要件に挙げる。 | H52: swebok-v4a.pdf ch04 Software Construction > 4-4.1 API Design and Use(backward compatibility / 安定性) | I52: CORE | J52: 原則適用。案件スコープ・成果物・規制・リスク上非該当の場合はN/A根拠を記録。 | K52: SRC-SWEBOK-V4A
A53: CON-072 | B53: SWEBOK | C53: 8. API設計・インタフェース(SWEBOK 4-4.1) | D53: High | E53: 公開APIが文書化されている | F53: 公開関数・エンドポイントに目的・引数・戻り値・例外/エラー応答・使用例が記述されている。Web APIはOpenAPI等の機械可読定義がある | G53: APIはシグネチャだけでなくセマンティクス(効果・振る舞い)の記述を含むべきというSWEBOKの要請。文書がないと利用者は実装を読むか試行錯誤で使い、誤用が広がる。 | H53: swebok-v4a.pdf ch04 Software Construction > 4-4.1 API Design and Use(セマンティクスの記述・OpenAPI) | I53: CORE | J53: 原則適用。案件スコープ・成果物・規制・リスク上非該当の場合はN/A根拠を記録。 | K53: SRC-SWEBOK-V4A
A54: CON-073 | B54: SWEBOK | C54: 8. API設計・インタフェース(SWEBOK 4-4.1) | D54: Medium | E54: 公開範囲が最小化されている | F54: 内部実装がpublicになっていない(アクセス修飾子・モジュール公開設定が最小権限)。公開APIの数が意図的に管理されている | G54: 内部実装の意図せぬ公開は外部から依存され、以後の内部変更がすべて破壊的変更になる。公開面の最小化は将来の変更の自由を守る。 | H54: swebok-v4a.pdf ch04 Software Construction > 4-4.1 API Design and Use / 4-1.2 Anticipating Change | I54: CORE | J54: 原則適用。案件スコープ・成果物・規制・リスク上非該当の場合はN/A根拠を記録。 | K54: SRC-SWEBOK-V4A
A55: CON-074 | B55: SWEBOK | C55: 8. API設計・インタフェース(SWEBOK 4-4.1) | D55: Medium | E55: 入出力の契約が安定している | F55: 戻り値のnull/空コレクションの規約が統一され、可変オブジェクトの内部状態を直接返却・受領していない(防御的コピーまたは不変型) | G55: 可変内部状態の直接返却は呼び出し側からの意図せぬ書き換えという遠隔作用バグを許す。null/空の規約不統一は呼び出し側の防御コードの漏れを誘う。 | H55: swebok-v4a.pdf ch04 Software Construction > 4-4.1 API Design and Use / 4-4.4 Design by Contract | I55: CORE | J55: 原則適用。案件スコープ・成果物・規制・リスク上非該当の場合はN/A根拠を記録。 | K55: SRC-SWEBOK-V4A
A56: CON-075 | B56: SWEBOK | C56: 8. API設計・インタフェース(SWEBOK 4-4.1) | D56: Medium | E56: エラー応答が仕様化されている | F56: APIのエラー時の応答(エラーコード体系・メッセージ形式・HTTPステータス)が定義され、実装と一致している | G56: エラー応答が未仕様だとクライアントはエラーの機械判定ができず、障害時に「リトライすべきか・諦めるべきか」を誤って二次被害を広げる。 | H56: swebok-v4a.pdf ch04 Software Construction > 4-4.1 API Design and Use / 4-4.5 Error Handling(例外報告の標準化) | I56: CORE | J56: 原則適用。案件スコープ・成果物・規制・リスク上非該当の場合はN/A根拠を記録。 | K56: SRC-SWEBOK-V4A
A57: CON-902 | B57: 追加承認 | C57: 8. API設計・インタフェース(SWEBOK 4-4.1) | D57: Medium | E57: 再利用を意図した共通部品が再利用可能な品質で構築されている | F57: 共通ライブラリ・共有モジュールとして提供されるコードは、可変点がパラメータ・設定・拡張ポイントとして明示され、特定プロジェクト固有のロジックのハードコードがなく、利用方法の文書と可変性を検証するテストがある | G57: 特定案件の都合が焼き込まれた「共通部品」は他所で使えず、コピーして改変されてクローン増殖の起点になる。作る側の可変性設計と文書化を確認して再利用を成立させる。 | H57: swebok-v4a.pdf ch04 Software Construction > 3.5 Reuse in Construction — 再利用のための構築(可変性の実装・カプセル化・再利用資産の記述と公開) | I57: CORE | J57: 原則適用。案件スコープ・成果物・規制・リスク上非該当の場合はN/A根拠を記録。 | K57: SRC-SWEBOK-V4A
A58: CON-904 | B58: 追加承認 | C58: 8. API設計・インタフェース(SWEBOK 4-4.1) | D58: Low | E58: プラットフォーム依存コードが分離されている | F58: 複数プラットフォーム(OS・ブラウザ・実行環境)対応が要件の場合、プラットフォーム固有API・非標準機能の使用箇所が抽象化層・アダプタに隔離され、ビジネスロジックが標準API(POSIX、Web標準等)の範囲で記述されている | G58: プラットフォーム依存コードが全体に散在すると、対応環境の追加・変更時に全面書き換えとなり、特定環境でのみ再現する欠陥の温床にもなる。 | H58: swebok-v4a.pdf ch04 Software Construction > 3.8 Cross-Platform Development / 4.15 Platform Standards(クロスプラットフォーム開発とプラットフォーム標準) | I58: CORE | J58: 原則適用。案件スコープ・成果物・規制・リスク上非該当の場合はN/A根拠を記録。 | K58: SRC-SWEBOK-V4A
... A67: CON-090 | B67: SWEBOK | C67: 10. ビルド・依存関係管理(SWEBOK 4-2.4) | D67: Critical | E67: ビルドが再現可能である | F67: 依存のバージョンがマニフェスト+ロックファイルで固定され、クリーン環境(CI)で同一手順により同一成果物がビルドできる | G67: ビルドが再現不能だと「自分の環境では動く」問題と、依存の暗黙更新による無変更デグレードが起きる。ロックファイルとクリーン環境ビルドで成果物を決定的にする。 | H67: swebok-v4a.pdf ch04 Software Construction > 4-2.4 Managing Dependencies(パッケージマネージャによる依存管理) | I67: CORE | J67: 原則適用。案件スコープ・成果物・規制・リスク上非該当の場合はN/A根拠を記録。 | K67: SRC-SWEBOK-V4A
A68: CON-091 | B68: SWEBOK | C68: 10. ビルド・依存関係管理(SWEBOK 4-2.4) | D68: Critical | E68: 既知の重大脆弱性を持つ依存がない | F68: 依存関係の脆弱性スキャンが実行され、Critical/High の脆弱性が残存しない(残存する場合はリスク受容の記録がある) | G68: SWEBOKは依存サプライチェーンの脆弱性伝播の防止を明示している。推移的依存の既知脆弱性は自プロダクトの脆弱性そのものであり、スキャンなしでは存在にすら気づけない。 | H68: swebok-v4a.pdf ch04 Software Construction > 4-2.4 Managing Dependencies(脆弱性の伝播防止) | I68: CORE | J68: 原則適用。案件スコープ・成果物・規制・リスク上非該当の場合はN/A根拠を記録。 | K68: SRC-SWEBOK-V4A | L68: SEC-SUPPLY-CHAIN
A69: CON-092 | B69: SWEBOK | C69: 10. ビルド・依存関係管理(SWEBOK 4-2.4) | D69: High | E69: 依存のライセンスが確認されている | F69: 全依存(推移的依存を含む)のライセンスが把握され、プロジェクトの配布形態と競合するライセンスがない | G69: SWEBOKが明示する依存のライセンス競合回避。コピーレフト等との競合は出荷後に発覚するとソース公開義務や販売停止など法務リスクに直結する。 | H69: swebok-v4a.pdf ch04 Software Construction > 4-2.4 Managing Dependencies(ライセンス競合の回避) | I69: CORE | J69: 原則適用。案件スコープ・成果物・規制・リスク上非該当の場合はN/A根拠を記録。 | K69: SRC-SWEBOK-V4A
A70: CON-093 | B70: SWEBOK | C70: 10. ビルド・依存関係管理(SWEBOK 4-2.4) | D70: Medium | E70: 不要な依存がない | F70: 未使用の依存がマニフェストに残っていない。小さな機能のために大型ライブラリを追加していない(追加時の選定理由が記録されている) | G70: SWEBOKは不要依存の回避によるビルド効率改善を明示する。不要依存は攻撃対象面積・脆弱性対応工数・ビルド時間を無意味に増やす。 | H70: swebok-v4a.pdf ch04 Software Construction > 4-2.4 Managing Dependencies(不要な依存の回避) | I70: CORE | J70: 原則適用。案件スコープ・成果物・規制・リスク上非該当の場合はN/A根拠を記録。 | K70: SRC-SWEBOK-V4A
A71: CON-094 | B71: SWEBOK | C71: 10. ビルド・依存関係管理(SWEBOK 4-2.4) | D71: High | E71: ビルドスクリプトが環境非依存である | F71: ビルドが特定個人の環境(絶対パス・ローカル固有ツール・手作業手順)に依存せず、必要なツールとバージョンがコード化されている | G71: 特定個人の環境に依存したビルドは、その人の不在・PC交換で誰もリリースできなくなる属人化リスクの典型。ツールとバージョンのコード化で誰でも再現可能にする。 | H71: swebok-v4a.pdf ch04 Software Construction > 4-1.5 Applying Standards / 4-3.7 Integration(実務補完: ビルド自動化) | I71: CORE | J71: 原則適用。案件スコープ・成果物・規制・リスク上非該当の場合はN/A根拠を記録。 | K71: SRC-SWEBOK-V4A;SRC-PRACTICE
A72: CON-095 | B72: SWEBOK | C72: 10. ビルド・依存関係管理(SWEBOK 4-2.4) | D72: Medium | E72: ビルド警告が管理されている | F72: コンパイラ/リンタの警告がゼロ、または警告をエラー扱いにする設定が有効(例外は明示的に抑制+理由記載) | G72: 放置された警告の山は「警告は見なくてよい」という文化を作り、その中に埋もれた本物の欠陥予兆(未初期化・型不一致等)を見逃させる。 | H72: swebok-v4a.pdf ch04 Software Construction > 4-3.6 Construction Quality(静的解析) | I72: CORE | J72: 原則適用。案件スコープ・成果物・規制・リスク上非該当の場合はN/A根拠を記録。 | K72: SRC-SWEBOK-V4A
A73: CON-096 | B73: SWEBOK | C73: 10. ビルド・依存関係管理(SWEBOK 4-2.4) | D73: Medium | E73: 依存の取得元が管理されている | F73: パッケージの取得元レジストリが明示され、内部パッケージの名前空間が保護されている(依存関係かく乱・typosquatting への考慮がある) | G73: SWEBOKが明示する「信頼できない外部依存の導入防止の規制・監視」。取得元が無管理だと依存関係かく乱・typosquattingで悪意あるパッケージが混入し得る。 | H73: swebok-v4a.pdf ch04 Software Construction > 4-2.4 Managing Dependencies(信頼できない外部依存の導入防止) | I73: CORE | J73: 原則適用。案件スコープ・成果物・規制・リスク上非該当の場合はN/A根拠を記録。 | K73: SRC-SWEBOK-V4A
A74: CON-100 | B74: SWEBOK | C74: 11. 統合・CI(SWEBOK 4-3.7, 4-4.17) | D74: Critical | E74: 継続的インテグレーションが構成されている | F74: 全コミット(またはPR)に対しビルド・静的解析・単体テストが自動実行され、結果が可視化されている | G74: CIがないと統合の失敗が数週間分まとめて発覚し、原因コミットの特定に膨大な時間を要する。SWEBOKはCIによる1日複数回の統合と高速フィードバックを標準実践とする。 | H74: swebok-v4a.pdf ch04 Software Construction > 4-3.7 Integration(継続的インテグレーション) | I74: CORE | J74: 原則適用。案件スコープ・成果物・規制・リスク上非該当の場合はN/A根拠を記録。 | K74: SRC-SWEBOK-V4A
A75: CON-101 | B75: SWEBOK | C75: 11. 統合・CI(SWEBOK 4-3.7, 4-4.17) | D75: High | E75: インクリメンタル統合になっている | F75: 変更が小さい単位(目安: PRが数百行以内)で頻繁に統合され、長期間未統合のブランチ(目安: 2週間超)がない | G75: SWEBOKはインクリメンタル統合の利点(エラー位置特定の容易さ・早期フィードバック)をフェーズド(ビッグバン)統合と対比して明示する。巨大PRと長命ブランチはレビュー精度低下とマージ地獄を招く。 | H75: swebok-v4a.pdf ch04 Software Construction > 4-3.7 Integration(インクリメンタル統合 vs フェーズド統合) | I75: CORE | J75: 原則適用。案件スコープ・成果物・規制・リスク上非該当の場合はN/A根拠を記録。 | K75: SRC-SWEBOK-V4A
A76: CON-102 | B76: SWEBOK | C76: 11. 統合・CI(SWEBOK 4-3.7, 4-4.17) | D76: High | E76: メインブランチがグリーンに保たれている | F76: メインブランチのビルド・テスト失敗が放置されず、失敗時の対応(即修正または差し戻し)のルールが運用されている | G76: 壊れたメインブランチの放置は全員の作業のベースを汚染し、「失敗は普通」という割れ窓状態を作ってCIの欠陥検出機能を無効化する。 | H76: swebok-v4a.pdf ch04 Software Construction > 4-3.7 Integration / 4-4.17 Feedback Loop for Construction | I76: CORE | J76: 原則適用。案件スコープ・成果物・規制・リスク上非該当の場合はN/A根拠を記録。 | K76: SRC-SWEBOK-V4A
A77: CON-103 | B77: SWEBOK | C77: 11. 統合・CI(SWEBOK 4-3.7, 4-4.17) | D77: Medium | E77: 統合順序・スタブ方針が計画されている | F77: 未完成コンポーネントとの結合にスタブ/モック/フィーチャーフラグの方針があり、統合の順序が構築計画に記述されている | G77: SWEBOKは統合順序の計画とスタブ・ドライバ・モック等の足場作りを統合の主要関心事に挙げる。無計画な結合は未完成部品待ちの手空きとビッグバン統合への逆戻りを生む。 | H77: swebok-v4a.pdf ch04 Software Construction > 4-3.7 Integration(統合順序の計画・スキャフォールディング)/ 4-2.2 Construction Planning | I77: CORE | J77: 原則適用。案件スコープ・成果物・規制・リスク上非該当の場合はN/A根拠を記録。 | K77: SRC-SWEBOK-V4A
A78: CON-104 | B78: SWEBOK | C78: 11. 統合・CI(SWEBOK 4-3.7, 4-4.17) | D78: Medium | E78: 静的解析がパイプラインに含まれる | F78: 静的解析ツールがCIで実行され、新規指摘の増加がブロックされる(ベースライン管理されている) | G78: 静的解析は実行せずに欠陥・脆弱性を検出できる構築品質の主要技法。CIに組み込まれていないと実行が任意になり、指摘の蓄積で誰も見なくなる。 | H78: swebok-v4a.pdf ch04 Software Construction > 4-3.6 Construction Quality(静的解析・セキュリティ弱点の自動解析) | I78: CORE | J78: 原則適用。案件スコープ・成果物・規制・リスク上非該当の場合はN/A根拠を記録。 | K78: SRC-SWEBOK-V4A
A79: CON-105 | B79: SWEBOK | C79: 11. 統合・CI(SWEBOK 4-3.7, 4-4.17) | D79: Low | E79: ビルド時間が管理されている | F79: CIの所要時間が計測されており、フィードバックループを損なう遅延(目安: 単体テストまで15分超)に対する改善計画がある | G79: CIの高速フィードバックは構築の欠陥検出コストを下げる根幹。ビルドが遅いと開発者は結果を待たずに次へ進み、失敗対応が遅れて統合頻度も下がる。 | H79: swebok-v4a.pdf ch04 Software Construction > 4-4.17 Feedback Loop for Construction(高速フィードバック) | I79: CORE | J79: 原則適用。案件スコープ・成果物・規制・リスク上非該当の場合はN/A根拠を記録。 | K79: SRC-SWEBOK-V4A
A80: CON-901 | B80: 追加承認 | C80: 11. 統合・CI(SWEBOK 4-3.7, 4-4.17) | D80: Medium | E80: 構築活動の計測が仕組み化されている | F80: コード規模・複雑度・テストカバレッジ・静的解析指摘数などの構築メトリクスがCI等で自動収集され、推移が参照可能である(ダッシュボードまたは定期レポートが存在する) | G80: 計測がないと複雑度や欠陥率の悪化に誰も気づかず、品質劣化が障害の増加という形で初めて発覚する。自動収集で構築品質を継続的に可視化する。 | H80: swebok-v4a.pdf ch04 Software Construction > 2.3 Construction Measurement(構築の計測) | I80: CORE | J80: 原則適用。案件スコープ・成果物・規制・リスク上非該当の場合はN/A根拠を記録。 | K80: SRC-SWEBOK-V4A
... A86: CON-115 | B86: SWEBOK | C86: 12. コード文書化・レビュー記録(SWEBOK 4-3.3, IEEE 1028) | D86: Low | E86: READMEと構築手順が最新である | F86: ビルド・テスト・実行手順の記述が現状のコードで再現でき、新規参画者が手順どおりに環境構築できる | G86: 陳腐化した構築手順は新規参画者の立ち上げを数日単位で浪費させ、緊急時に「ビルド方法が分からない」という最悪の事態を招く。 | H86: swebok-v4a.pdf ch04 Software Construction > 4-1.5 Applying Standards(文書標準)/ 実務補完(オンボーディング) | I86: CORE | J86: 原則適用。案件スコープ・成果物・規制・リスク上非該当の場合はN/A根拠を記録。 | K86: SRC-SWEBOK-V4A;SRC-PRACTICE

Sheet 05_テスト
A1: ID | B1: 区分 | C1: カテゴリ | D1: 基準重要度 | E1: チェック項目 | F1: 合格基準 | G1: 意図(なぜ確認するか) | H1: 対象ドキュメント(参照箇所) | I1: 適用プロファイル | J1: 適用条件 | K1: 出典ID | L1: 重複統制グループ | M1: 案件重要度 | N1: 適用判定 | O1: 判定 | P1: 証跡・参照箇所 | Q1: 指摘・Issue ID | R1: 対応方針 | S1: 例外・リスク受容承認者 | T1: 是正期限 | U1: レビュアー | V1: レビュー日 | W1: 再確認結果
A2: TST-001 | B2: SWEBOK | C2: 1. テスト計画(TST-001〜) | D2: Critical | E2: テスト対象のスコープが定義されている | F2: 対象と対象外の両方が機能・コンポーネント単位で列挙され、対象外には根拠が付記されている | G2: スコープが曖昧なまま進むと、対象外のはずの領域の障害流出や、逆に不要なテストへの工数浪費が起きる。悉皆テストは不可能というSWEBOKの前提の下、何を捨てるかの判断を明示させるための項目。 | H2: swebok-v4a.pdf ch05 Software Testing > 5.1.2 Test Guides and Organizational Process / 5.2.1 Test Planning Process | I2: CORE | J2: 原則適用。案件スコープ・成果物・規制・リスク上非該当の場合はN/A根拠を記録。 | K2: SRC-SWEBOK-V4A
A3: TST-002 | B3: SWEBOK | C3: 1. テスト計画(TST-001〜) | D3: Critical | E3: テストレベル構成が定義されている | F3: 単体/統合/システム/受入の各レベルについて、対象・目的・担当・使用環境が表等で明記されている | G3: レベル構成が未定義だと、単体で捕まえるべき欠陥がシステムテストまで持ち越されて修正コストが跳ね上がり、責任の押し付け合いも生じる。4段階の目的・担当を先に固定して欠陥検出の場所を最適化する。 | H3: swebok-v4a.pdf ch05 Software Testing > 2.1 The Target of the Test | I3: CORE | J3: 原則適用。案件スコープ・成果物・規制・リスク上非該当の場合はN/A根拠を記録。 | K3: SRC-SWEBOK-V4A
A4: TST-003 | B4: SWEBOK | C4: 1. テスト計画(TST-001〜) | D4: Critical | E4: 終了基準(Exit Criteria)が測定可能に定義されている | F4: 「全 Critical 障害修正済み」「分岐網羅率 80% 以上」等、数値または二値判定可能な条件で記述され、「十分にテストする」等の曖昧表現がない | G4: 「どこまでやれば十分か」を測定可能に定義しないと、終了判断が声の大きさや納期都合で決まり、品質根拠のないリリースや際限のないテスト継続を招く。 | H4: swebok-v4a.pdf ch05 Software Testing > 1.2.2 Test Selection and Adequacy Criteria / 5.1.8 Test Completion | I4: CORE | J4: 原則適用。案件スコープ・成果物・規制・リスク上非該当の場合はN/A根拠を記録。 | K4: SRC-SWEBOK-V4A
A5: TST-004 | B5: SWEBOK | C5: 1. テスト計画(TST-001〜) | D5: High | E5: 開始基準(Entry Criteria)が定義されている | F5: 各テストレベルの開始条件(前工程成果物の完成、環境準備完了等)が判定可能な形で列挙されている | G5: 開始条件が曖昧だと、未完成のビルドや未準備の環境でテストを始めて大量のBlockedと手戻りが発生し、実行工数が空費される。 | H5: swebok-v4a.pdf ch05 Software Testing > 5.2.1 Test Planning Process(実務補完: ISO/IEC/IEEE 29119-3) | I5: CORE | J5: 原則適用。案件スコープ・成果物・規制・リスク上非該当の場合はN/A根拠を記録。 | K5: SRC-SWEBOK-V4A;SRC-ISO-GENERAL;SRC-PRACTICE
A6: TST-005 | B6: SWEBOK | C6: 1. テスト計画(TST-001〜) | D6: High | E6: 中断・再開基準が定義されている | F6: テスト中断に至る条件(Blocked 率、環境障害等)と再開条件が記述されている | G6: 中断基準がないと、環境障害や先行欠陥の多発時に無意味な実行を続けて結果の信頼性を損ない、再開時にどこからやり直すかで混乱する。 | H6: 実務補完(ISO/IEC/IEEE 29119-3、IEEE 829系のテスト計画実務) | I6: CORE | J6: 原則適用。案件スコープ・成果物・規制・リスク上非該当の場合はN/A根拠を記録。 | K6: SRC-ISO-GENERAL;SRC-PRACTICE
A7: TST-006 | B7: SWEBOK | C7: 1. テスト計画(TST-001〜) | D7: Critical | E7: リスク分析に基づく重点化が行われている | F7: プロダクトリスクが発生確率と影響度で評価され、リスクの高い領域へのテスト重点配分(技法・工数・優先度)が計画に反映されている | G7: テストは常に限られた資源と無限のテスト要求のトレードオフであり、リスクに基づく重点化がないと低リスク領域に工数を均等散布して重大障害を見逃す。 | H7: swebok-v4a.pdf ch05 Software Testing > 5.1.2 Test Guides(リスクベースドテスト)/ 5.2.1 Test Planning Process(リスク計画) | I7: CORE | J7: 原則適用。案件スコープ・成果物・規制・リスク上非該当の場合はN/A根拠を記録。 | K7: SRC-SWEBOK-V4A
A8: TST-007 | B8: SWEBOK | C8: 1. テスト計画(TST-001〜) | D8: High | E8: テスト体制とロールが定義されている | F8: テスト管理者・設計者・実行者等のロールと担当者(またはアサイン方針)、独立性の程度が記述されている | G8: ロールと独立性が未定義だと、実装者バイアスで欠陥が見逃されたり、テスト実行の責任者不在で進捗が停滞したりする。 | H8: swebok-v4a.pdf ch05 Software Testing > 5.1.5 Test Team / 5.3 Staffing | I8: CORE | J8: 原則適用。案件スコープ・成果物・規制・リスク上非該当の場合はN/A根拠を記録。 | K8: SRC-SWEBOK-V4A
A9: TST-008 | B9: SWEBOK | C9: 1. テスト計画(TST-001〜) | D9: High | E9: スケジュールが工程と整合している | F9: テスト設計・環境構築・実行・報告の各活動に期間が割り当てられ、開発スケジュールとの依存関係が示されている | G9: テストが開発スケジュールと独立に立てられると、開発遅延のしわ寄せでテスト期間だけが圧縮され、計画したテストが実施されないままリリースされる。 | H9: swebok-v4a.pdf ch05 Software Testing > 5.2.1 Test Planning Process | I9: CORE | J9: 原則適用。案件スコープ・成果物・規制・リスク上非該当の場合はN/A根拠を記録。 | K9: SRC-SWEBOK-V4A
A10: TST-009 | B10: SWEBOK | C10: 1. テスト計画(TST-001〜) | D10: Medium | E10: 自動化方針が定義されている | F10: 自動化する範囲(回帰テスト等)と手動で行う範囲、使用ツール、CI への組込み方針が記述されている | G10: 自動化範囲を決めずに始めると、回帰テストが手動のまま肥大化して変更のたびに実行しきれなくなるか、費用対効果の低い箇所を自動化して保守負債になる。 | H10: swebok-v4a.pdf ch05 Software Testing > 1.2.11 Test Execution and Automation / 6.1.2 Testing in Line with Shift-Left Movement | I10: CORE | J10: 原則適用。案件スコープ・成果物・規制・リスク上非該当の場合はN/A根拠を記録。 | K10: SRC-SWEBOK-V4A
A11: TST-010 | B11: SWEBOK | C11: 1. テスト計画(TST-001〜) | D11: Medium | E11: テスト成果物の管理方法が定義されている | F11: テストケース・結果・インシデントの管理場所(ツール/リポジトリ)と版管理の方法が記述されている | G11: テスト成果物が構成管理されていないと、どの版の仕様に対するテスト結果か追跡できず、監査時に品質の証跡を示せなくなる。 | H11: swebok-v4a.pdf ch05 Software Testing > 5.1.4 Test Documentation(テスト文書はSCM管理下に置く) | I11: CORE | J11: 原則適用。案件スコープ・成果物・規制・リスク上非該当の場合はN/A根拠を記録。 | K11: SRC-SWEBOK-V4A
A12: TST-011 | B12: SWEBOK | C12: 1. テスト計画(TST-001〜) | D12: Medium | E12: 非機能テストの計画が含まれている | F12: 性能・負荷・セキュリティ等、要求に存在する非機能特性についてテストの実施有無と方法が明記され、実施しない場合は根拠がある | G12: 非機能テストは計画時に環境・ツール・期間の手当てが必要で、後付けでは実施不能になりやすい。性能・セキュリティ問題は本番で初めて顕在化すると被害が大きい。 | H12: swebok-v4a.pdf ch05 Software Testing > 2.2.7 Non-functional Testing / 2.2.8 Security Testing | I12: CORE | J12: 原則適用。案件スコープ・成果物・規制・リスク上非該当の場合はN/A根拠を記録。 | K12: SRC-SWEBOK-V4A
A13: TST-012 | B13: SWEBOK | C13: 1. テスト計画(TST-001〜) | D13: Low | E13: テスト計画書自体のレビュー・承認記録がある | F13: 計画書にレビュー実施者・承認者・日付が記録されている | G13: 計画自体の欠陥(スコープ漏れ、非現実的な基準)は下流の全テスト活動を歪めるため、承認記録により関係者合意と説明責任を担保する。 | H13: 実務補完(ISO/IEC/IEEE 29119-3 テスト計画の承認実務) | I13: CORE | J13: 原則適用。案件スコープ・成果物・規制・リスク上非該当の場合はN/A根拠を記録。 | K13: SRC-ISO-GENERAL;SRC-PRACTICE
... A38: TST-901 | B38: 追加承認 | C38: 3. テスト観点・技法選定(TST-201〜) | D38: Medium | E38: 運用プロファイルに基づくテストの要否が判断されている | F38: 利用頻度・重要度の高い操作/機能が運用プロファイル(想定利用分布)として整理され、それに基づくテスト配分または統計的信頼性評価の実施有無と根拠が記録されている | G38: 利用実態と無関係なテスト配分では、ユーザーが毎日使う機能の欠陥が残って体感品質が崩壊する。運用プロファイルは信頼性推定とテスト重点化の両方の基盤になる。 | H38: swebok-v4a.pdf ch05 Software Testing > 3.5 Usage-Based Techniques / 4.1.4-4.1.5 運用プロファイルに基づく信頼性評価と信頼性成長モデル | I38: CORE | J38: 原則適用。案件スコープ・成果物・規制・リスク上非該当の場合はN/A根拠を記録。 | K38: SRC-SWEBOK-V4A
A39: TST-CA01 | B39: クラウド補完 | C39: 3. テスト観点・技法選定(TST-201〜) | D39: Medium | E39: 回復性(レジリエンス)が求められるシステムで、障害注入テスト(カオスエンジニアリング)がテスト技法の候補として検討され、採否と理由、実施時は障害シナリオと合否基準(RTO/RPO)が記録されている | F39: テスト計画に障害注入(依存先停止・遅延・ゾーン障害・リソース枯渇等)の実施有無・対象シナリオ・合否基準が明記されている | G39: フェイルオーバー・自己復旧・縮退運転は障害を実際に注入しない限り検証できず、机上設計のままでは実障害時に機能しない。 | H39: AWS Well-Architected Framework > 信頼性の柱 > REL 12 > REL12-BP04 Test resiliency using chaos engineering / Azure Well-Architected Framework > 信頼性の柱 > RE:08 Test for resiliency and availability scenarios by applying the principles of chaos engineering | I39: CORE | J39: 原則適用。案件スコープ・成果物・規制・リスク上非該当の場合はN/A根拠を記録。 | K39: SRC-AWS-WAF;SRC-AZR-WAF | L39: CONTINUITY-DR
A40: TST-301 | B40: SWEBOK | C40: 4. テストケース設計(TST-301〜) | D40: Critical | E40: 各テストケースに一意の ID がある | F40: 全テストケースに命名規則に従った一意の識別子が付与されている | G40: 一意IDがないと、結果記録・インシデント・トレーサビリティの全てで参照が崩れ、どのテストが未実施かすら集計できなくなる。 | H40: swebok-v4a.pdf ch05 Software Testing > 5.1.4 Test Documentation(テストケース仕様)(実務補完: ISO/IEC/IEEE 29119-3) | I40: CORE | J40: 原則適用。案件スコープ・成果物・規制・リスク上非該当の場合はN/A根拠を記録。 | K40: SRC-SWEBOK-V4A;SRC-ISO-GENERAL;SRC-PRACTICE
A41: TST-302 | B41: SWEBOK | C41: 4. テストケース設計(TST-301〜) | D41: Critical | E41: 期待結果が具体的でオラクルが明確である | F41: 期待結果が具体値・具体状態(表示文言、遷移先、DB 値等)で記述され、「正しく動作すること」等の主観依存の記述がない | G41: テストは結果の合否を判定できて初めて意味を持つ(オラクル問題)。期待結果が曖昧だと実行者の主観で合否が揺れ、欠陥の見逃しと誤検出の両方が起きる。 | H41: swebok-v4a.pdf ch05 Software Testing > 1.2.7 The Oracle Problem | I41: CORE | J41: 原則適用。案件スコープ・成果物・規制・リスク上非該当の場合はN/A根拠を記録。 | K41: SRC-SWEBOK-V4A
A42: TST-303 | B42: SWEBOK | C42: 4. テストケース設計(TST-301〜) | D42: Critical | E42: 要求とテストケースのトレーサビリティがある | F42: 各テストケースが要求 ID または観点 ID と紐付き、逆方向(要求→テストケース)の対応表が存在する | G42: 要求との双方向トレースがないと、テストされていない要求の存在に気づけず、要求カバレッジの主張やアセスメント・認証の証跡も成立しない。 | H42: swebok-v4a.pdf ch05 Software Testing > 1.2.5 Assessment and Certification / 5.1.7 Test Monitoring and Control(要求充足の追跡) | I42: CORE | J42: 原則適用。案件スコープ・成果物・規制・リスク上非該当の場合はN/A根拠を記録。 | K42: SRC-SWEBOK-V4A
A43: TST-304 | B43: SWEBOK | C43: 4. テストケース設計(TST-301〜) | D43: Critical | E43: 異常系・無効入力のテストケースが存在する | F43: 無効同値クラス、エラー処理、例外パスに対するテストケースが正常系と別に存在する | G43: 正常系だけのテストでは、エラー処理・例外パスの欠陥がそのまま残り、本番の異常入力でクラッシュや不正データ受理を起こす。異常系は意図的に設計しないと書かれない。 | H43: swebok-v4a.pdf ch05 Software Testing > 3.1.11 Forcing Exception / 3.1.2 Boundary Value Analysis(ロバストネステスト) | I43: CORE | J43: 原則適用。案件スコープ・成果物・規制・リスク上非該当の場合はN/A根拠を記録。 | K43: SRC-SWEBOK-V4A
A44: TST-305 | B44: SWEBOK | C44: 4. テストケース設計(TST-301〜) | D44: Critical | E44: 事前条件と手順が再現可能に記述されている | F44: 事前条件(データ状態、ログイン状態等)と操作手順が番号付きで記述され、別の実行者が同じ手順を再現できる | G44: テストは科学的な統制実験として他者が再現できる形で文書化すべきであり、再現不能な手順は障害の再現・修正確認を妨げ、担当者交代で実行不能になる。 | H44: swebok-v4a.pdf ch05 Software Testing > 5.2.4 Controlled Experiments and Test Execution | I44: CORE | J44: 原則適用。案件スコープ・成果物・規制・リスク上非該当の場合はN/A根拠を記録。 | K44: SRC-SWEBOK-V4A
A45: TST-306 | B45: SWEBOK | C45: 4. テストケース設計(TST-301〜) | D45: High | E45: 技法の適用結果とテストケースが対応している | F45: 同値クラス表・決定表・状態遷移表等の設計成果物の各項目が、対応するテストケース ID を持つ(導出漏れがない) | G45: 同値表や決定表を作っても、そこからテストケースへの導出が漏れれば技法適用の意味がない。設計成果物とケースIDの対応で導出漏れを機械的に検出可能にする。 | H45: swebok-v4a.pdf ch05 Software Testing > 5.2.2 Test Design and Implementation | I45: CORE | J45: 原則適用。案件スコープ・成果物・規制・リスク上非該当の場合はN/A根拠を記録。 | K45: SRC-SWEBOK-V4A
A46: TST-307 | B46: SWEBOK | C46: 4. テストケース設計(TST-301〜) | D46: High | E46: 優先度が付与されている | F46: 各テストケースにリスク・重要度に基づく優先度(High/Medium/Low 等)が付与されている | G46: 優先度がないと、期間圧縮時にどのテストを削るかを場当たりで決めることになり、高リスク領域の未実施のままのリリースに気づけない。 | H46: swebok-v4a.pdf ch05 Software Testing > 1.2.3 Prioritization/Minimization / 2.2.6 Prioritization Testing | I46: CORE | J46: 原則適用。案件スコープ・成果物・規制・リスク上非該当の場合はN/A根拠を記録。 | K46: SRC-SWEBOK-V4A
A47: TST-308 | B47: SWEBOK | C47: 4. テストケース設計(TST-301〜) | D47: High | E47: テストケース間の依存関係が明示されている | F47: 実行順序に依存があるケースはその旨と先行ケースが明記され、依存のないケースは独立に実行可能である | G47: 暗黙の実行順序依存があると、順序を変えた途端に大量の偽の失敗が発生し、並列実行や部分実行もできなくなる。 | H47: 実務補完(ISO/IEC/IEEE 29119-3 テスト手順仕様の実務) | I47: CORE | J47: 原則適用。案件スコープ・成果物・規制・リスク上非該当の場合はN/A根拠を記録。 | K47: SRC-ISO-GENERAL;SRC-PRACTICE
A48: TST-309 | B48: SWEBOK | C48: 4. テストケース設計(TST-301〜) | D48: High | E48: テストデータが特定されている | F48: 各テストケースで使用するデータ(値、ファイル、アカウント等)が具体的に指定されるか、データ定義への参照がある | G48: テストデータが特定されていないと実行者ごとに異なるデータで実施され、結果の再現も失敗の切り分けもできなくなる。 | H48: swebok-v4a.pdf ch05 Software Testing > 5.1.4 Test Documentation(テストデータ要件) | I48: CORE | J48: 原則適用。案件スコープ・成果物・規制・リスク上非該当の場合はN/A根拠を記録。 | K48: SRC-SWEBOK-V4A
A49: TST-310 | B49: SWEBOK | C49: 4. テストケース設計(TST-301〜) | D49: Medium | E49: 事後条件・後始末が記述されている | F49: データ変更を伴うテストについて、実行後の状態確認または環境復元手順が記述されている | G49: データ変更を伴うテストの後始末がないと、残留データが後続テストの前提を壊し、原因不明の失敗(実は環境汚染)の調査に時間を溶かす。 | H49: 実務補完(ISO/IEC/IEEE 29119-3 テストケース仕様の事後条件) | I49: CORE | J49: 原則適用。案件スコープ・成果物・規制・リスク上非該当の場合はN/A根拠を記録。 | K49: SRC-ISO-GENERAL;SRC-PRACTICE
A50: TST-311 | B50: SWEBOK | C50: 4. テストケース設計(TST-301〜) | D50: Medium | E50: 実行結果の記録欄が定義されている | F50: Pass/Fail/Blocked、実施日、実施者、証跡(スクリーンショット・ログ)への参照を記録する欄が用意されている | G50: 結果記録欄が未整備だと、実施証跡が個人メモに散逸し、完了報告の集計やインシデントの遡及調査ができなくなる。 | H50: swebok-v4a.pdf ch05 Software Testing > 5.1.4 Test Documentation(テスト実行文書・実結果)/ 5.2.5 Test Incident Reporting | I50: CORE | J50: 原則適用。案件スコープ・成果物・規制・リスク上非該当の場合はN/A根拠を記録。 | K50: SRC-SWEBOK-V4A
A51: TST-312 | B51: SWEBOK | C51: 4. テストケース設計(TST-301〜) | D51: Low | E51: テストケースの粒度が均質である | F51: 1ケース1検証目的が原則として守られ、多数の検証を1ケースに詰め込んだものがない | G51: 1ケースに多数の検証を詰め込むと、失敗時にどの検証が落ちたか特定できず、部分的な再実行もできないため、障害解析の効率が大きく落ちる。 | H51: 実務補完(テストケース設計の実務慣行) | I51: CORE | J51: 原則適用。案件スコープ・成果物・規制・リスク上非該当の場合はN/A根拠を記録。 | K51: SRC-PRACTICE
... A76: TST-607 | B76: SWEBOK | C76: 7. テスト実行・インシデント管理(TST-601〜) | D76: Medium | E76: Blocked ケースの障害要因が管理されている | F76: Blocked となったテストの阻害要因(環境障害、先行障害等)と解消見込みが記録されている | G76: Blocked の阻害要因を管理しないと、環境障害や先行欠陥の解消が放置されて未実施ケースが終盤に山積し、スケジュール破綻が突然表面化する。 | H76: swebok-v4a.pdf ch05 Software Testing > 5.1.7 Test Monitoring and Control | I76: CORE | J76: 原則適用。案件スコープ・成果物・規制・リスク上非該当の場合はN/A根拠を記録。 | K76: SRC-SWEBOK-V4A
A77: TST-608 | B77: SWEBOK | C77: 7. テスト実行・インシデント管理(TST-601〜) | D77: Medium | E77: テスト進捗が監視されている | F77: 消化率・合格率・障害発生数の推移が定期的に記録され、計画からの乖離時の対応が確認できる | G77: 進捗と障害発生の推移を監視しないと、計画からの乖離やリスクの高まりに気づくのが手遅れになり、計画見直しの機会を失う。監視データは計画改訂の入力でもある。 | H77: swebok-v4a.pdf ch05 Software Testing > 5.1.6 Test Process Measures / 5.1.7 Test Monitoring and Control | I77: CORE | J77: 原則適用。案件スコープ・成果物・規制・リスク上非該当の場合はN/A根拠を記録。 | K77: SRC-SWEBOK-V4A | L77: OPS-OBSERVABILITY
A78: TST-701 | B78: SWEBOK | C78: 8. テスト測定・網羅性評価(TST-701〜) | D78: Critical | E78: 要求カバレッジが測定されている | F78: 要求(機能・非機能)に対するテストケースの対応率が算出され、未カバー要求がゼロ、または対象外の根拠が記録されている | G78: 要求カバレッジを測らないと、実装されたのに一度も検証されない要求が残り、「テスト完了」の宣言が要求充足の根拠を持たなくなる。 | H78: swebok-v4a.pdf ch05 Software Testing > 4. Test-Related Measures(機能要求カバレッジ)/ 5.1.7 Test Monitoring and Control | I78: CORE | J78: 原則適用。案件スコープ・成果物・規制・リスク上非該当の場合はN/A根拠を記録。 | K78: SRC-SWEBOK-V4A
A79: TST-702 | B79: SWEBOK | C79: 8. テスト測定・網羅性評価(TST-701〜) | D79: High | E79: コードカバレッジが基準と比較されている | F79: 計画で定めた構造網羅基準(文/分岐等)に対する実績値が測定され、未達の場合は追加テストまたは受容の判断が記録されている | G79: 基準だけ定めて実績と比較しなければ網羅基準は形骸化する。未達を放置するか受容するかの判断記録がないと、完了判定の根拠が崩れる。 | H79: swebok-v4a.pdf ch05 Software Testing > 3.2.1 Control Flow Testing / 4. Test-Related Measures | I79: CORE | J79: 原則適用。案件スコープ・成果物・規制・リスク上非該当の場合はN/A根拠を記録。 | K79: SRC-SWEBOK-V4A
A80: TST-703 | B80: SWEBOK | C80: 8. テスト測定・網羅性評価(TST-701〜) | D80: High | E80: カバレッジ未達箇所が分析されている | F80: カバレッジから漏れたコード・仕様について、実行不可能パス/対象外/テスト追加のいずれかの分類と根拠が記録されている | G80: 未達箇所には実行不可能パスも含まれるため、分類せずに数値だけ追うと無駄なテスト追加や、逆に本来テストすべき箇所の見逃しが起きる。 | H80: swebok-v4a.pdf ch05 Software Testing > 1.2.9 The Problem of Infeasible Paths / 4. Test-Related Measures | I80: CORE | J80: 原則適用。案件スコープ・成果物・規制・リスク上非該当の場合はN/A根拠を記録。 | K80: SRC-SWEBOK-V4A
A81: TST-704 | B81: SWEBOK | C81: 8. テスト測定・網羅性評価(TST-701〜) | D81: Medium | E81: 障害の傾向分析が行われている | F81: 検出障害が分類(機能別、原因別、混入工程別等)され、障害密度や収束傾向が品質評価に使われている | G81: 障害を分類・分析しないと、欠陥の多発領域や混入工程が見えず、品質予測もプロセス改善も勘頼みになる。過去の欠陥傾向は次のテスト重点化の最良の入力でもある。 | H81: swebok-v4a.pdf ch05 Software Testing > 4.1.2 Fault Types, Classification and Statistics / 4.1.3 Fault Density | I81: CORE | J81: 原則適用。案件スコープ・成果物・規制・リスク上非該当の場合はN/A根拠を記録。 | K81: SRC-SWEBOK-V4A
A82: TST-705 | B82: SWEBOK | C82: 8. テスト測定・網羅性評価(TST-701〜) | D82: Medium | E82: テストスイート自体の有効性評価が検討されている | F82: 変異テスト・故障注入等によるテスト有効性評価の実施有無が判断され、実施した場合は変異スコア等の結果が記録されている | G82: カバレッジが高くてもアサーションが弱ければ欠陥は素通りする。変異テスト・故障注入はテストスイート自体の欠陥検出力を測る手段であり、検討すらしないと検出力の過信が残る。 | H82: swebok-v4a.pdf ch05 Software Testing > 4.2 Evaluation of the Tests Performed(4.2.1 Fault Injection / 4.2.2 Mutation Score)/ 3.4 Fault-Based and Mutation Techniques | I82: CORE | J82: 原則適用。案件スコープ・成果物・規制・リスク上非該当の場合はN/A根拠を記録。 | K82: SRC-SWEBOK-V4A
A83: TST-706 | B83: SWEBOK | C83: 8. テスト測定・網羅性評価(TST-701〜) | D83: Low | E83: カバレッジの限界が報告に明記されている | F83: 報告書に「カバレッジ達成は欠陥不在の証明ではない」旨、または残存リスクとしての言及がある | G83: 「テストはバグの存在は示せるが不在は示せない」(Dijkstra)という理論的限界を報告で明示しないと、カバレッジ達成が品質保証の完了だと経営層が誤解し、残存リスクへの備えを怠る。 | H83: swebok-v4a.pdf ch05 Software Testing > 1.2.8 Theoretical and Practical Limitations | I83: CORE | J83: 原則適用。案件スコープ・成果物・規制・リスク上非該当の場合はN/A根拠を記録。 | K83: SRC-SWEBOK-V4A
A84: TST-801 | B84: SWEBOK | C84: 9. テスト結果報告・完了判定(TST-801〜) | D84: Critical | E84: 終了基準に対する達成状況が報告されている | F84: 計画書の終了基準の各項目について達成/未達成が個別に判定され、根拠データが示されている | G84: 終了基準への達成状況を項目別に判定しないと、「概ね完了」という曖昧な総括で未達が隠れ、テスト完了の判断が計画と切り離された恣意的なものになる。 | H84: swebok-v4a.pdf ch05 Software Testing > 5.1.8 Test Completion | I84: CORE | J84: 原則適用。案件スコープ・成果物・規制・リスク上非該当の場合はN/A根拠を記録。 | K84: SRC-SWEBOK-V4A
A85: TST-802 | B85: SWEBOK | C85: 9. テスト結果報告・完了判定(TST-801〜) | D85: Critical | E85: 残存障害と残存リスクが明記されている | F85: 未解決インシデントの一覧(重要度付き)と、未実施・未達成に起因する残存リスクが報告書に記載されている | G85: 残存障害と残存リスクを明示しないと、リリース判断者がリスクを知らずに判断することになり、本番障害発生時に「知らされていなかった」という組織的問題に発展する。 | H85: swebok-v4a.pdf ch05 Software Testing > 5.1.8 Test Completion(残存フェイラのコストとリスクの考慮) | I85: CORE | J85: 原則適用。案件スコープ・成果物・規制・リスク上非該当の場合はN/A根拠を記録。 | K85: SRC-SWEBOK-V4A
A86: TST-803 | B86: SWEBOK | C86: 9. テスト結果報告・完了判定(TST-801〜) | D86: Critical | E86: 未達成項目の受容判断が承認されている | F86: 終了基準未達・残存障害ありのままリリースする場合、受容の判断者・日付・根拠が記録されている | G86: 未達のままのリリースは残存リスクの受容判断であり、判断者・根拠の記録がないと責任の所在が曖昧なままリスクだけが引き継がれる。 | H86: swebok-v4a.pdf ch05 Software Testing > 5.1.8 Test Completion(実務補完: リスク受容の承認記録) | I86: CORE | J86: 原則適用。案件スコープ・成果物・規制・リスク上非該当の場合はN/A根拠を記録。 | K86: SRC-SWEBOK-V4A;SRC-PRACTICE
A87: TST-804 | B87: SWEBOK | C87: 9. テスト結果報告・完了判定(TST-801〜) | D87: High | E87: 実施統計が正確に集計されている | F87: 計画/実施/合格/不合格/Blocked の件数がテストケースの実行記録と一致している(抜き取り確認で矛盾がない) | G87: 報告書の統計が実行記録と食い違っていると、報告全体の信頼性が崩れ、それに基づくリリース判断も誤る。集計の正確性は完了報告の最低条件。 | H87: swebok-v4a.pdf ch05 Software Testing > 5.1.6 Test Process Measures(実施・合格・不合格件数の測定) | I87: CORE | J87: 原則適用。案件スコープ・成果物・規制・リスク上非該当の場合はN/A根拠を記録。 | K87: SRC-SWEBOK-V4A
A88: TST-805 | B88: SWEBOK | C88: 9. テスト結果報告・完了判定(TST-801〜) | D88: High | E88: 対象バージョンと環境が特定されている | F88: 報告対象の SUT のバージョン(コミット/タグ)とテスト環境が一意に特定できる | G88: SUTのバージョンと環境が特定できない結果は、その後の変更でどこまで有効か判断できず、障害調査時に「どの版で確認済みか」を辿れない。 | H88: swebok-v4a.pdf ch05 Software Testing > 5.2.4 Controlled Experiments and Test Execution(明確に定義された版のSUT)/ 5.2.5 Test Incident Reporting | I88: CORE | J88: 原則適用。案件スコープ・成果物・規制・リスク上非該当の場合はN/A根拠を記録。 | K88: SRC-SWEBOK-V4A
A89: TST-806 | B89: SWEBOK | C89: 9. テスト結果報告・完了判定(TST-801〜) | D89: Medium | E89: リリース可否の推奨が根拠付きで記述されている | F89: 総合判定(可/条件付き可/不可)とその根拠(基準達成状況、残存リスク評価)が2文以上で記述されている | G89: データの羅列だけでは判断は読み手任せになる。根拠付きの推奨がないと、テスト結果がリリース判断に反映されず報告が形式化する。 | H89: swebok-v4a.pdf ch05 Software Testing > 5.1.8 Test Completion(結果のステークホルダーへの伝達) | I89: CORE | J89: 原則適用。案件スコープ・成果物・規制・リスク上非該当の場合はN/A根拠を記録。 | K89: SRC-SWEBOK-V4A
... A91: TST-808 | B91: SWEBOK | C91: 9. テスト結果報告・完了判定(TST-801〜) | D91: Low | E91: テスト資産の引き継ぎが記述されている | F91: 保守フェーズで再利用するテストケース・自動テストの保管場所と保守方針が記述されている | G91: テスト資産の保管場所と保守方針を引き継がないと、保守フェーズで回帰テストをゼロから作り直すことになり、再利用によるコスト削減効果を失う。 | H91: swebok-v4a.pdf ch05 Software Testing > 5.1.9 Test Reusability | I91: CORE | J91: 原則適用。案件スコープ・成果物・規制・リスク上非該当の場合はN/A根拠を記録。 | K91: SRC-SWEBOK-V4A

Sheet 06_運用
A1: ID | B1: 区分 | C1: カテゴリ | D1: 基準重要度 | E1: チェック項目 | F1: 合格基準 | G1: 意図(なぜ確認するか) | H1: 対象ドキュメント(参照箇所) | I1: 適用プロファイル | J1: 適用条件 | K1: 出典ID | L1: 重複統制グループ | M1: 案件重要度 | N1: 適用判定 | O1: 判定 | P1: 証跡・参照箇所 | Q1: 指摘・Issue ID | R1: 対応方針 | S1: 例外・リスク受容承認者 | T1: 是正期限 | U1: レビュアー | V1: レビュー日 | W1: 再確認結果
A2: OPS-001 | B2: SWEBOK | C2: 1. 運用計画・体制(SWEBOK 6-2.1) | D2: Critical | E2: 運用体制のロールと責任が定義されている | F2: 運用エンジニア・オンコール・管理者等のロールごとに担当業務と責任範囲が表形式等で明記されている | G2: 役割の空白や重複があると、障害時に「誰も自分の担当と思っていない」作業が放置され、復旧遅延や対応漏れが起きる。運用移管後に責任の押し付け合いが発生する事態を防ぐ。 | H2: swebok-v4a.pdf ch06 SE Operations > 2.1.1 Operations Plan(roles and responsibilities)/ 1.1 Definition of Software Engineering Operations | I2: CORE | J2: 原則適用。案件スコープ・成果物・規制・リスク上非該当の場合はN/A根拠を記録。 | K2: SRC-SWEBOK-V4A
A3: OPS-002 | B3: SWEBOK | C3: 1. 運用計画・体制(SWEBOK 6-2.1) | D3: Critical | E3: エスカレーション経路に空白がない | F3: 一次対応→二次対応→管理者/ベンダーの各段階に具体的な連絡先(チーム名・連絡手段)が記載され、「未定」「TBD」が残っていない | G3: エスカレーション先が「TBD」のまま本番稼働すると、深夜の重大障害で連絡先を探すことに時間を浪費し、復旧が数時間単位で遅れる。経路の空白を稼働前に潰すためにチェックする。 | H3: swebok-v4a.pdf ch06 SE Operations > 2.1.1 Operations Plan(communication to the relevant parties)/ 4.1 Incident Management(escalation) | I3: CORE | J3: 原則適用。案件スコープ・成果物・規制・リスク上非該当の場合はN/A根拠を記録。 | K3: SRC-SWEBOK-V4A
A4: OPS-003 | B4: SWEBOK | C4: 1. 運用計画・体制(SWEBOK 6-2.1) | D4: High | E4: オンコール体制(当番・交代・時間帯)が定義されている | F4: 対応時間帯(24/365、営業時間内等)と当番の割り当て・交代ルールが記載されている | G4: 当番・交代ルールが曖昧だと夜間・休日の障害が翌営業日まで放置されたり、特定個人に負荷が集中して疲弊・離職を招く。対応時間帯の期待値を関係者間で揃える。 | H4: swebok-v4a.pdf ch06 SE Operations > 2.1.1 Operations Plan(staffing and recruitment requirements) | I4: CORE | J4: 原則適用。案件スコープ・成果物・規制・リスク上非該当の場合はN/A根拠を記録。 | K4: SRC-SWEBOK-V4A
A5: OPS-004 | B5: SWEBOK | C5: 1. 運用計画・体制(SWEBOK 6-2.1) | D5: High | E5: サービス受入基準が定義されている | F5: 運用移管時に満たすべき条件(文書整備、監視稼働、訓練実施等)がチェック可能な項目として列挙されている | G5: 受入基準がないと、文書未整備・監視未稼働のまま運用チームへ移管され、運用開始直後から障害対応が属人化・混乱する。移管時のゲートとして機能させる。 | H5: swebok-v4a.pdf ch06 SE Operations > 2.1.1 Operations Plan(service acceptance criteria) | I5: CORE | J5: 原則適用。案件スコープ・成果物・規制・リスク上非該当の場合はN/A根拠を記録。 | K5: SRC-SWEBOK-V4A
A6: OPS-005 | B6: SWEBOK | C6: 1. 運用計画・体制(SWEBOK 6-2.1) | D6: Medium | E6: 要員の教育・引き継ぎ計画がある | F6: 新任者への教育項目・引き継ぎ手順、または必要スキルの定義が記載されている | G6: 教育・引き継ぎ計画がないと、担当者の退職・異動でノウハウが消失し、単純な障害でも復旧できないチームになる。ISO 20000-1 が求める要員育成・後継計画の観点を担保する。 | H6: swebok-v4a.pdf ch06 SE Operations > 1.1 Definition of Software Engineering Operations(resource training and development / succession planning) | I6: CORE | J6: 原則適用。案件スコープ・成果物・規制・リスク上非該当の場合はN/A根拠を記録。 | K6: SRC-SWEBOK-V4A
A7: OPS-006 | B7: SWEBOK | C7: 1. 運用計画・体制(SWEBOK 6-2.1) | D7: Medium | E7: 定常運用作業の一覧がある | F7: 日次・週次・月次等の定常作業が、頻度・担当・手順参照付きで一覧化されている | G7: 定常作業が一覧化されていないと、証明書更新やログローテーション等の定期作業が漏れて突発障害化する。作業の頻度・担当を可視化し実施漏れを防ぐ。 | H7: swebok-v4a.pdf ch06 SE Operations > 2. Software Engineering Operations Planning(procedures / process control records) | I7: CORE | J7: 原則適用。案件スコープ・成果物・規制・リスク上非該当の場合はN/A根拠を記録。 | K7: SRC-SWEBOK-V4A
A8: OPS-007 | B8: SWEBOK | C8: 1. 運用計画・体制(SWEBOK 6-2.1) | D8: Medium | E8: メンテナンスウィンドウが定義されている | F8: 計画停止の可否・時間帯・事前告知ルールが記載されている | G8: 計画停止のルールがないと、告知なしのメンテナンスでユーザークレームや SLA 違反紛争が発生する。停止可否と告知ルールを事前合意しておく。 | H8: swebok-v4a.pdf ch06 SE Operations > 2.3 Software Availability, Continuity, and Service Levels | I8: CORE | J8: 原則適用。案件スコープ・成果物・規制・リスク上非該当の場合はN/A根拠を記録。 | K8: SRC-SWEBOK-V4A
A9: OPS-901 | B9: 追加承認 | C9: 1. 運用計画・体制(SWEBOK 6-2.1) | D9: Medium | E9: 運用コストの見積もりと予算計画がある | F9: インフラ費用・ライセンス・要員等の運用コストの見積もりと、予算枠・期間(年度等)・増強時の費用対応が記載されている | G9: 運用フェーズは開発より長期に及ぶため、コスト計画がないとクラウド費用の想定外増大や容量増強の予算未確保でサービス継続が脅かされる。運用開始後の「予算がなくて増強できない」事態を防ぐ。 | H9: swebok-v4a.pdf ch06 SE Operations > 2.1.1 Operations Plan — 運用の財務管理・予算・コスト見積もり(financial management, budgets and timescales, estimate of operations and maintenance costs) | I9: CORE | J9: 原則適用。案件スコープ・成果物・規制・リスク上非該当の場合はN/A根拠を記録。 | K9: SRC-SWEBOK-V4A | L9: COST
A10: OPS-010 | B10: SWEBOK | C10: 2. サプライヤ管理(SWEBOK 6-2.1.2) | D10: High | E10: 依存するサプライヤ(クラウド・外部委託先)が一覧化されている | F10: IaaS/PaaS・SaaS・委託先ごとに提供サービスと契約範囲が列挙されている | G10: 依存サプライヤの全体像が見えていないと、外部サービスの障害・仕様変更・値上げが自サービスに与える影響を評価できず、初動が遅れる。依存関係の棚卸しを強制する。 | H10: swebok-v4a.pdf ch06 SE Operations > 2.1.2 Supplier Management | I10: CORE | J10: 原則適用。案件スコープ・成果物・規制・リスク上非該当の場合はN/A根拠を記録。 | K10: SRC-SWEBOK-V4A
A11: OPS-011 | B11: SWEBOK | C11: 2. サプライヤ管理(SWEBOK 6-2.1.2) | D11: Critical | E11: 責任分界点が明確である | F11: 自組織とサプライヤの責任範囲(例: クラウドの責任共有モデル)が成果物・レイヤーごとに記載されている | G11: 責任分界が曖昧だと、障害時に「クラウド側の問題」と誤認して自組織側の対処が遅れたり、逆にクラウド側の責任範囲を自前で二重管理して無駄が生じる。責任共有モデルの明文化で押し付け合いを防ぐ。 | H11: swebok-v4a.pdf ch06 SE Operations > 2.1.2 Supplier Management(managing out-sourced services and cloud services like IaaS and PaaS) | I11: CORE | J11: 原則適用。案件スコープ・成果物・規制・リスク上非該当の場合はN/A根拠を記録。 | K11: SRC-SWEBOK-V4A
A12: OPS-012 | B12: SWEBOK | C12: 2. サプライヤ管理(SWEBOK 6-2.1.2) | D12: High | E12: サプライヤ障害時の連絡経路とサポート契約が記載されている | F12: 各サプライヤのサポート窓口・サポートレベル(対応時間)・チケット起票方法が記載されている | G12: サプライヤ障害の際にサポート窓口・チケット起票方法を知らないと、契約上受けられるはずの支援を受けられず復旧が遅延する。障害当日に契約書を探す事態を防ぐ。 | H12: swebok-v4a.pdf ch06 SE Operations > 2.1.2 Supplier Management | I12: CORE | J12: 原則適用。案件スコープ・成果物・規制・リスク上非該当の場合はN/A根拠を記録。 | K12: SRC-SWEBOK-V4A
A13: OPS-013 | B13: SWEBOK | C13: 2. サプライヤ管理(SWEBOK 6-2.1.2) | D13: Medium | E13: サプライヤの SLA と自サービスの SLO の整合が確認されている | F13: 依存サービスの SLA(可用性等)が自サービスの SLO 達成に十分であることの検討記録がある | G13: 依存先の SLA が自サービスの SLO より緩いと、構造的に SLO を達成できない設計になる。この不整合を稼働前に検出し、冗長化や SLO 見直しの判断につなげる。 | H13: swebok-v4a.pdf ch06 SE Operations > 2.1.2 Supplier Management / 2.3 Software Availability, Continuity, and Service Levels | I13: CORE | J13: 原則適用。案件スコープ・成果物・規制・リスク上非該当の場合はN/A根拠を記録。 | K13: SRC-SWEBOK-V4A
A14: OPS-020 | B14: SWEBOK | C14: 3. 環境管理・IaC(SWEBOK 6-2.2) | D14: Critical | E14: 環境一覧(開発/テスト/プレプロダクション/本番)と用途が定義されている | F14: 各環境の用途・アクセス可能者・データの種別(本番データ可否)が記載されている | G14: 環境の用途・アクセス権・データ種別が未定義だと、テスト環境に本番個人データが流出したり、検証不十分なまま本番投入される事故が起きる。環境ごとの統制の前提を固める。 | H14: swebok-v4a.pdf ch06 SE Operations > 2.2 Development and Operational Environments | I14: CORE | J14: 原則適用。案件スコープ・成果物・規制・リスク上非該当の場合はN/A根拠を記録。 | K14: SRC-SWEBOK-V4A | L14: OPS-IAC
A15: OPS-021 | B15: SWEBOK | C15: 3. 環境管理・IaC(SWEBOK 6-2.2) | D15: High | E15: 本番と非本番環境の構成差分が明記されている | F15: スペック・冗長構成・外部接続等の差分が一覧化されているか、「差分なし」と明記されている | G15: 本番と非本番の差分が不明だと「テストでは動いたのに本番で落ちる」障害が繰り返される。SWEBOK が求める環境間の一貫性・同期を差分の可視化によって担保する。 | H15: swebok-v4a.pdf ch06 SE Operations > 2.2 Development and Operational Environments(environments coherent and synchronized with production) | I15: CORE | J15: 原則適用。案件スコープ・成果物・規制・リスク上非該当の場合はN/A根拠を記録。 | K15: SRC-SWEBOK-V4A | L15: OPS-IAC
A16: OPS-022 | B16: SWEBOK | C16: 3. 環境管理・IaC(SWEBOK 6-2.2) | D16: High | E16: 環境が IaC で再現可能、または手作業範囲が明示されている | F16: IaC リポジトリの参照があるか、手作業で構築する部分の範囲と理由が記載されている | G16: 環境構築が手作業・暗黙知だと、災害復旧や環境増設のたびに構成差異(スノーフレーク)が生まれ、再現不能な障害の温床になる。IaC による単一ソースからの再現性を確認する。 | H16: swebok-v4a.pdf ch06 SE Operations > 2.2 Development and Operational Environments(IaC / single source of truth) | I16: CORE | J16: 原則適用。案件スコープ・成果物・規制・リスク上非該当の場合はN/A根拠を記録。 | K16: SRC-SWEBOK-V4A | L16: OPS-IAC
A17: OPS-023 | B17: SWEBOK | C17: 3. 環境管理・IaC(SWEBOK 6-2.2) | D17: Critical | E17: 本番環境へのアクセス制御が定義されている | F17: 本番へのログイン・変更操作の権限者、認証方式、承認フローが記載されている | G17: 本番アクセス制御が緩いと、誤操作による本番破壊や内部不正・情報漏えいが起き、原因追跡もできない。権限者・認証・承認フローを事前に定めて事故と監査指摘を防ぐ。 | H17: swebok-v4a.pdf ch06 SE Operations > 2.6 Software and Data Safety, Security, Integrity, Protection, and Controls | I17: CORE | J17: 原則適用。案件スコープ・成果物・規制・リスク上非該当の場合はN/A根拠を記録。 | K17: SRC-SWEBOK-V4A | L17: OPS-IAC
A18: OPS-024 | B18: SWEBOK | C18: 3. 環境管理・IaC(SWEBOK 6-2.2) | D18: Medium | E18: 構成情報(パラメータ・シークレット)の管理方法が定義されている | F18: 設定値の管理場所と、シークレットが平文でリポジトリ・文書に置かれない旨の方式が記載されている | G18: シークレットが平文でリポジトリや文書に置かれると、漏えい時に全環境の認証情報の一斉ローテーションを迫られる重大事故になる。設定値の管理場所を一元化し漏えいリスクを下げる。 | H18: swebok-v4a.pdf ch06 SE Operations > 2.2 Development and Operational Environments / 2.6(protection and controls) | I18: CORE | J18: 原則適用。案件スコープ・成果物・規制・リスク上非該当の場合はN/A根拠を記録。 | K18: SRC-SWEBOK-V4A | L18: OPS-IAC
A19: OPS-025 | B19: SWEBOK | C19: 3. 環境管理・IaC(SWEBOK 6-2.2) | D19: Medium | E19: 環境の払い出し・破棄の手順または自動化がある | F19: 新環境の作成・不要環境の削除の手順か、セルフサービス化されたパイプラインの記載がある | G19: 環境の払い出し・破棄の仕組みがないと、検証のたびに環境待ちで開発が停滞したり、放置環境がコストとセキュリティホールになる。環境オンデマンド化(サービスとしての環境提供)の観点を確認する。 | H19: swebok-v4a.pdf ch06 SE Operations > 1.1 Definition(environment on demand)/ 2.2 Development and Operational Environments | I19: CORE | J19: 原則適用。案件スコープ・成果物・規制・リスク上非該当の場合はN/A根拠を記録。 | K19: SRC-SWEBOK-V4A | L19: OPS-IAC
A20: OPS-030 | B20: SWEBOK | C20: 4. サービスレベル(SLO/SLI/SLA)(SWEBOK 6-2.3) | D20: Critical | E20: SLI が定義され、計測方法が明記されている | F20: 各 SLI に定義式(分子/分母)・データソース・計測ポイントが記載され、第三者が同じ値を再現計算できる | G20: SLI の定義式・データソースが曖昧だと、関係者ごとに違う数値を見て「達成/未達」の水掛け論になる。第三者が再現計算できる定義にすることで、サービスレベル管理の土台を作る。 | H20: swebok-v4a.pdf ch06 SE Operations > 2.3 Software Availability, Continuity, and Service Levels(service-level management) | I20: CORE | J20: 原則適用。案件スコープ・成果物・規制・リスク上非該当の場合はN/A根拠を記録。 | K20: SRC-SWEBOK-V4A
A21: OPS-031 | B21: SWEBOK | C21: 4. サービスレベル(SLO/SLI/SLA)(SWEBOK 6-2.3) | D21: Critical | E21: SLO に目標値と計測期間が設定されている | F21: 各 SLO に数値目標(例: 99.9%)と期間(例: 直近30日ローリング)が記載されている | G21: 目標値と計測期間がないと、可用性が徐々に劣化しても「問題」と認識されず、信頼性投資の判断ができない。数値目標と期間の合意が改善サイクルの起点になる。 | H21: swebok-v4a.pdf ch06 SE Operations > 2.3 Software Availability, Continuity, and Service Levels(service-level targets) | I21: CORE | J21: 原則適用。案件スコープ・成果物・規制・リスク上非該当の場合はN/A根拠を記録。 | K21: SRC-SWEBOK-V4A
A22: OPS-032 | B22: SWEBOK | C22: 4. サービスレベル(SLO/SLI/SLA)(SWEBOK 6-2.3) | D22: High | E22: SLI がユーザー体験を代表している | F22: 可用性・レイテンシ・エラー率等がユーザー接点(リクエスト成否等)で定義され、サーバー死活のみに依存していない | G22: サーバー死活だけを SLI にすると、ユーザーには使えないのに「全系正常」と表示される監視盲点が生まれる。ユーザー体験ベースの指標にすることで「動いているのに使えない」障害の見逃しを防ぐ。 | H22: swebok-v4a.pdf ch06 SE Operations > 2.3 Software Availability, Continuity, and Service Levels + 実務補完(Google SRE) | I22: CORE | J22: 原則適用。案件スコープ・成果物・規制・リスク上非該当の場合はN/A根拠を記録。 | K22: SRC-SWEBOK-V4A;SRC-GCP-AIML;SRC-SRE;SRC-PRACTICE
A23: OPS-033 | B23: SWEBOK | C23: 4. サービスレベル(SLO/SLI/SLA)(SWEBOK 6-2.3) | D23: High | E23: SLO の除外条件が定義されている | F23: 計画メンテナンス・不可抗力等の除外条件の有無が明記されている(除外なしの場合はその旨) | G23: 除外条件が未定義だと、計画メンテナンス後に SLO 未達の扱いをめぐって顧客・経営と紛争になる。計測ルールの解釈揺れを事前に排除する。 | H23: swebok-v4a.pdf ch06 SE Operations > 2.3 Software Availability, Continuity, and Service Levels(SLAs clarify obligations) | I23: CORE | J23: 原則適用。案件スコープ・成果物・規制・リスク上非該当の場合はN/A根拠を記録。 | K23: SRC-SWEBOK-V4A
A24: OPS-034 | B24: SWEBOK | C24: 4. サービスレベル(SLO/SLI/SLA)(SWEBOK 6-2.3) | D24: High | E24: エラーバジェット消費時のアクションが決まっている | F24: バジェット枯渇・超過時の対応(リリース凍結、信頼性作業の優先等)と判断者が記載されている | G24: エラーバジェット枯渇時のルールがないと、信頼性が悪化していても機能リリースが止まらず、SLO が形骸化する。リリース凍結等の強制力ある対応をあらかじめ合意しておく。 | H24: 実務補完(Google SRE: エラーバジェットポリシー)。SWEBOK 2.3 の SLO 管理を実効化する項目 | I24: CORE | J24: 原則適用。案件スコープ・成果物・規制・リスク上非該当の場合はN/A根拠を記録。 | K24: SRC-GCP-WAF;SRC-SRE;SRC-PRACTICE
A25: OPS-035 | B25: SWEBOK | C25: 4. サービスレベル(SLO/SLI/SLA)(SWEBOK 6-2.3) | D25: Medium | E25: SLA と SLO の関係が整理されている | F25: 対外 SLA がある場合、SLO が SLA より厳しい値に設定されているか、対応関係が記載されている | G25: SLO が対外 SLA と同値以下だと、内部で異常に気付いた時点で既に契約違反(違約金)が確定している。SLO を SLA より厳しく設定し、対外約束の手前で検知・対処できる余裕を確保する。 | H25: swebok-v4a.pdf ch06 SE Operations > 2.3 Software Availability, Continuity, and Service Levels(SLA) | I25: CORE | J25: 原則適用。案件スコープ・成果物・規制・リスク上非該当の場合はN/A根拠を記録。 | K25: SRC-SWEBOK-V4A
A26: OPS-036 | B26: SWEBOK | C26: 4. サービスレベル(SLO/SLI/SLA)(SWEBOK 6-2.3) | D26: Medium | E26: SLO の見直し周期と承認者が定義されている | F26: 見直し頻度(例: 四半期ごと)と承認者・合意プロセスが記載されている | G26: SLO を一度決めたきり放置すると、ビジネス要求や実力値と乖離して達成不能または緩すぎる目標になり、誰も参照しなくなる。見直し周期と承認者を決めて生きた指標に保つ。 | H26: swebok-v4a.pdf ch06 SE Operations > 2.3(service-level management process monitors agreed service levels)/ 4.5 Service Reporting | I26: CORE | J26: 原則適用。案件スコープ・成果物・規制・リスク上非該当の場合はN/A根拠を記録。 | K26: SRC-SWEBOK-V4A
A27: OPS-037 | B27: SWEBOK | C27: 4. サービスレベル(SLO/SLI/SLA)(SWEBOK 6-2.3) | D27: Low | E27: サポート時間・問い合わせ窓口が定義されている | F27: ユーザーからの問い合わせ受付時間・チャネル・応答目標が記載されている | G27: 問い合わせ窓口・受付時間が未定義だと、ユーザーが障害を報告できず検知が遅れたり、運用チームが無制限のサポート要求を負うことになる。CONOPS が求める「利用者が問題を報告する方法」を確認する。 | H27: swebok-v4a.pdf ch06 SE Operations > 2.1.1 Operations Plan(CONOPS: how users report problems)/ 4.4 Operations Support | I27: CORE | J27: 原則適用。案件スコープ・成果物・規制・リスク上非該当の場合はN/A根拠を記録。 | K27: SRC-SWEBOK-V4A
A28: OPS-040 | B28: SWEBOK | C28: 5. 容量・性能管理(SWEBOK 6-1.6 / 6-2.4) | D28: High | E28: 現状のリソース使用状況と上限が把握されている | F28: CPU・メモリ・ストレージ・接続数等の現在値と上限(またはその計測手段)が記載されている | G28: 現在のリソース使用量と上限を把握していないと、ディスク枯渇や接続数上限到達という「予見可能な障害」を突発障害として食らう。容量管理の出発点となる現状把握を確認する。 | H28: swebok-v4a.pdf ch06 SE Operations > 2.4 Software Capacity Management(data on resource utilization captured and analyzed) | I28: CORE | J28: 原則適用。案件スコープ・成果物・規制・リスク上非該当の場合はN/A根拠を記録。 | K28: SRC-SWEBOK-V4A
A29: OPS-041 | B29: SWEBOK | C29: 5. 容量・性能管理(SWEBOK 6-1.6 / 6-2.4) | D29: High | E29: 需要予測に基づく容量計画がある | F29: 利用者数・データ量等の増加見込みと、それに対する増強計画・時期が記載されている | G29: 需要予測なしの運用は、キャンペーンや利用者増でキャパシティ超過に陥り、緊急増強(高コスト・高リスク)を強いられる。事業予測を容量要件に翻訳しておくことで計画的な増強を可能にする。 | H29: swebok-v4a.pdf ch06 SE Operations > 2.4 Software Capacity Management(business predictions and workload estimates translated into requirements) | I29: CORE | J29: 原則適用。案件スコープ・成果物・規制・リスク上非該当の場合はN/A根拠を記録。 | K29: SRC-SWEBOK-V4A
A30: OPS-042 | B30: SWEBOK | C30: 5. 容量・性能管理(SWEBOK 6-1.6 / 6-2.4) | D30: High | E30: スケール方式が定義されている | F30: 垂直/水平スケールの方式、自動スケールの条件(トリガー・上限)または手動増強の手順が記載されている | G30: スケール方式が未定義だと、負荷急増時にその場しのぎの構成変更で二次障害を起こす。自動スケールの条件と上限(暴走時のコスト歯止め)まで決めておく。 | H30: swebok-v4a.pdf ch06 SE Operations > 1.6 Performance, Reliability and Load Balancing(adjust dynamically according to demand)/ 2.4 | I30: CORE | J30: 原則適用。案件スコープ・成果物・規制・リスク上非該当の場合はN/A根拠を記録。 | K30: SRC-SWEBOK-V4A
A31: OPS-043 | B31: SWEBOK | C31: 5. 容量・性能管理(SWEBOK 6-1.6 / 6-2.4) | D31: Medium | E31: 容量計画の見直し周期が定義されている | F31: 年1回以上の見直し頻度と実施契機(定期・イベント時)が記載されている | G31: 容量計画は作成時点から陳腐化するため、見直し契機がないと予測と実態が乖離したまま運用される。SWEBOK/ISO 20000-1 が求める「少なくとも年1回」の更新を担保する。 | H31: swebok-v4a.pdf ch06 SE Operations > 2.4 Software Capacity Management(capacity plan produced at suitable frequency, at least annually) | I31: CORE | J31: 原則適用。案件スコープ・成果物・規制・リスク上非該当の場合はN/A根拠を記録。 | K31: SRC-SWEBOK-V4A
A32: OPS-044 | B32: SWEBOK | C32: 5. 容量・性能管理(SWEBOK 6-1.6 / 6-2.4) | D32: Medium | E32: 性能要件(レイテンシ・スループット)と負荷分散方式が記載されている | F32: 性能目標値と、負荷分散の構成(方式・ヘルスチェック)が記載されている | G32: 性能目標と負荷分散構成が文書化されていないと、性能劣化時に「何が正常か」の基準がなく対応判断ができない。またヘルスチェック不備は障害ノードへの振り分け継続を招く。 | H32: swebok-v4a.pdf ch06 SE Operations > 1.6 Performance, Reliability and Load Balancing | I32: CORE | J32: 原則適用。案件スコープ・成果物・規制・リスク上非該当の場合はN/A根拠を記録。 | K32: SRC-SWEBOK-V4A
A33: OPS-045 | B33: SWEBOK | C33: 5. 容量・性能管理(SWEBOK 6-1.6 / 6-2.4) | D33: Medium | E33: 容量逼迫の予兆を検知するアラートがある | F33: ストレージ・接続数等の使用率に対する警告閾値(枯渇前に対応可能な水準)が監視設計に含まれる | G33: 使用率アラートがないと、容量逼迫は「満杯になった瞬間」の障害として顕在化する。枯渇前に対応時間を確保できる閾値を設定し、予防保全を可能にする。 | H33: swebok-v4a.pdf ch06 SE Operations > 2.4 Software Capacity Management / 5.1 Incident and Problem Prevention | I33: CORE | J33: 原則適用。案件スコープ・成果物・規制・リスク上非該当の場合はN/A根拠を記録。 | K33: SRC-SWEBOK-V4A | L33: OPS-OBSERVABILITY
A34: OPS-CA01 | B34: クラウド補完 | C34: 5. 容量・性能管理(SWEBOK 6-1.6 / 6-2.4) | D34: High | E34: 利用する外部サービス・プラットフォームの上限値(クォータ・サービス制限・APIレート制限・ライセンス数等)が棚卸しされ、使用量の監視と、フェイルオーバー/ピーク時の必要量を織り込んだ事前引き上げのプロセスがある | F34: 運用設計書に依存サービスの上限一覧と現在使用率・監視方法(閾値アラート)・引き上げ手順が記載され、DR/ピーク時所要量を加味した事前確保の記録がある | G34: 上限到達はスケール失敗やスロットリング、災害復旧の失敗として最悪のタイミングで突然顕在化し、容量計画だけでは防げない。 | H34: AWS Well-Architected Framework > 信頼性の柱 > REL 1 > REL01-BP04 Monitor and manage quotas / REL01-BP06 / Well-Architected Framework for OCI > Reliability and Resilience > Manage Your Service Limits > Monitor and Manage Your Service Limits / Factor Failover Usage in Your Service Limits | I34: CORE | J34: 原則適用。案件スコープ・成果物・規制・リスク上非該当の場合はN/A根拠を記録。 | K34: SRC-AWS-WAF;SRC-OCI-WAF | L34: RELIABILITY-HA;OPS-OBSERVABILITY
A35: OPS-CG02 | B35: クラウド補完 | C35: 5. 容量・性能管理(SWEBOK 6-1.6 / 6-2.4) | D35: Medium | E35: 過負荷・部分障害時のスロットリング・負荷制限(load shedding)および縮退モード(グレースフルデグラデーション)の方針・発動条件・運用手順が定義されている | F35: 処理能力超過時のリクエスト制御方針(レート制限、過剰リクエストの早期拒否、優先度付け)と、縮退モードの発動判断基準・切替手順・ユーザー告知手順が運用設計書/Runbookに記載されている | G35: 過負荷・部分障害時の制御方針がないと、突発的なトラフィックが連鎖停止に発展し、部分障害を全面停止として扱うことになる。 | H35: Google Cloud Well-Architected Framework > 信頼性 > Design for graceful degradation > Implement throttling / Drop excess requests early / Azure Well-Architected Framework > 信頼性の柱 > RE:07 (Self-healing and self-preservation > Implement a graceful degradation mode) | I35: CORE | J35: 原則適用。案件スコープ・成果物・規制・リスク上非該当の場合はN/A根拠を記録。 | K35: SRC-GCP-WAF;SRC-AZR-WAF
A36: OPS-050 | B36: SWEBOK | C36: 6. バックアップ・災害復旧・フェイルオーバー(SWEBOK 6-2.5) | D36: Critical | E36: RTO/RPO が数値で定義されている | F36: 目標復旧時間(RTO)と目標復旧時点(RPO)が数値で記載され、業務要求との対応が示されている | G36: RTO/RPO が未定義だと、バックアップ頻度や DR 構成の妥当性を判断する基準がなく、被災後に「そんなに失われるとは思わなかった」という業務側との認識齟齬が露呈する。復旧目標を業務要求と紐付けて合意する。 | H36: swebok-v4a.pdf ch06 SE Operations > 2.5 Software Backup, Disaster Recovery, and Failover(recovery needs influence backup methods, restore points, retention) | I36: CORE | J36: 原則適用。案件スコープ・成果物・規制・リスク上非該当の場合はN/A根拠を記録。 | K36: SRC-SWEBOK-V4A | L36: CONTINUITY-BACKUP;CONTINUITY-DR;RELIABILITY-HA
A37: OPS-051 | B37: SWEBOK | C37: 6. バックアップ・災害復旧・フェイルオーバー(SWEBOK 6-2.5) | D37: Critical | E37: バックアップの対象・頻度・保持期間・保管先が定義されている | F37: データ・構成・ソフトウェアごとに、取得頻度・世代数/保持期間・保管先(別リージョン等)が表等で記載されている | G37: バックアップの対象・頻度・保管先に漏れがあると、被災時に「その系だけ取っていなかった」「同一リージョンで共倒れ」が発覚する。データ・構成・ソフトウェアを網羅した設計を確認する。 | H37: swebok-v4a.pdf ch06 SE Operations > 2.5 Software Backup, Disaster Recovery, and Failover(backups of data, documents and software) | I37: CORE | J37: 原則適用。案件スコープ・成果物・規制・リスク上非該当の場合はN/A根拠を記録。 | K37: SRC-SWEBOK-V4A | L37: CONTINUITY-BACKUP;CONTINUITY-DR;RELIABILITY-HA
A38: OPS-052 | B38: SWEBOK | C38: 6. バックアップ・災害復旧・フェイルオーバー(SWEBOK 6-2.5) | D38: Critical | E38: リストア手順が文書化されている | F38: バックアップからの復元手順が番号付きステップで記載され、所要時間の見込みがある | G38: リストア手順が文書化されていないと、最も切迫した状況(データ喪失直後)でぶっつけ本番の復旧作業となり、誤操作でバックアップ自体を壊すリスクすらある。手順と所要時間見込みを事前に用意する。 | H38: swebok-v4a.pdf ch06 SE Operations > 2.5 Software Backup, Disaster Recovery, and Failover(successful recovery is especially vital) | I38: CORE | J38: 原則適用。案件スコープ・成果物・規制・リスク上非該当の場合はN/A根拠を記録。 | K38: SRC-SWEBOK-V4A | L38: CONTINUITY-BACKUP;CONTINUITY-DR;RELIABILITY-HA
A39: OPS-053 | B39: SWEBOK | C39: 6. バックアップ・災害復旧・フェイルオーバー(SWEBOK 6-2.5) | D39: High | E39: リストア/フェイルオーバーの検証(訓練)実績または計画がある | F39: 実施日と結果の記録、または実施予定(頻度・シナリオ)が記載されている | G39: テストされていないバックアップは「あるつもり」で実際には復元できないことが多い(取得漏れ・破損・手順齟齬)。SWEBOK が求める継続的なリハーサルの実績・計画を確認する。 | H39: swebok-v4a.pdf ch06 SE Operations > 2.5(preparedness and regular test of backup, disaster recovery, and failover should be constantly rehearsed) | I39: CORE | J39: 原則適用。案件スコープ・成果物・規制・リスク上非該当の場合はN/A根拠を記録。 | K39: SRC-SWEBOK-V4A | L39: CONTINUITY-BACKUP;CONTINUITY-DR;RELIABILITY-HA
A40: OPS-054 | B40: SWEBOK | C40: 6. バックアップ・災害復旧・フェイルオーバー(SWEBOK 6-2.5) | D40: High | E40: フェイルオーバー方式(自動/手動)と切り替え条件が定義されている | F40: 冗長構成の方式、自動切り替えのトリガー条件、または手動切り替えの判断者・手順が記載されている | G40: 切り替え条件と判断者が未定義だと、フェイルオーバーすべき場面で誰も決断できず停止が長引く。自動化できれば復旧時間を劇的に短縮できるため、方式の選択を明示させる。 | H40: swebok-v4a.pdf ch06 SE Operations > 2.5 Software Backup, Disaster Recovery, and Failover(automated failover daemons can reduce recovery time drastically) | I40: CORE | J40: 原則適用。案件スコープ・成果物・規制・リスク上非該当の場合はN/A根拠を記録。 | K40: SRC-SWEBOK-V4A | L40: CONTINUITY-BACKUP;CONTINUITY-DR;RELIABILITY-HA
A41: OPS-055 | B41: SWEBOK | C41: 6. バックアップ・災害復旧・フェイルオーバー(SWEBOK 6-2.5) | D41: Medium | E41: バックアップ自体の成否が監視されている | F41: バックアップジョブの失敗を検知するアラートが監視設計に含まれる | G41: バックアップジョブは静かに失敗し続けることがあり、気付くのは復元が必要になった時である。失敗検知アラートで「いざという時に空だった」事故を防ぐ。 | H41: swebok-v4a.pdf ch06 SE Operations > 2.5 Software Backup, Disaster Recovery, and Failover + 実務補完(バックアップ監視) | I41: CORE | J41: 原則適用。案件スコープ・成果物・規制・リスク上非該当の場合はN/A根拠を記録。 | K41: SRC-SWEBOK-V4A;SRC-PRACTICE | L41: CONTINUITY-BACKUP;CONTINUITY-DR;RELIABILITY-HA;OPS-OBSERVABILITY
A42: OPS-056 | B42: SWEBOK | C42: 6. バックアップ・災害復旧・フェイルオーバー(SWEBOK 6-2.5) | D42: Medium | E42: 広域災害シナリオ(リージョン障害等)の方針がある | F42: 大規模災害時の復旧方針(別リージョン復旧、縮退運転、復旧断念の判断を含む)が記載されている | G42: リージョン全体障害のような広域災害は方針なしでは現場判断不能であり、復旧か縮退か断念かで数日を空費する。大規模災害時の意思決定の枠組みを事前に用意する。 | H42: swebok-v4a.pdf ch06 SE Operations > 2.5 Software Backup, Disaster Recovery, and Failover(continuity planning / major service failure or disaster) | I42: CORE | J42: 原則適用。案件スコープ・成果物・規制・リスク上非該当の場合はN/A根拠を記録。 | K42: SRC-SWEBOK-V4A | L42: CONTINUITY-BACKUP;CONTINUITY-DR;RELIABILITY-HA
A43: OPS-060 | B43: SWEBOK | C43: 7. セキュリティ・データ保護(SWEBOK 6-2.6) | D43: Critical | E43: アクセス権限の付与・剥奪プロセスが定義されている | F43: 権限の申請・承認・付与・棚卸し・退職/異動時の剥奪の流れが記載されている | G43: 権限の棚卸しと剥奪プロセスがないと、退職者アカウントの放置や過剰権限の蓄積が進み、不正アクセス・内部犯行の温床となる。監査でも真っ先に指摘される統制を確認する。 | H43: swebok-v4a.pdf ch06 SE Operations > 2.6 Software and Data Safety, Security, Integrity, Protection, and Controls(controls b: roles and responsibilities allocated) | I43: CORE | J43: 原則適用。案件スコープ・成果物・規制・リスク上非該当の場合はN/A根拠を記録。 | K43: SRC-SWEBOK-V4A
A44: OPS-061 | B44: SWEBOK | C44: 7. セキュリティ・データ保護(SWEBOK 6-2.6) | D44: Critical | E44: セキュリティインシデントの報告経路が定義されている | F44: 検知時の報告先・報告期限・対応体制(CSIRT 等)が記載されている | G44: セキュリティインシデントは初動の遅れが被害範囲を拡大させ、法定報告期限(個人情報漏えい等)の徒過は法的リスクに直結する。報告経路と対応体制を事前に定める。 | H44: swebok-v4a.pdf ch06 SE Operations > 2.6(controls h: security incidents reported following incident management procedures) | I44: CORE | J44: 原則適用。案件スコープ・成果物・規制・リスク上非該当の場合はN/A根拠を記録。 | K44: SRC-SWEBOK-V4A
A45: OPS-062 | B45: SWEBOK | C45: 7. セキュリティ・データ保護(SWEBOK 6-2.6) | D45: High | E45: パッチ・脆弱性対応の方針が定義されている | F45: 脆弱性情報の収集方法、深刻度別の適用期限、緊急パッチの手順が記載されている | G45: パッチ適用方針がないと、既知脆弱性が放置され、公開エクスプロイトによる侵害という「防げた事故」が起きる。深刻度別の適用期限で対応の優先順位を強制する。 | H45: swebok-v4a.pdf ch06 SE Operations > 2.6 Software and Data Safety, Security, Integrity, Protection, and Controls + 実務補完(脆弱性管理) | I45: CORE | J45: 原則適用。案件スコープ・成果物・規制・リスク上非該当の場合はN/A根拠を記録。 | K45: SRC-SWEBOK-V4A;SRC-PRACTICE | L45: SEC-SUPPLY-CHAIN
A46: OPS-063 | B46: SWEBOK | C46: 7. セキュリティ・データ保護(SWEBOK 6-2.6) | D46: High | E46: 監査ログ(操作記録)の取得と保護が定義されている | F46: 本番での特権操作・データアクセスのログ取得範囲・保持期間・改ざん防止策が記載されている | G46: 監査ログがない・改ざん可能だと、事故発生時に「誰が何をしたか」を特定できず、原因究明も法的対応もできない。特権操作の追跡可能性を稼働前に確保する。 | H46: swebok-v4a.pdf ch06 SE Operations > 2.6 Software and Data Safety, Security, Integrity, Protection, and Controls(integrity, protection and controls) | I46: CORE | J46: 原則適用。案件スコープ・成果物・規制・リスク上非該当の場合はN/A根拠を記録。 | K46: SRC-SWEBOK-V4A | L46: OPS-OBSERVABILITY
A47: OPS-064 | B47: SWEBOK | C47: 7. セキュリティ・データ保護(SWEBOK 6-2.6) | D47: High | E47: データの分類と保護策が定義されている | F47: 個人情報・機密データの所在と、暗号化(保存時/転送時)・マスキング等の保護策が記載されている | G47: どこに個人情報・機密データがあるか把握していないと、保護策の適用漏れ(暗号化されていない複製、ログへの混入)が生じ、漏えい時の影響評価もできない。データの所在と保護策の対応を確認する。 | H47: swebok-v4a.pdf ch06 SE Operations > 2.6(risk assessment on the security and availability of information / data protection) | I47: CORE | J47: 原則適用。案件スコープ・成果物・規制・リスク上非該当の場合はN/A根拠を記録。 | K47: SRC-SWEBOK-V4A
A48: OPS-065 | B48: SWEBOK | C48: 7. セキュリティ・データ保護(SWEBOK 6-2.6) | D48: Medium | E48: セキュリティがプロセスに早期統合されている(DevSecOps) | F48: パイプライン内のセキュリティ検査(脆弱性スキャン等)または設計段階のセキュリティレビューの記載がある | G48: セキュリティ検査をリリース直前・稼働後に後回しにすると、発見された脆弱性の修正コストが跳ね上がり、リリース遅延か脆弱なままの稼働かの二択を迫られる。DevSecOps の早期統合を確認する。 | H48: swebok-v4a.pdf ch06 SE Operations > 2.6(DevSecOps: integration of security early and throughout the software process) | I48: CORE | J48: 原則適用。案件スコープ・成果物・規制・リスク上非該当の場合はN/A根拠を記録。 | K48: SRC-SWEBOK-V4A
A49: OPS-066 | B49: SWEBOK | C49: 7. セキュリティ・データ保護(SWEBOK 6-2.6) | D49: Medium | E49: 権限の最小化(最小権限の原則)が適用されている | F49: ロール別の権限設計があり、全員が管理者権限を持つ設計になっていない | G49: 全員が管理者権限を持つ設計は、一つの認証情報漏えいや一人の誤操作が全システム侵害・全損に直結する。権限を業務上必要な範囲に絞り、事故の影響半径を限定する。 | H49: swebok-v4a.pdf ch06 SE Operations > 2.6 Software and Data Safety, Security, Integrity, Protection, and Controls + 実務補完(最小権限の原則) | I49: CORE | J49: 原則適用。案件スコープ・成果物・規制・リスク上非該当の場合はN/A根拠を記録。 | K49: SRC-SWEBOK-V4A;SRC-PRACTICE | L49: SEC-IAM
A50: OPS-902 | B50: 追加承認 | C50: 7. セキュリティ・データ保護(SWEBOK 6-2.6) | D50: High | E50: 情報セキュリティリスクアセスメントとポリシー・教育の枠組みがある | F50: 情報資産に対するリスクアセスメントの実施記録(または計画)と、準拠するセキュリティポリシーの参照、運用要員へのセキュリティ教育・周知の方法が記載されている | G50: 個別の技術対策だけではリスクの見落とし(未評価の資産・脅威)が残り、ポリシーと教育がなければ統制が現場で実行されない。対策の網羅性を上流のリスク評価で担保し、要員の認識不足による事故を防ぐ。 | H50: swebok-v4a.pdf ch06 SE Operations > 2.6 Software and Data Safety, Security, Integrity, Protection, and Controls — 情報セキュリティリスクアセスメントとポリシー・教育(security risk assessment, information security policy, staff awareness/training) | I50: CORE | J50: 原則適用。案件スコープ・成果物・規制・リスク上非該当の場合はN/A根拠を記録。 | K50: SRC-SWEBOK-V4A
A51: OPS-070 | B51: SWEBOK | C51: 8. デプロイ/リリース工学(SWEBOK 6-3.1 / 6-3.2) | D51: High | E51: デプロイとリリースが区別されている | F51: バージョンの環境導入(デプロイ)と機能の顧客公開(リリース)が区別され、それぞれの手順・判断が記載されている | G51: デプロイとリリースを混同すると、「本番に載せる=即ユーザー公開」となり段階的公開・即時無効化ができず、リリースリスクを制御する手段を失う。両者を分離する設計判断を確認する。 | H51: swebok-v4a.pdf ch06 SE Operations > 3.2 Deployment/Release Engineering(deployment vs. release の定義) | I51: CORE | J51: 原則適用。案件スコープ・成果物・規制・リスク上非該当の場合はN/A根拠を記録。 | K51: SRC-SWEBOK-V4A
A52: OPS-071 | B52: SWEBOK | C52: 8. デプロイ/リリース工学(SWEBOK 6-3.1 / 6-3.2) | D52: Critical | E52: デプロイ手順が再現可能な具体性で書かれている | F52: 各ステップに実行コマンド/パイプライン名・実行者・期待結果が記載され、担当者によらず同じ結果になる | G52: 手順が担当者の暗黙知に依存すると、代理実施者のミスや手順飛ばしによるデプロイ事故が起きる。誰が実行しても同じ結果になる具体性を要求し、属人化と作業ミスを防ぐ。 | H52: swebok-v4a.pdf ch06 SE Operations > 3.2 Deployment/Release Engineering(automating the different deployment steps) | I52: CORE | J52: 原則適用。案件スコープ・成果物・規制・リスク上非該当の場合はN/A根拠を記録。 | K52: SRC-SWEBOK-V4A
A53: OPS-072 | B53: SWEBOK | C53: 8. デプロイ/リリース工学(SWEBOK 6-3.1 / 6-3.2) | D53: Critical | E53: リリース判定基準(事前条件)が定義されている | F53: テスト完了・承認・監視準備等の判定項目がチェックリスト形式で記載され、判定者が明記されている | G53: 判定基準がないと、テスト未完・監視未準備のまま「なんとなく」リリースされ、初日から障害対応に追われる。Go/No-Go の判定項目と判定者を明確にしてリリース品質のゲートを設ける。 | H53: swebok-v4a.pdf ch06 SE Operations > 3.2 Deployment/Release Engineering(release requests identified, recorded and approved — ISO 12207 release control) | I53: CORE | J53: 原則適用。案件スコープ・成果物・規制・リスク上非該当の場合はN/A根拠を記録。 | K53: SRC-SWEBOK-V4A;SRC-ISO-GENERAL
A54: OPS-073 | B54: SWEBOK | C54: 8. デプロイ/リリース工学(SWEBOK 6-3.1 / 6-3.2) | D54: High | E54: リリース戦略(段階的展開)が選択・記載されている | F54: 環境ベース/アプリケーションベース(フィーチャートグル)の別と、カナリアリリース等の段階展開の要否・方法が記載されている | G54: 全ユーザー一斉リリースは、不具合の影響が即座に全体へ波及する。環境ベース/アプリケーションベース(トグル)やカナリアによる段階展開の選択を求め、リリースの爆発半径を制御する。 | H54: swebok-v4a.pdf ch06 SE Operations > 3.2 Deployment/Release Engineering(environment-based / application-based release strategies, canary release) | I54: CORE | J54: 原則適用。案件スコープ・成果物・規制・リスク上非該当の場合はN/A根拠を記録。 | K54: SRC-SWEBOK-V4A
A55: OPS-074 | B55: SWEBOK | C55: 8. デプロイ/リリース工学(SWEBOK 6-3.1 / 6-3.2) | D55: High | E55: リリース後の検証項目が定義されている | F55: スモークテスト項目・監視確認項目・確認担当と確認時間が列挙されている | G55: リリース後の確認項目がないと、デプロイ起因の不具合をユーザーからの苦情で初めて知ることになる。スモークテストと監視確認で「静かな失敗」を即座に検知する。 | H55: swebok-v4a.pdf ch06 SE Operations > 3.2 Deployment/Release Engineering(executing smoke testing / observing newly started software)/ 1.3 Software Installation(verification step) | I55: CORE | J55: 原則適用。案件スコープ・成果物・規制・リスク上非該当の場合はN/A根拠を記録。 | K55: SRC-SWEBOK-V4A
A56: OPS-075 | B56: SWEBOK | C56: 8. デプロイ/リリース工学(SWEBOK 6-3.1 / 6-3.2) | D56: High | E56: 関係者への周知(事前告知・完了報告)が定義されている | F56: 通知先・タイミング・テンプレートまたは記載例がある | G56: 周知がないと、関係部署がリリース起因の事象を通常障害として二重調査したり、ユーザー窓口が変更を知らずに誤案内する。ステークホルダーへの情報伝達を仕組み化する。 | H56: swebok-v4a.pdf ch06 SE Operations > 2.1.1 Operations Plan(inform all stakeholders) | I56: CORE | J56: 原則適用。案件スコープ・成果物・規制・リスク上非該当の場合はN/A根拠を記録。 | K56: SRC-SWEBOK-V4A
A57: OPS-076 | B57: SWEBOK | C57: 8. デプロイ/リリース工学(SWEBOK 6-3.1 / 6-3.2) | D57: Medium | E57: 変更内容とリスク評価がリリース単位で記録される | F57: リリースごとに変更概要・影響範囲・リスクと対策を記録する様式がある | G57: リリース単位のリスク評価がないと、危険な変更(スキーマ変更・依存更新)が通常変更と同じ軽さで扱われ、対策なしで本番に入る。ISO 12207 のリリース計画が求めるリスク評価を記録させる。 | H57: swebok-v4a.pdf ch06 SE Operations > 2.1.1 Operations Plan(assess the risk of a given release)/ 4.2 Change Management | I57: CORE | J57: 原則適用。案件スコープ・成果物・規制・リスク上非該当の場合はN/A根拠を記録。 | K57: SRC-SWEBOK-V4A
A58: OPS-077 | B58: SWEBOK | C58: 8. デプロイ/リリース工学(SWEBOK 6-3.1 / 6-3.2) | D58: Medium | E58: デプロイパイプラインが自動化されている(または自動化計画がある) | F58: CI/CD による自動ビルド・テスト・デプロイの記載、または手動部分の自動化計画がある | G58: 手動デプロイは時間と品質の両面で非効率であり、ヒューマンエラーの主要因になる。CI/CD による自動化(または計画)を確認し、デプロイの再現性と頻度を高める。 | H58: swebok-v4a.pdf ch06 SE Operations > 3.2 Deployment/Release Engineering / 6. Software Engineering Operations Tools(CI/CD) | I58: CORE | J58: 原則適用。案件スコープ・成果物・規制・リスク上非該当の場合はN/A根拠を記録。 | K58: SRC-SWEBOK-V4A
A59: OPS-078 | B59: SWEBOK | C59: 8. デプロイ/リリース工学(SWEBOK 6-3.1 / 6-3.2) | D59: Low | E59: デプロイ頻度・所要時間が計測されている | F59: デプロイの頻度・リードタイム等の指標を記録する仕組みの記載がある | G59: デプロイ頻度・リードタイムを計測しないと、デリバリー能力の劣化(リリースが重く・怖くなっていく傾向)に気付けない。改善の基礎データとして計測の仕組みを確認する。 | H59: swebok-v4a.pdf ch06 SE Operations > 4.3 Monitor, Measure, Track, and Review + 実務補完(DORA メトリクス) | I59: CORE | J59: 原則適用。案件スコープ・成果物・規制・リスク上非該当の場合はN/A根拠を記録。 | K59: SRC-SWEBOK-V4A;SRC-DORA;SRC-PRACTICE
A60: OPS-080 | B60: SWEBOK | C60: 9. ロールバック・データ移行(SWEBOK 6-3.3) | D60: Critical | E60: すべてのリリース手順にロールバック手順が併記されている | F60: 前バージョンへ戻す具体的手順(コマンド・所要時間)が記載され、「ロールバック不可」の場合は代替(前方修正)方針が明記されている | G60: ロールバック手順なしのリリースは、不具合発生時に前方修正しか選択肢がなく、障害が数時間〜数日単位で長期化する。SWEBOK が求める「デプロイ前に計画・リハーサル済みのロールバック」を担保する。 | H60: swebok-v4a.pdf ch06 SE Operations > 3.3 Rollback and Data Migration(planned and rehearsed rollback before deployment) | I60: CORE | J60: 原則適用。案件スコープ・成果物・規制・リスク上非該当の場合はN/A根拠を記録。 | K60: SRC-SWEBOK-V4A
A61: OPS-081 | B61: SWEBOK | C61: 9. ロールバック・データ移行(SWEBOK 6-3.3) | D61: Critical | E61: ロールバックの判断基準が明文化されている | F61: 発動条件(エラー率・SLO 違反等の数値条件、または判断者と判断材料)が記載されている | G61: 発動基準がないと、障害中に「戻すか粘るか」の議論で貴重な復旧時間を浪費する。数値条件または判断者を事前に決め、ロールバック判断を迅速化する。 | H61: swebok-v4a.pdf ch06 SE Operations > 3.3 Rollback and Data Migration / 4.2 Change Management(need for a rollback strategy) | I61: CORE | J61: 原則適用。案件スコープ・成果物・規制・リスク上非該当の場合はN/A根拠を記録。 | K61: SRC-SWEBOK-V4A
... A80: OPS-104 | B80: SWEBOK | C80: 11. 変更管理(SWEBOK 6-4.2) | D80: Medium | E80: 小さく頻繁な変更を可能にする方針がある | F80: 変更を小単位で独立してデプロイできる方針・仕組み(トランクベース開発、CD 等)の記載、または大規模一括リリースとする理由の記載がある | G80: 大規模一括リリースは変更間の相互作用でリスクが乗算的に増え、失敗時の切り分けも困難になる。DevOps が推奨する小さく独立した変更を可能にする方針(またはそうしない理由)を確認する。 | H80: swebok-v4a.pdf ch06 SE Operations > 4.2 Change Management(deliver small units of change on demand and independently) | I80: CORE | J80: 原則適用。案件スコープ・成果物・規制・リスク上非該当の場合はN/A根拠を記録。 | K80: SRC-SWEBOK-V4A
A81: OPS-110 | B81: SWEBOK | C81: 12. 監視・テレメトリ・アラート(SWEBOK 6-4.3 / 6-5.1 / 6-6.4) | D81: Critical | E81: アプリケーション・OS・インフラの3層で監視項目が定義されている | F81: 各層のログ・メトリクス・トレースの収集対象が一覧化され、いずれかの層が丸ごと欠けていない | G81: いずれかの層(アプリ/OS/インフラ)の監視が丸ごと欠けると、その層で起きる障害が検知不能な盲点になり、原因特定も他層からの推測頼みになる。SWEBOK が求める全層でのデータ収集を確認する。 | H81: swebok-v4a.pdf ch06 SE Operations > 6.4 Monitoring and Telemetry(collect data at all layers)/ 5.1 Incident and Problem Prevention | I81: CORE | J81: 原則適用。案件スコープ・成果物・規制・リスク上非該当の場合はN/A根拠を記録。 | K81: SRC-SWEBOK-V4A | L81: OPS-OBSERVABILITY
A82: OPS-111 | B82: SWEBOK | C82: 12. 監視・テレメトリ・アラート(SWEBOK 6-4.3 / 6-5.1 / 6-6.4) | D82: Critical | E82: 各アラートに閾値・重要度・通知先が定義されている | F82: アラート定義表に、監視項目・発報条件(数値閾値)・重要度・通知先(チャネル/オンコール)が揃っている | G82: 閾値・重要度・通知先のいずれかが欠けたアラートは、発報されない・誰にも届かない・重要度が判断できないのいずれかで機能しない。アラート定義の完全性を表形式で検証可能にする。 | H82: swebok-v4a.pdf ch06 SE Operations > 5.2 Operational Risk Management(automate the alerts / agreed-upon risk tolerance)/ 6.4 Monitoring and Telemetry | I82: CORE | J82: 原則適用。案件スコープ・成果物・規制・リスク上非該当の場合はN/A根拠を記録。 | K82: SRC-SWEBOK-V4A | L82: OPS-OBSERVABILITY
A83: OPS-112 | B83: SWEBOK | C83: 12. 監視・テレメトリ・アラート(SWEBOK 6-4.3 / 6-5.1 / 6-6.4) | D83: Critical | E83: 各アラートに対応アクションが紐付いている | F83: すべてのアラートが対応 Runbook を参照するか、対応不要(情報のみ)と明示されている | G83: 対応アクションのないアラートは受信者に判断を丸投げし、放置か場当たり対応を生む。全アラートを Runbook 参照または「対応不要」明示のいずれかに分類し、通知の実効性を保証する。 | H83: swebok-v4a.pdf ch06 SE Operations > 6.4 Monitoring and Telemetry + 実務補完(アクショナブルアラート) | I83: CORE | J83: 原則適用。案件スコープ・成果物・規制・リスク上非該当の場合はN/A根拠を記録。 | K83: SRC-SWEBOK-V4A;SRC-PRACTICE | L83: OPS-OBSERVABILITY
A84: OPS-113 | B84: SWEBOK | C84: 12. 監視・テレメトリ・アラート(SWEBOK 6-4.3 / 6-5.1 / 6-6.4) | D84: High | E84: SLO 違反を検知できる監視がある | F84: SLI の計測とSLO 違反(またはバジェット消費の加速)を検知するアラートが定義されている | G84: SLO を定義しても違反を検知する監視がなければ、未達は月次報告で事後に判明するだけで対処が間に合わない。SLI 計測とバジェット消費の監視を接続する。 | H84: swebok-v4a.pdf ch06 SE Operations > 2.3 Software Availability, Continuity, and Service Levels(availability measured and recorded)/ 4.3 Monitor, Measure, Track, and Review | I84: CORE | J84: 原則適用。案件スコープ・成果物・規制・リスク上非該当の場合はN/A根拠を記録。 | K84: SRC-SWEBOK-V4A | L84: OPS-OBSERVABILITY
A85: OPS-114 | B85: SWEBOK | C85: 12. 監視・テレメトリ・アラート(SWEBOK 6-4.3 / 6-5.1 / 6-6.4) | D85: High | E85: 対応不能・恒常的に無視されるアラートがない設計である | F85: アラートの抑制条件・チューニング(見直し)プロセスが定義されている | G85: 対応不能・常時発報のアラートはオンコールを疲弊させ、本当に重要なアラートが埋もれて見逃される(アラート疲れ)。抑制条件とチューニングプロセスで信号対雑音比を維持する。 | H85: swebok-v4a.pdf ch06 SE Operations > 5.2 Operational Risk Management(agreed-upon level of risk tolerance for alerts)+ 実務補完(アラート疲れ対策) | I85: CORE | J85: 原則適用。案件スコープ・成果物・規制・リスク上非該当の場合はN/A根拠を記録。 | K85: SRC-SWEBOK-V4A;SRC-PRACTICE | L85: OPS-OBSERVABILITY
A86: OPS-115 | B86: SWEBOK | C86: 12. 監視・テレメトリ・アラート(SWEBOK 6-4.3 / 6-5.1 / 6-6.4) | D86: High | E86: ログ・メトリクスの保持期間が定義されている | F86: データ種別ごとの保持期間と、障害調査・監査要件との整合が記載されている | G86: 保持期間が短すぎると障害調査や監査で過去データが参照できず、長すぎると保管コストが膨張する。調査・監査要件との整合を根拠にした保持設計を求める。 | H86: swebok-v4a.pdf ch06 SE Operations > 6.4 Monitoring and Telemetry / 2.6(controls) | I86: CORE | J86: 原則適用。案件スコープ・成果物・規制・リスク上非該当の場合はN/A根拠を記録。 | K86: SRC-SWEBOK-V4A | L86: OPS-OBSERVABILITY
A87: OPS-116 | B87: SWEBOK | C87: 12. 監視・テレメトリ・アラート(SWEBOK 6-4.3 / 6-5.1 / 6-6.4) | D87: Medium | E87: 閲覧者別のダッシュボードが設計されている | F87: オンコール用・管理/報告用など目的別のダッシュボード構成が記載されている | G87: 単一のダッシュボードに全情報を詰め込むと、オンコールは障害時に必要な情報を探せず、経営層は読めない。SWEBOK が述べる「ステークホルダー別のダッシュボード」設計を確認する。 | H87: swebok-v4a.pdf ch06 SE Operations > 6.4 Monitoring and Telemetry(different dashboards for different stakeholders) | I87: CORE | J87: 原則適用。案件スコープ・成果物・規制・リスク上非該当の場合はN/A根拠を記録。 | K87: SRC-SWEBOK-V4A | L87: OPS-OBSERVABILITY
A88: OPS-117 | B88: SWEBOK | C88: 12. 監視・テレメトリ・アラート(SWEBOK 6-4.3 / 6-5.1 / 6-6.4) | D88: Medium | E88: 予防的検知(傾向監視)が含まれている | F88: 突発障害だけでなく、リソース逼迫・エラー率漸増などの予兆を捉える監視項目がある | G88: 突発障害の検知だけでは、リソース逼迫やエラー率漸増のような「予告された障害」を防げない。テレメトリ分析による早期発見(インシデント予防)の観点を求める。 | H88: swebok-v4a.pdf ch06 SE Operations > 5.1 Incident and Problem Prevention(product telemetry with analytics to detect problems as early as possible) | I88: CORE | J88: 原則適用。案件スコープ・成果物・規制・リスク上非該当の場合はN/A根拠を記録。 | K88: SRC-SWEBOK-V4A | L88: OPS-OBSERVABILITY
A89: OPS-118 | B89: SWEBOK | C89: 12. 監視・テレメトリ・アラート(SWEBOK 6-4.3 / 6-5.1 / 6-6.4) | D89: Low | E89: テレメトリのコストが考慮されている | F89: 収集量・保持期間に対するコスト見積もりまたは抑制方針の記載がある | G89: テレメトリは無計画に収集するとログ保管・転送コストがインフラ本体を上回ることがある。収集量・保持のコスト見積もりで観測性と費用のバランスを取る。 | H89: 実務補完(オブザーバビリティコスト管理)。SWEBOK 6.4 Monitoring and Telemetry の運用面の補完 | I89: CORE | J89: 原則適用。案件スコープ・成果物・規制・リスク上非該当の場合はN/A根拠を記録。 | K89: SRC-PRACTICE | L89: OPS-OBSERVABILITY;COST
A90: OPS-903 | B90: 追加承認 | C90: 12. 監視・テレメトリ・アラート(SWEBOK 6-4.3 / 6-5.1 / 6-6.4) | D90: Medium | E90: 承認外の構成変更(構成ドリフト)を検知する仕組みがある | F90: 承認されたデプロイ・変更作業以外による本番構成の変更を検知する手段(IaC 差分検出、構成監査、変更検知アラート等)が記載されている | G90: 手動 hotfix や不正操作による構成ドリフトを放置すると、IaC と実環境が乖離して再現不能な障害を生み、セキュリティ侵害の兆候も見逃す。承認プロセスを迂回した変更を検知して統制の実効性を保つ。 | H90: swebok-v4a.pdf ch06 SE Operations > 4.3 Monitor, Measure, Track, and Review — 承認外の構成変更の検知(configuration changes unrelated to approved deployment tasks) | I90: CORE | J90: 原則適用。案件スコープ・成果物・規制・リスク上非該当の場合はN/A根拠を記録。 | K90: SRC-SWEBOK-V4A | L90: OPS-OBSERVABILITY
A91: OPS-120 | B91: SWEBOK | C91: 13. サービス報告・障害報告書・継続的改善(SWEBOK 6-4.5 / 6-5) | D91: High | E91: 定期サービス報告の内容と頻度が定義されている | F91: SLO 達成状況・インシデント件数/傾向・セキュリティ事象・容量トレンドを含む報告項目と頻度・宛先が記載されている | G91: 定期報告がないと、サービスレベルの劣化傾向や容量トレンドが意思決定層に届かず、投資判断が障害後の後手に回る。SWEBOK が挙げる報告項目(SLA 達成・セキュリティ・傾向・満足度)を網羅させる。 | H91: swebok-v4a.pdf ch06 SE Operations > 4.5 Service Reporting(performance against service-level targets, security breaches, trend information) | I91: CORE | J91: 原則適用。案件スコープ・成果物・規制・リスク上非該当の場合はN/A根拠を記録。 | K91: SRC-SWEBOK-V4A
A92: OPS-121 | B92: SWEBOK | C92: 13. サービス報告・障害報告書・継続的改善(SWEBOK 6-4.5 / 6-5) | D92: Critical | E92: 障害報告書にタイムラインがある | F92: 発生・検知・対応判断・復旧の時刻が時系列で記録され、検知までの時間と復旧までの時間が読み取れる | G92: タイムラインがない障害報告書では、検知の遅れと復旧の遅れを区別できず、どこを改善すべきか(監視か手順か)が特定できない。時系列記録を必須にして改善点の分析を可能にする。 | H92: swebok-v4a.pdf ch06 SE Operations > 4.1 Incident Management(proper analysis and/or post mortems) | I92: CORE | J92: 原則適用。案件スコープ・成果物・規制・リスク上非該当の場合はN/A根拠を記録。 | K92: SRC-SWEBOK-V4A
A93: OPS-122 | B93: SWEBOK | C93: 13. サービス報告・障害報告書・継続的改善(SWEBOK 6-4.5 / 6-5) | D93: Critical | E93: 障害報告書で直接原因と根本原因が区別されている | F93: 表面的な事象(直接原因)と、それを生んだ仕組み上の原因(根本原因)が区別して記載されている | G93: 直接原因(例: プロセス停止)だけで報告を閉じると、それを生んだ仕組み上の欠陥が残り同種障害が再発する。直接原因と根本原因の区別を強制し、再発防止の深さを担保する。 | H93: swebok-v4a.pdf ch06 SE Operations > 3.4 Problem Resolution(analysis of the cause / underlying cause)/ 4.1(find the source of the incident) | I93: CORE | J93: 原則適用。案件スコープ・成果物・規制・リスク上非該当の場合はN/A根拠を記録。 | K93: SRC-SWEBOK-V4A
A94: OPS-123 | B94: SWEBOK | C94: 13. サービス報告・障害報告書・継続的改善(SWEBOK 6-4.5 / 6-5) | D94: Critical | E94: 再発防止策が担当者・期限付きのアクションアイテムになっている | F94: 各再発防止策に担当者・期限・追跡先(チケット等)が記載されている | G94: 担当者・期限のない再発防止策は「今後注意する」で終わり、実行されない。アクションアイテム化と追跡先の記録で、対策の実施を検証可能にする。 | H94: swebok-v4a.pdf ch06 SE Operations > 4.1 Incident Management(appropriate solutions must be implemented to prevent similar incidents) | I94: CORE | J94: 原則適用。案件スコープ・成果物・規制・リスク上非該当の場合はN/A根拠を記録。 | K94: SRC-SWEBOK-V4A
A95: OPS-124 | B95: SWEBOK | C95: 13. サービス報告・障害報告書・継続的改善(SWEBOK 6-4.5 / 6-5) | D95: High | E95: 障害報告書が非難を伴わない記述である | F95: 個人の責任追及でなくプロセス・システムの改善に焦点を当てた記述であり、個人名の吊るし上げがない | G95: 個人を非難する報告文化では、次の障害でメンバーが情報を隠すようになり、正確な原因究明が不可能になる。プロセス・システム改善に焦点を当てた記述で報告の誠実さを守る。 | H95: 実務補完(ブレームレスポストモーテム、Google SRE)。SWEBOK 4.1 のポストモーテムを実効化する項目 | I95: CORE | J95: 原則適用。案件スコープ・成果物・規制・リスク上非該当の場合はN/A根拠を記録。 | K95: SRC-GCP-WAF;SRC-SRE;SRC-PRACTICE
A96: OPS-125 | B96: SWEBOK | C96: 13. サービス報告・障害報告書・継続的改善(SWEBOK 6-4.5 / 6-5) | D96: High | E96: 影響範囲が定量的に記載されている | F96: 影響ユーザー数・件数・時間・SLO/エラーバジェットへの影響が数値で記載されている | G96: 影響が定量化されていないと、障害の重大性を経営・顧客に正しく伝えられず、再発防止投資の優先順位判断も感覚頼みになる。ユーザー数・時間・SLO 影響の数値記載を求める。 | H96: swebok-v4a.pdf ch06 SE Operations > 4.1 Incident Management(assessing the business impact)/ 4.5 Service Reporting | I96: CORE | J96: 原則適用。案件スコープ・成果物・規制・リスク上非該当の場合はN/A根拠を記録。 | K96: SRC-SWEBOK-V4A
A97: OPS-126 | B97: SWEBOK | C97: 13. サービス報告・障害報告書・継続的改善(SWEBOK 6-4.5 / 6-5) | D97: Medium | E97: 検知・対応の改善(監視・Runbook 見直し)が含まれている | F97: 「もっと早く検知/復旧できたか」の考察と、監視・アラート・Runbook への反映有無が記載されている | G97: 根本原因対策だけでは、次の(別原因の)障害でも検知・復旧が同じだけ遅れる。「もっと早く検知・復旧できたか」の考察を必須にし、監視・Runbook 側の改善につなげる。 | H97: swebok-v4a.pdf ch06 SE Operations > 5.1 Incident and Problem Prevention / 4.3 Monitor, Measure, Track, and Review | I97: CORE | J97: 原則適用。案件スコープ・成果物・規制・リスク上非該当の場合はN/A根拠を記録。 | K97: SRC-SWEBOK-V4A | L97: OPS-OBSERVABILITY
A98: OPS-127 | B98: SWEBOK | C98: 13. サービス報告・障害報告書・継続的改善(SWEBOK 6-4.5 / 6-5) | D98: Medium | E98: ポストモーテム実施の基準がある | F98: どの Severity 以上で障害報告書を作成するかの基準が定義されている | G98: 作成基準がないと、報告書の作成が担当者の裁量になり、学ぶべき重大障害が記録されないか、軽微な事象まで報告義務化されて形骸化する。Severity 基準でポストモーテムの実施を安定させる。 | H98: swebok-v4a.pdf ch06 SE Operations > 4.1 Incident Management(post mortems)+ 実務補完(ポストモーテム基準) | I98: CORE | J98: 原則適用。案件スコープ・成果物・規制・リスク上非該当の場合はN/A根拠を記録。 | K98: SRC-SWEBOK-V4A;SRC-PRACTICE
A99: OPS-CG01 | B99: クラウド補完 | C99: 13. サービス報告・障害報告書・継続的改善(SWEBOK 6-4.5 / 6-5) | D99: Medium | E99: 障害報告書(ポストモーテム)が組織横断で共有される仕組みがある | F99: ポストモーテムの共有先・共有方法(全社公開、ナレッジベース登録等)が定義され、対象読者が理解できる記述レベルで公開されている | G99: 共有範囲が狭いと学習効果がチーム内に閉じ、他チームで同種の障害が再発する。 | H99: Google Cloud Well-Architected Framework > 信頼性 > Conduct thorough postmortems > Share the postmortem as widely as possible / Make the postmortem report readable by all intended audiences | I99: CORE | J99: 原則適用。案件スコープ・成果物・規制・リスク上非該当の場合はN/A根拠を記録。 | K99: SRC-GCP-WAF
A100: OPS-130 | B100: SWEBOK | C100: 14. 自動化・ツール・組織適合(SWEBOK 6-1.4 / 6-5.3 / 6-5.4 / 6-6) | D100: High | E100: 反復作業の自動化方針がある | F100: 環境構築・デプロイ・テスト・フェイルオーバー等の反復作業について、自動化済み/自動化予定/手動維持(理由付き)が整理されている | G100: 反復作業を手動のまま放置すると、遅延・ばらつき・ヒューマンエラーが恒常化し、運用のスケールが人数に比例してしまう。SWEBOK が全編で強調する自動化の方針(対象と優先順位)を確認する。 | H100: swebok-v4a.pdf ch06 SE Operations > 1.4 Scripting and Automating / 5.3 Automating Software Engineering Operations | I100: CORE | J100: 原則適用。案件スコープ・成果物・規制・リスク上非該当の場合はN/A根拠を記録。 | K100: SRC-SWEBOK-V4A
A101: OPS-131 | B101: SWEBOK | C101: 14. 自動化・ツール・組織適合(SWEBOK 6-1.4 / 6-5.3 / 6-5.4 / 6-6) | D101: Medium | E101: 属人化された手作業が特定されている | F101: 特定個人しか実施できない作業の有無が確認され、ある場合は Runbook 化・自動化の計画がある | G101: 特定個人しかできない作業は、その人の不在・退職が即サービス継続リスクになる。属人作業の棚卸しと Runbook 化・自動化計画で単一障害点(人)を解消する。 | H101: swebok-v4a.pdf ch06 SE Operations > 1.4 Scripting and Automating(standardization of operations)+ 実務補完(属人化解消) | I101: CORE | J101: 原則適用。案件スコープ・成果物・規制・リスク上非該当の場合はN/A根拠を記録。 | K101: SRC-SWEBOK-V4A;SRC-PRACTICE
A102: OPS-132 | B102: SWEBOK | C102: 14. 自動化・ツール・組織適合(SWEBOK 6-1.4 / 6-5.3 / 6-5.4 / 6-6) | D102: Medium | E102: 使用ツールと役割が一覧化されている | F102: CI/CD・コンテナ/オーケストレーション・監視等のツールと用途・管理者が記載されている(実在するツール名であること) | G102: ツールの全体像と管理者が不明だと、ライセンス切れ・管理者退職・ツール間の隙間が運用停止の原因になる。また架空・曖昧なツール名は設計が机上の空論である兆候として検出する。 | H102: swebok-v4a.pdf ch06 SE Operations > 6. Software Engineering Operations Tools / 6.1 Containers and Virtualization | I102: CORE | J102: 原則適用。案件スコープ・成果物・規制・リスク上非該当の場合はN/A根拠を記録。 | K102: SRC-SWEBOK-V4A
A103: OPS-133 | B103: SWEBOK | C103: 14. 自動化・ツール・組織適合(SWEBOK 6-1.4 / 6-5.3 / 6-5.4 / 6-6) | D103: Medium | E103: プロセスが組織規模に適合している | F103: 小規模組織の場合に過剰な承認段階・文書がなく(ISO/IEC 29110 の趣旨)、大規模の場合に必要な統制が欠けていない | G103: 大組織向け標準を小規模組織にそのまま適用すると、承認・文書のコストが実作業を圧迫して形骸化する。逆に規模に必要な統制が欠ければ事故になる。ISO/IEC 29110 の趣旨に沿った適合度を確認する。 | H103: swebok-v4a.pdf ch06 SE Operations > 5.4 Software Engineering Operations for Small Organizations(ISO/IEC 29110) | I103: CORE | J103: 原則適用。案件スコープ・成果物・規制・リスク上非該当の場合はN/A根拠を記録。 | K103: SRC-SWEBOK-V4A;SRC-ISO-GENERAL
A104: OPS-134 | B104: SWEBOK | C104: 14. 自動化・ツール・組織適合(SWEBOK 6-1.4 / 6-5.3 / 6-5.4 / 6-6) | D104: Low | E104: 運用テストがライフサイクル早期から計画されている | F104: 運用観点のテスト(監視動作、フェイルオーバー、Runbook 検証)がリリース前テスト計画に含まれている | G104: 運用観点のテスト(監視動作・フェイルオーバー)をリリース直前に回すと、不備の修正が間に合わず「監視なしで稼働開始」になる。TDD/ATDD の思想どおり開発早期からの計画を求める。 | H104: swebok-v4a.pdf ch06 SE Operations > 3.1 Operational Testing, Verification, and Acceptance(operational testing ongoing during development, not only at the end) | I104: CORE | J104: 原則適用。案件スコープ・成果物・規制・リスク上非該当の場合はN/A根拠を記録。 | K104: SRC-SWEBOK-V4A
A105: OPS-904 | B105: 追加承認 | C105: 14. 自動化・ツール・組織適合(SWEBOK 6-1.4 / 6-5.3 / 6-5.4 / 6-6) | D105: Medium | E105: 運用リスクが継続的に管理され、リスク許容度が関係者と合意されている | F105: 可用性・容量・セキュリティ等の運用リスクの一覧(リスク登録簿等)と見直し契機、およびアラート閾値・デプロイ方式の根拠となるリスク許容度をプロダクトオーナー等と合意した記録がある | G105: リスク許容度の合意がないと、アラート閾値やデプロイ方式の厳しさが運用チームの独断となり、事業側との認識齟齬(過剰な慎重さ、または想定外の障害受容)を生む。運用リスクを一過性でなく継続的に管理する枠組みを担保する。 | H105: swebok-v4a.pdf ch06 SE Operations > 5.2 Operational Risk Management — 継続的な運用リスク管理とリスク許容度の合意(continuous risk management, agreed-upon level of risk tolerance) | I105: CORE | J105: 原則適用。案件スコープ・成果物・規制・リスク上非該当の場合はN/A根拠を記録。 | K105: SRC-SWEBOK-V4A
A106: OPS-CZ01 | B106: クラウド補完 | C106: 15. クラウドコスト運用(FinOps) | D106: High | E106: 運用設計にコスト監視が含まれ、予算アラート(閾値・予測)と異常検知の通知先・対応手順が定義されている | F106: 運用設計書にコストアラートの閾値・通知先・対応フローが記載され、定期コストレビューが運用カレンダーに組み込まれている | G106: コストはクラウド運用の品質特性であり、監視しないと予算超過の検知が請求後になる。 | H106: Azure Well-Architected Framework > コスト最適化の柱 > CO:03 (Collect and review cost data / Automate cost alerts) | I106: CORE | J106: 原則適用。案件スコープ・成果物・規制・リスク上非該当の場合はN/A根拠を記録。 | K106: SRC-AZR-WAF | L106: OPS-OBSERVABILITY;COST

Sheet 07_保守
A1: ID | B1: 区分 | C1: カテゴリ | D1: 基準重要度 | E1: チェック項目 | F1: 合格基準 | G1: 意図(なぜ確認するか) | H1: 対象ドキュメント(参照箇所) | I1: 適用プロファイル | J1: 適用条件 | K1: 出典ID | L1: 重複統制グループ | M1: 案件重要度 | N1: 適用判定 | O1: 判定 | P1: 証跡・参照箇所 | Q1: 指摘・Issue ID | R1: 対応方針 | S1: 例外・リスク受容承認者 | T1: 是正期限 | U1: レビュアー | V1: レビュー日 | W1: 再確認結果
A2: MNT-001 | B2: SWEBOK | C2: 1. 保守計画(MNT-001〜) | D2: Critical | E2: 対象システムと適用範囲が特定されている | F2: システム名・バージョン・対象環境(本番/検証)・対象外事項が明記されている | G2: 対象システムと範囲が曖昧なまま保守契約・作業が始まると、障害時に「それはうちの担当外」という責任の押し付け合いや、想定外環境への対応で工数が破綻する事故を防ぐ。 | H2: swebok-v4a.pdf ch07 Software Maintenance > 3.2.2 Planning Activities(Scope of software maintenance) | I2: CORE | J2: 原則適用。案件スコープ・成果物・規制・リスク上非該当の場合はN/A根拠を記録。 | K2: SRC-SWEBOK-V4A
A3: MNT-002 | B3: SWEBOK | C3: 1. 保守計画(MNT-001〜) | D3: Critical | E3: 保守体制と役割が定義されている | F3: 窓口、一次対応、改修担当、承認者、エスカレーション経路が個人名または役割名で列挙されている | G3: 受付から承認までの役割が不明確だと、MR が宙に浮いたまま放置されたり、権限のない担当が独断でリリースして障害を招く。エスカレーション経路の欠落は重大障害時の初動遅延に直結する。 | H3: swebok-v4a.pdf ch07 Software Maintenance > 3.2.2 Planning Activities(Identification of the maintenance organization)/ 2.2.5 Organizational Aspects of Maintenance | I3: CORE | J3: 原則適用。案件スコープ・成果物・規制・リスク上非該当の場合はN/A根拠を記録。 | K3: SRC-SWEBOK-V4A
A4: MNT-003 | B4: SWEBOK | C4: 1. 保守計画(MNT-001〜) | D4: High | E4: 開発兼任か専任保守チームかの体制選択が根拠付きで記述されている | F4: 体制形態とその選定理由(知識継承・要員コスト等のトレードオフ)が1段落以上ある | G4: 開発兼任は新規開発の中断や退職時の知識喪失、専任保守は要員の離職リスクと引き継ぎ摩擦という各々の欠点を持つ。根拠なき体制選択は後から知識継承の破綻として表面化するため、トレードオフの明文化を求める。 | H4: swebok-v4a.pdf ch07 Software Maintenance > 2.2.5 Organizational Aspects of Maintenance | I4: CORE | J4: 原則適用。案件スコープ・成果物・規制・リスク上非該当の場合はN/A根拠を記録。 | K4: SRC-SWEBOK-V4A
A5: MNT-004 | B5: SWEBOK | C5: 1. 保守計画(MNT-001〜) | D5: Critical | E5: MR/PR の受付フローが定義されている | F5: 起票→トリアージ→承認→実装→リリースの各段階と、各段階の責任者・却下基準が図または箇条書きで示されている | G5: MR/PR の受付〜リリースの流れが未定義だと、口頭依頼による無記録変更や、トリアージなしの場当たり対応が常態化し、変更の追跡不能・品質低下を招く。 | H5: swebok-v4a.pdf ch07 Software Maintenance > 2.1.3 Impact Analysis(MR/PR の提出手続き・識別スキーム)/ 3.2 Software Maintenance Activities and Tasks | I5: CORE | J5: 原則適用。案件スコープ・成果物・規制・リスク上非該当の場合はN/A根拠を記録。 | K5: SRC-SWEBOK-V4A
A6: MNT-005 | B6: SWEBOK | C6: 1. 保守計画(MNT-001〜) | D6: High | E6: 計画の4階層(事業計画/保守計画/リリース計画/MR計画)の対応が示されている | F6: 上位計画への参照(文書名・版)があり、リリースサイクルと MR 処理の関係が記述されている | G6: SWEBOK は事業計画・保守計画・リリース計画・MR 計画の4階層の計画を求めている。上位計画との対応がないと、個々の MR 対応がリリースサイクルや予算と整合せず、場当たりリリースや予算超過を招く。 | H6: swebok-v4a.pdf ch07 Software Maintenance > 3.2.2 Planning Activities(Business/Maintenance/Release/MR planning) | I6: CORE | J6: 原則適用。案件スコープ・成果物・規制・リスク上非該当の場合はN/A根拠を記録。 | K6: SRC-SWEBOK-V4A
A7: MNT-006 | B7: SWEBOK | C7: 1. 保守計画(MNT-001〜) | D7: High | E7: コスト計画に保守固有の費目が含まれている | F7: 人件費に加え、教育訓練・SEE(ソフトウェア技術環境)維持費・ライセンス費のうち該当するものが計上され、対象外費目は理由が書かれている | G7: 保守コストは人件費以外に教育訓練・SEE 維持・ライセンス等の固有費目を含む。これらを見落とすと年度途中でツール更新費やライセンス更改費が捻出できず、保守基盤自体が陳腐化する。 | H7: swebok-v4a.pdf ch07 Software Maintenance > 2.3.2 Maintenance Cost Estimation(ISO/IEC/IEEE 14764 のコスト要素) | I7: CORE | J7: 原則適用。案件スコープ・成果物・規制・リスク上非該当の場合はN/A根拠を記録。 | K7: SRC-SWEBOK-V4A;SRC-ISO-GENERAL | L7: COST
A8: MNT-007 | B8: SWEBOK | C8: 1. 保守計画(MNT-001〜) | D8: Medium | E8: 保守要員の教育・引き継ぎ計画がある | F8: 新規参画者向けの習熟項目(システム理解・ツール・手順)と期間が定義されている | G8: 初期開発者が去った後に参画する保守者は理解ゼロから始まる。習熟計画がないと属人化した知識が引き継がれず、単純な修正にも過大な調査工数がかかり続ける。 | H8: swebok-v4a.pdf ch07 Software Maintenance > 1.2 Nature of Software Maintenance(開発者不在後の参画課題)/ 2.2.2 Staffing | I8: CORE | J8: 原則適用。案件スコープ・成果物・規制・リスク上非該当の場合はN/A根拠を記録。 | K8: SRC-SWEBOK-V4A
A9: MNT-008 | B9: SWEBOK | C9: 1. 保守計画(MNT-001〜) | D9: Medium | E9: 計画の改定条件と改定履歴がある | F9: 改定トリガー(体制変更・SLA 改定等)が列挙され、改定履歴表に版・日付・変更概要がある | G9: 保守は廃棄まで続く長期活動であり、体制や SLA の変化に計画が追随しないと文書と実態が乖離し、監査や引き継ぎ時に「どれが正か」不明になる。改定条件の明示で計画の陳腐化を防ぐ。 | H9: swebok-v4a.pdf ch07 Software Maintenance > 3.2.2 Planning Activities(保守フェーズは廃棄まで継続)/ 実務補完(文書管理の一般慣行) | I9: CORE | J9: 原則適用。案件スコープ・成果物・規制・リスク上非該当の場合はN/A根拠を記録。 | K9: SRC-SWEBOK-V4A;SRC-PRACTICE
A10: MNT-009 | B10: SWEBOK | C10: 1. 保守計画(MNT-001〜) | D10: High | E10: 保守ヘルプデスク/問い合わせ窓口の運用が定義されている | F10: 受付チャネル、受付時間、問い合わせと MR/PR 起票の関係が記述されている | G10: SWEBOK はヘルプデスクを MR の評価・優先度付け・コスト見積りを起動する保守固有の機能と位置付ける。窓口運用が未定義だと問い合わせが MR に変換されず、利用者の問題が黙殺される。 | H10: swebok-v4a.pdf ch07 Software Maintenance > 3.2 Software Maintenance Activities and Tasks(Maintenance help desk) | I10: CORE | J10: 原則適用。案件スコープ・成果物・規制・リスク上非該当の場合はN/A根拠を記録。 | K10: SRC-SWEBOK-V4A
A11: MNT-020 | B11: SWEBOK | C11: 2. 保守区分と MR/PR 管理(MNT-020〜) | D11: Critical | E11: 保守区分の定義が標準に準拠している | F11: 是正/予防/適応/追加/完全化(+緊急)の区分、または ISO/IEC/IEEE 14764 の修正/拡張の大別が定義され、独自区分には標準区分との対応がある | G11: 是正/予防/適応/追加/完全化(+緊急)の標準区分がないと、修正と拡張が混在した報告になり「保守=バグ修正」という誤解のもとで是正コストが過大評価され、予算配分判断を誤る。 | H11: swebok-v4a.pdf ch07 Software Maintenance > 1.6 Categories of Software Maintenance(ISO/IEC/IEEE 14764 の Corrections/Enhancements 大別) | I11: CORE | J11: 原則適用。案件スコープ・成果物・規制・リスク上非該当の場合はN/A根拠を記録。 | K11: SRC-SWEBOK-V4A;SRC-ISO-GENERAL
A12: MNT-021 | B12: SWEBOK | C12: 2. 保守区分と MR/PR 管理(MNT-020〜) | D12: Critical | E12: 各 MR/PR に保守区分が付与されている | F12: レビュー対象の MR/PR 記録の全件に区分が記録され、未分類が0件である | G12: 区分未付与の MR が混じると区分別の工数集計・コスト傾向分析が成立せず、保守投資の説明責任が果たせない。全件分類の徹底が測定・改善の前提になる。 | H12: swebok-v4a.pdf ch07 Software Maintenance > 1.6 Categories of Software Maintenance / 2.3 Software Maintenance Costs(区分別コスト提示) | I12: CORE | J12: 原則適用。案件スコープ・成果物・規制・リスク上非該当の場合はN/A根拠を記録。 | K12: SRC-SWEBOK-V4A
A13: MNT-022 | B13: SWEBOK | C13: 2. 保守区分と MR/PR 管理(MNT-020〜) | D13: Critical | E13: MR/PR の受理/却下の判断と根拠が記録されている | F13: 判断結果・判断者・日付・根拠が全件に記録されている | G13: 受理/却下の判断根拠が残らないと、却下された要求が繰り返し起票されたり、後日「なぜ対応しなかったのか」を説明できず利用者との信頼を失う。 | H13: swebok-v4a.pdf ch07 Software Maintenance > 3.2 Software Maintenance Activities and Tasks(MR acceptance/rejection) | I13: CORE | J13: 原則適用。案件スコープ・成果物・規制・リスク上非該当の場合はN/A根拠を記録。 | K13: SRC-SWEBOK-V4A
A14: MNT-023 | B14: SWEBOK | C14: 2. 保守区分と MR/PR 管理(MNT-020〜) | D14: High | E14: 優先度付けの基準が定義され適用されている | F14: 優先度の段階と判定基準(影響利用者数・業務停止有無等)が定義され、各 MR に優先度が付与されている | G14: 優先度基準がないと声の大きい依頼者の MR が先に処理され、業務影響の大きい問題が後回しになる。SWEBOK も PR の重大度を対応順序の指針とすることを求めている。 | H14: swebok-v4a.pdf ch07 Software Maintenance > 2.1.3 Impact Analysis(categorizing and prioritizing MRs/PRs、PR severity) | I14: CORE | J14: 原則適用。案件スコープ・成果物・規制・リスク上非該当の場合はN/A根拠を記録。 | K14: SRC-SWEBOK-V4A
A15: MNT-024 | B15: SWEBOK | C15: 2. 保守区分と MR/PR 管理(MNT-020〜) | D15: Critical | E15: 緊急保守に恒久対処の MR が紐付いている | F15: 緊急(一時対処)と記録された変更の全件に、恒久対処 MR の ID 参照または「一時対処で完結する根拠」がある | G15: 緊急保守は「是正保守までの一時しのぎ」であり、暫定対処が恒久化すると隠れた欠陥と技術的負債が蓄積する。ワークアラウンドを除去まで追跡することが標準の要求である。 | H15: swebok-v4a.pdf ch07 Software Maintenance > 1.6 Categories(Emergency maintenance)/ 2.1.3 Impact Analysis(work-around の除去までの追跡) | I15: CORE | J15: 原則適用。案件スコープ・成果物・規制・リスク上非該当の場合はN/A根拠を記録。 | K15: SRC-SWEBOK-V4A
A16: MNT-025 | B16: SWEBOK | C16: 2. 保守区分と MR/PR 管理(MNT-020〜) | D16: Medium | E16: MR/PR に起票者・受理日・完了日が記録されている | F16: 全件に3項目が揃っており、処理時間(リードタイム)が算出可能である | G16: 起票日・完了日がないと MR あたりの処理時間が算出できず、SLA 遵守の証明も傾向分析による改善もできなくなる。 | H16: swebok-v4a.pdf ch07 Software Maintenance > 2.4 Software Maintenance Measurement(期間別 MR 件数・MR あたり工数) | I16: CORE | J16: 原則適用。案件スコープ・成果物・規制・リスク上非該当の場合はN/A根拠を記録。 | K16: SRC-SWEBOK-V4A
A17: MNT-026 | B17: SWEBOK | C17: 2. 保守区分と MR/PR 管理(MNT-020〜) | D17: Medium | E17: 却下された MR/PR が起票者へフィードバックされる手順がある | F17: 却下時の通知方法と再申請の可否が手順として定義されている | G17: 却下のフィードバックがないと利用者は要求が握り潰されたと感じ、正規窓口を迂回した非公式依頼が増えて SCM 外の変更を誘発する。SWEBOK も利用者へのフォローアップフィードバックの決定を求める。 | H17: swebok-v4a.pdf ch07 Software Maintenance > 2.1.3 Impact Analysis(follow-up feedback to users) | I17: CORE | J17: 原則適用。案件スコープ・成果物・規制・リスク上非該当の場合はN/A根拠を記録。 | K17: SRC-SWEBOK-V4A
A18: MNT-040 | B18: SWEBOK | C18: 3. 影響分析(MNT-040〜) | D18: Critical | E18: 変更内容と変更理由が記述されている | F18: 何を・なぜ変えるかが第三者に伝わる文章で書かれ、対象 MR/PR の ID が参照されている | G18: 変更要求はまずソフトウェアの言葉に翻訳・分析される必要がある。何を・なぜ変えるかが書かれていないと、影響分析もレビューも対象を誤り、意図と異なる改修が実装される。 | H18: swebok-v4a.pdf ch07 Software Maintenance > 2.1.3 Impact Analysis(change request の分析と翻訳) | I18: CORE | J18: 原則適用。案件スコープ・成果物・規制・リスク上非該当の場合はN/A根拠を記録。 | K18: SRC-SWEBOK-V4A
A19: MNT-041 | B19: SWEBOK | C19: 3. 影響分析(MNT-040〜) | D19: Critical | E19: 影響範囲がモジュール/データ/インタフェース/ドキュメント/他システムの観点で特定されている | F19: 5観点それぞれについて影響の有無と対象一覧が記載され、「影響なし」にも判断根拠がある | G19: 影響分析は変更で影響を受ける「すべてのシステムとソフトウェア製品」の特定を求める。観点漏れ(特に他システム・ドキュメント)は、リリース後の連携障害や文書と実装の乖離として跳ね返る。 | H19: swebok-v4a.pdf ch07 Software Maintenance > 2.1.3 Impact Analysis | I19: CORE | J19: 原則適用。案件スコープ・成果物・規制・リスク上非該当の場合はN/A根拠を記録。 | K19: SRC-SWEBOK-V4A
... A28: MNT-060 | B28: SWEBOK | C28: 4. 保守性と技術的負債(MNT-060〜) | D28: Critical | E28: 技術的負債管理台帳の各項目が具体的箇所に紐付いている | F28: 全項目にファイル/モジュール/コンポーネント名または計測レポートへの参照があり、根拠のない項目が0件である | G28: 具体箇所に紐付かない負債項目(「コードが汚い」等)は返済作業に着手できず、台帳が愚痴リストと化す。ツール計測や箇所特定により返済可能な単位で管理させる。 | H28: swebok-v4a.pdf ch07 Software Maintenance > 2.3.1 Technical Debt Cost Estimation(サイズ・複雑度・違反数等の指標による計測) | I28: CORE | J28: 原則適用。案件スコープ・成果物・規制・リスク上非該当の場合はN/A根拠を記録。 | K28: SRC-SWEBOK-V4A
A29: MNT-061 | B29: SWEBOK | C29: 4. 保守性と技術的負債(MNT-060〜) | D29: Critical | E29: 各負債に放置リスクと返済コスト見積りが付与されている | F29: 全項目にリスク記述と工数または規模の見積りがある | G29: SWEBOK は「現在の品質・負債の程度・品質向上投資の節約効果・事業影響」の把握を求める。リスクと返済コストがないと投資対効果を比較できず、負債返済は永遠に新機能に負ける。 | H29: swebok-v4a.pdf ch07 Software Maintenance > 2.3.1 Technical Debt Cost Estimation | I29: CORE | J29: 原則適用。案件スコープ・成果物・規制・リスク上非該当の場合はN/A根拠を記録。 | K29: SRC-SWEBOK-V4A | L29: COST
A30: MNT-062 | B30: SWEBOK | C30: 4. 保守性と技術的負債(MNT-060〜) | D30: High | E30: 負債の分類が定義され適用されている | F30: コード・設計・テスト・ドキュメント・インフラ等の分類が定義され、全項目に付与されている | G30: 負債の分類がないと、コード品質の問題とプロセス・チームの問題が混同され、対処先を誤る。SWEBOK も負債を単独でなく根本原因の検討とともに扱うことを求める。 | H30: swebok-v4a.pdf ch07 Software Maintenance > 2.3.1 Technical Debt Cost Estimation(根本原因の検討)/ 実務補完(負債分類の実務慣行) | I30: CORE | J30: 原則適用。案件スコープ・成果物・規制・リスク上非該当の場合はN/A根拠を記録。 | K30: SRC-SWEBOK-V4A;SRC-PRACTICE
A31: MNT-063 | B31: SWEBOK | C31: 4. 保守性と技術的負債(MNT-060〜) | D31: High | E31: 負債の計測方法が定義されている | F31: 静的解析・品質評価ツールの名称と計測指標(複雑度・重複・違反数・カバレッジ等)が明記されている | G31: 計測方法が未定義だと負債の増減が判定できず、返済活動の効果を示せない。複雑度・違反数などツールで取得可能な指標の明示が改善サイクルの前提になる。 | H31: swebok-v4a.pdf ch07 Software Maintenance > 2.3.1 Technical Debt Cost Estimation / 2.4 Software Maintenance Measurement(複雑度・技術的負債の計測ツール) | I31: CORE | J31: 原則適用。案件スコープ・成果物・規制・リスク上非該当の場合はN/A根拠を記録。 | K31: SRC-SWEBOK-V4A
A32: MNT-064 | B32: SWEBOK | C32: 4. 保守性と技術的負債(MNT-060〜) | D32: High | E32: 優先順位付けの基準がある | F32: 優先度の決め方(リスク×返済コスト等)が定義され、全項目に優先度がある | G32: 「すべての技術的負債が緊急ではない」— 関連性・組織目標との整合を無視した一律返済は投資の無駄になる。優先順位基準により、事業影響の大きい負債から返済させる。 | H32: swebok-v4a.pdf ch07 Software Maintenance > 2.1.4 Maintainability(Code quality versus relevance / Alignment with organizational objectives) | I32: CORE | J32: 原則適用。案件スコープ・成果物・規制・リスク上非該当の場合はN/A根拠を記録。 | K32: SRC-SWEBOK-V4A
A33: MNT-065 | B33: SWEBOK | C33: 4. 保守性と技術的負債(MNT-060〜) | D33: Medium | E33: 台帳に状態と日付が管理されている | F33: 全項目に状態(未着手/計画済/返済済等)と起票日・更新日がある | G33: 状態・日付のない台帳は返済の進捗が見えず、Lehman の法則が示す「対処しなければ複雑さは増大し続ける」状況を放置しているのと同じになる。 | H33: swebok-v4a.pdf ch07 Software Maintenance > 1.5 Evolution of Software(Increasing Complexity)/ 実務補完(台帳管理の実務) | I33: CORE | J33: 原則適用。案件スコープ・成果物・規制・リスク上非該当の場合はN/A根拠を記録。 | K33: SRC-SWEBOK-V4A;SRC-PRACTICE
A34: MNT-066 | B34: SWEBOK | C34: 4. 保守性と技術的負債(MNT-060〜) | D34: High | E34: 保守性が ISO/IEC 25010 の特性で評価されている | F34: モジュール性・再利用性・解析性・修正性・試験性のうち評価対象とした特性と評価方法が明記されている | G34: 保守性は「修正されうる能力」として開発中から仕様化・レビュー・統制すべき品質特性であり、モジュール性・解析性等の計測可能な特性で評価しないと、保守性の劣化に気付けない。 | H34: swebok-v4a.pdf ch07 Software Maintenance > 2.1.4 Maintainability / 2.4 Software Maintenance Measurement(Modularity/Reusability/Analyzability/Modifiability/Testability) | I34: CORE | J34: 原則適用。案件スコープ・成果物・規制・リスク上非該当の場合はN/A根拠を記録。 | K34: SRC-SWEBOK-V4A
A35: MNT-067 | B35: SWEBOK | C35: 4. 保守性と技術的負債(MNT-060〜) | D35: Medium | E35: 新規開発・改修時に負債を作り込まないための基準への参照がある | F35: コーディング規約・静的解析ゲート・レビュー基準など予防策への参照が記載されている | G35: 負債は時間制約下の即席対応・レビュー省略から蓄積する。ISO/IEC/IEEE 14764 が挙げる可読性確保・複雑度低減・インスペクション等の予防策への参照がないと、返済と同じ速度で新規負債が作られる。 | H35: swebok-v4a.pdf ch07 Software Maintenance > 2.3.1 Technical Debt Cost Estimation(14764 の保守性向上策) | I35: CORE | J35: 原則適用。案件スコープ・成果物・規制・リスク上非該当の場合はN/A根拠を記録。 | K35: SRC-SWEBOK-V4A
A36: MNT-080 | B36: SWEBOK | C36: 5. リファクタリング(MNT-080〜) | D36: Critical | E36: 「外部から見た振る舞いを変えない」ことの保証方法が定義されている | F36: 既存テストの網羅状況の確認結果、不足時の特性テスト追加計画が記述されている | G36: リファクタリングの定義は「振る舞いを変えずに再構成する」ことであり、その保証はテストしかない。テスト不備のまま実施すると、改善のつもりの変更がデグレードとして本番に届く。 | H36: swebok-v4a.pdf ch07 Software Maintenance > 4.2 Software Reengineering(Refactoring)/ 2.1.2 Testing | I36: CORE | J36: 原則適用。案件スコープ・成果物・規制・リスク上非該当の場合はN/A根拠を記録。 | K36: SRC-SWEBOK-V4A
A37: MNT-081 | B37: SWEBOK | C37: 5. リファクタリング(MNT-080〜) | D37: Critical | E37: 機能変更とリファクタリングが分離されている | F37: 計画・コミット・MR のいずれの単位でも両者が混在せず、混在があれば Fail | G37: 機能変更とリファクタリングが混在すると、障害発生時にどちらが原因か切り分けられず、レビューも回帰テスト範囲の判断も困難になる。振る舞い不変の検証可能性を守るための分離である。 | H37: swebok-v4a.pdf ch07 Software Maintenance > 4.2 Software Reengineering(Refactoring の定義)/ 実務補完(Fowler のリファクタリング原則) | I37: CORE | J37: 原則適用。案件スコープ・成果物・規制・リスク上非該当の場合はN/A根拠を記録。 | K37: SRC-SWEBOK-V4A;SRC-PRACTICE
A38: MNT-082 | B38: SWEBOK | C38: 5. リファクタリング(MNT-080〜) | D38: High | E38: 対象範囲と現状の問題が計測値で示されている | F38: 対象コードの複雑度・重複率等の現状値、または具体的なコード箇所と問題の記述がある | G38: 現状の計測値がないと「何が問題で着手するのか」が主観になり、完了後の改善も示せない。負債返済の投資判断には現状品質の定量把握が必要である。 | H38: swebok-v4a.pdf ch07 Software Maintenance > 2.3.1 Technical Debt Cost Estimation(現在の品質・負債程度の把握) | I38: CORE | J38: 原則適用。案件スコープ・成果物・規制・リスク上非該当の場合はN/A根拠を記録。 | K38: SRC-SWEBOK-V4A
A39: MNT-083 | B39: SWEBOK | C39: 5. リファクタリング(MNT-080〜) | D39: High | E39: 完了判定基準が検証可能である | F39: 計測値の目標(例: 複雑度の上限)と回帰テスト全通過が完了条件として明記されている | G39: 完了基準が曖昧なリファクタリングは際限なく続くか中途半端に終わり、費やした工数の正当性を示せない。目標値と回帰テスト全通過という検証可能な条件で「終わり」を定義させる。 | H39: swebok-v4a.pdf ch07 Software Maintenance > 4.2 Software Reengineering / 2.4 Software Maintenance Measurement | I39: CORE | J39: 原則適用。案件スコープ・成果物・規制・リスク上非該当の場合はN/A根拠を記録。 | K39: SRC-SWEBOK-V4A
A40: MNT-084 | B40: SWEBOK | C40: 5. リファクタリング(MNT-080〜) | D40: High | E40: 小さな単位に分割した実施ステップがある | F40: 各ステップ完了時にテストが通る状態を保つ分割になっている | G40: 大きな一括変更は失敗時の切り分けと切戻しが困難になる。CI の文脈での継続的リファクタリングのように、常にテストが通る小さなステップに分割することで、途中中断してもリリース可能な状態を保つ。 | H40: swebok-v4a.pdf ch07 Software Maintenance > 4.2 Software Reengineering(継続的リファクタリングと CI) | I40: CORE | J40: 原則適用。案件スコープ・成果物・規制・リスク上非該当の場合はN/A根拠を記録。 | K40: SRC-SWEBOK-V4A
A41: MNT-085 | B41: SWEBOK | C41: 5. リファクタリング(MNT-080〜) | D41: Medium | E41: 技術的負債管理台帳の項目と対応付いている | F41: 対応する負債 ID が参照されている(台帳が存在しない場合は N/A とし根拠を記す) | G41: 台帳と紐付かないリファクタリングは「なぜやるのか」の説明責任を欠き、負債側から見ると返済実績が記録されず台帳が実態と乖離する。 | H41: swebok-v4a.pdf ch07 Software Maintenance > 2.3.1 Technical Debt Cost Estimation / 実務補完(負債台帳との追跡) | I41: CORE | J41: 原則適用。案件スコープ・成果物・規制・リスク上非該当の場合はN/A根拠を記録。 | K41: SRC-SWEBOK-V4A;SRC-PRACTICE
... A47: MNT-104 | B47: SWEBOK | C47: 6. テスト・検証(MNT-100〜) | D47: Medium | E47: 本番相当環境での検証の要否が判定されている | F47: 稼働中システムを止められない制約下でのテスト環境(検証環境・データ)の方針が記述されている | G47: 重要機能を担うソフトはテストのためにオフラインにできないという保守固有の制約がある。本番相当環境の方針がないと、本番でしか再現しない問題を検証できず一発勝負のリリースになる。 | H47: swebok-v4a.pdf ch07 Software Maintenance > 2.1.2 Testing(稼働中ソフトをオフラインにする困難) | I47: CORE | J47: 原則適用。案件スコープ・成果物・規制・リスク上非該当の場合はN/A根拠を記録。 | K47: SRC-SWEBOK-V4A
A48: MNT-105 | B48: SWEBOK | C48: 6. テスト・検証(MNT-100〜) | D48: Medium | E48: 脆弱性評価が保守サイクルに組み込まれている | F48: 依存ライブラリの脆弱性スキャンまたはセキュリティ評価の実施頻度・方法が定義されている | G48: SWEBOK は保守者の継続活動に脆弱性評価を明記し、保守の目的にセキュリティ脅威の予防を含める。定期スキャンがないと、既知脆弱性を抱えた依存ライブラリが放置され、攻撃可能な状態が継続する。 | H48: swebok-v4a.pdf ch07 Software Maintenance > 3.2.1 Supporting and Monitoring Activities(vulnerability assessments)/ 1.3 Need for Software Maintenance(Prevent security threats) | I48: CORE | J48: 原則適用。案件スコープ・成果物・規制・リスク上非該当の場合はN/A根拠を記録。 | K48: SRC-SWEBOK-V4A | L48: SEC-SUPPLY-CHAIN
A49: MNT-903 | B49: 追加承認 | C49: 6. テスト・検証(MNT-100〜) | D49: Medium | E49: ビルド・リリース・デプロイの自動化状況が把握され、方針が定義されている | F49: ビルド/ステージング配備/本番デプロイの各工程について自動/手動の別が記録され、手動工程には自動化しない理由または自動化計画がある | G49: 小さな変更が高頻度に発生する保守では、手動デプロイは作業ミスによるリリース事故と リードタイム悪化の主要因になる。自動化状況の可視化により信頼性と処理速度の改善余地を特定する。 | H49: swebok-v4a.pdf ch07 Software Maintenance > 4.4 Continuous Delivery / Continuous Deployment(リリース・デプロイの自動化) | I49: CORE | J49: 原則適用。案件スコープ・成果物・規制・リスク上非該当の場合はN/A根拠を記録。 | K49: SRC-SWEBOK-V4A
A50: MNT-120 | B50: SWEBOK | C50: 7. 構成管理・リリース(MNT-120〜) | D50: Critical | E50: すべての変更が SCM プロセス(識別・承認・実装・リリース)を通っている | F50: SCM 外の直接変更(本番直接修正等)が0件、または発生時の事後登録手順が定義され実績が記録されている | G50: 「MR/PR の追跡だけでは不十分で、製品と基盤へのあらゆる変更が統制されなければならない」が標準の要求。SCM 外の本番直接修正は、構成の実態不明化と再現不能な障害の温床になる。 | H50: swebok-v4a.pdf ch07 Software Maintenance > 3.2.3 Configuration Management | I50: CORE | J50: 原則適用。案件スコープ・成果物・規制・リスク上非該当の場合はN/A根拠を記録。 | K50: SRC-SWEBOK-V4A
A51: MNT-121 | B51: SWEBOK | C51: 7. 構成管理・リリース(MNT-120〜) | D51: Critical | E51: リリースと MR/PR の双方向追跡が可能である | F51: 任意のリリースノートから含まれる MR/PR に、任意の MR から反映リリースに到達できる | G51: SCM は識別・承認・実装・リリースの各段階の検証・監査可能性を求める。リリースと MR の双方向追跡が切れると、障害時に「この不具合はどの変更で入ったか」を特定できず原因調査が長期化する。 | H51: swebok-v4a.pdf ch07 Software Maintenance > 3.2.3 Configuration Management / 3.2 Activities and Tasks(要求の追跡) | I51: CORE | J51: 原則適用。案件スコープ・成果物・規制・リスク上非該当の場合はN/A根拠を記録。 | K51: SRC-SWEBOK-V4A
